Workbook

Sheet Getting Started - FAQ
A1: Getting started and FAQ
A3: Sales Invoices, IR35 and VAT
A4: IR35 Status: Enter Y or N in the yellow IR35 question box (cell E9).
A6: VAT Status: Enter Y or N in the yellow VAT question box. If you are using the VAT flat rate scheme then enter the scheme percentage into cell E12 on Month 1. Please contact your Accountant if you require further information about the Flat Rate VAT Scheme.
A8: Sales - enter your gross (i.e. including VAT if applicable) figure into the gross column. If you entered either Y or N in the IR35 question box, the other entries will be completed automatically for you.
A10: Banked Receipts
A11: Opening Bank Balances: Enter the opening bank balances only in cells K10 and K11 of Month 1. These balances should be taken from your last Company accounts (not applicable for first company year).
A13: The bankings section is used to record money received into the company bank accounts as follows:
A14: From Sales - money you receive from your agent or client.
A15: Interest Received on Current Account - interest received on the current account.
A16: Other Bankings - other money paid into the Company current account for example refunds, loans from the director to the company, etc.
A17: Transfers From Deposit Account - transfers you make back into your current account from the deposit account.
... A48: If you have any questions relating to the completion of your spreadsheet please do not hesitate to contact your Accountant.

Sheet Example
A2: Company name Ltd
A4: Month | C4: 42095
A7: Sales Invoices | I7: Bankings
A9: Does this months income fall within IR35? (Y/N/both) | E9: n | F9: =IF(E9="Both","enter sales invoices manually at row 30 onwards",0) -> 0
I10: Opening Bank Balance: | J10: Current Account | K10: 0
A11: Is the Company VAT registered (Y/N) | E11: y | I11: (if overdrawn enter a | J11: Deposit Account | K11: 0
A12: VAT Flat rate scheme percentage (leave blank or zero if not using flat rate scheme) | E12: 0 | I12: negative figure)
L13: Interest | N13: Transfers | O13: Interest
C14: Inv | K14: From | L14: Received on | N14: From | O14: Received on
A15: Date | B15: Details | C15: No | D15: IR35 | E15: Non IR35 | F15: Gross | G15: VAT | I15: Date | J15: Details | K15: Sales | L15: Current Account | M15: Other bankings | N15: Deposit Account | O15: Deposit Account
C16: Balance b/f | D16: 0 | E16: 0 | F16: 0 | G16: 0 | J16: Bal b/f
A17: 42101 | B17: First Agency Ltd | C17: 25 | E17: =F17-G17 -> 5500 | F17: 6600 | G17: =F17*1/6 -> 1100 | I17: 42113 | J17: First Agency | K17: 6600
A18: 42103 | B18: First Agency Ltd | C18: 26 | E18: =F18-G18 -> 4500 | F18: 5400 | G18: =F18*1/6 -> 900 | I18: 42120 | J18: Interest Received | L18: 7.5
D19: 0 | E19: 0 | G19: =F19*1/6 -> 0 | I19: 42121 | J19: Trf from Dep Ac | N19: 2000
A20: 42109 | B20: Inv 27 - raised without VAT | C20: Z27 | D20: 0 | E20: =F20-G20 -> 2500 | F20: 2500 | I20: 42122 | J20: Int on Dep Ac | O20: 16
A21: 42124 | B21: VAT Only Invoice for Inv 27 | C21: V28 | D21: 0 | F21: 500 | G21: 500
D22: =IF(E9="y",F22-G22,0) -> 0 | E22: =IF(E9="y",,F22-G22) -> 0 | F22: 0 | G22: =F22*1/6 -> 0
D23: =IF(E9="y",F23-G23,0) -> 0 | E23: =IF(E9="y",,F23-G23) -> 0 | G23: =F23*1/6 -> 0
D24: =IF(E9="y",F24-G24,0) -> 0 | E24: =IF(E9="y",,F24-G24) -> 0 | F24: 0 | G24: =F24*1/6 -> 0
D25: =IF(E9="y",F25-G25,0) -> 0 | E25: =IF(E9="y",,F25-G25) -> 0 | G25: =F25*1/6 -> 0
D26: =IF(E9="y",F26-G26,0) -> 0 | E26: =IF(E9="y",,F26-G26) -> 0 | G26: =F26*1/6 -> 0
D27: =IF(E9="y",F27-G27,0) -> 0 | E27: =IF(E9="y",,F27-G27) -> 0 | G27: =F27*1/6 -> 0
D28: =IF(E9="y",F28-G28,0) -> 0 | E28: =IF(E9="y",,F28-G28) -> 0 | G28: =F28*1/6 -> 0
D29: =IF(E9="y",F29-G29,0) -> 0 | E29: =IF(E9="y",,F29-G29) -> 0 | F29: 0 | G29: =F29*1/6 -> 0
B30: =IF(E9="Both","Enter manual values here",0) -> 0 | E30: 0 | F30: 0 | G30: =F30*1/6 -> 0
D31: 0 | F31: 0 | G31: =F31*1/6 -> 0
D32: 0 | F32: 0 | G32: =F32*1/6 -> 0
D33: 0 | F33: 0 | G33: =F33*1/6 -> 0
G34: =F34*1/6 -> 0
G35: =F35*1/6 -> 0
G36: =F36*1/6 -> 0
G37: =F37*1/6 -> 0
G38: =F38*1/6 -> 0
G39: =F39*1/6 -> 0
G40: =F40*1/6 -> 0
G41: =F41*1/6 -> 0
A42: Total | D42: =SUM(D17:D41) -> 0 | E42: =SUM(E17:E41) -> 12500 | F42: =SUM(F17:F41) -> 15000 | G42: =SUM(G17:G41) -> 2500 | I42: Total | K42: =SUM(K16:K41) -> 6600 | L42: =SUM(L16:L41) -> 7.5 | M42: =SUM(M16:M41) -> 0 | N42: =SUM(N16:N41) -> 2000 | O42: =SUM(O16:O41) -> 16
A43: C/fwd | D43: =SUM(D16:D41) -> 0 | E43: =SUM(E16:E41) -> 12500 | F43: =SUM(F16:F41) -> 15000 | G43: =SUM(G16:G41) -> 2500 | I43: C/fwd | K43: =SUM(K16:K41) -> 6600 | L43: =SUM(L16:L41) -> 7.5 | M43: =SUM(M16:M41) -> 0 | N43: =SUM(N16:N41) -> 2000 | O43: =SUM(O16:O41) -> 16
A63: Expenditure
I65: Travelling, | J65: Professional, Employers | R65: Assets Purchased: | T65: Subscriptions,
D66: Company | E66: Cash | F66: Company | H66: Motor Expenses | I66: Accommodation | J66: and Public | K66: Company | M66: PAYE & National Ins | O66: Cost of | P66: Printing, postage & | Q66: Internet & | R66: Computer Hardware | S66: Computer related | T66: Books & | V66: Bank Charges and | W66: Use of | X66: Transfers to | Y66: VAT paid to | Z66: Corporation Tax | AA66: Directors | AB66: Business
A67: Date | B67: Details | C67: Cheque No | D67: Bank | E67: Expenses | F67: Credit Card | G67: VAT | H67: or Mileage Claims | I67: & Subsistence | J67: Liability Insurance | K67: Pension | L67: Net salary paid | M67: paid to HMR&C | N67: Dividends | O67: Goods sold | P67: Stationery | Q67: Telephone | R67: and Office Equipment | S67: Costs | T67: Journals | U67: Accountancy | V67: Interest payable | W67: Home | X67: Deposit Account | Y67: HMC&E | Z67: paid to HMR&C | AA67: Loan Account | AB67: Entertainment | AC67: Sundries | AD67: error line?
A69: 07.04.14 | B69: Fixed mileage allowance 100 miles (VAT at 3p per mile) | E69: 45 | G69: 3 | H69: 42 | AD69: =SUM(G69:AC69) -> 45 | AE69: =SUM(D69:F69) -> 45 | AF69: =AD69-AE69 -> 0
A70: 09.04.14 | B70: Stationery | D70: 0 | E70: 12 | G70: 2 | H70: 0 | P70: 10 | AD70: =SUM(G70:AC70) -> 12 | AE70: =SUM(D70:F70) -> 12 | AF70: =AD70-AE70 -> 0
A71: 15.04.14 | B71: Mobile Phone | C71: 1 | D71: 120 | G71: 20 | M71: 0 | Q71: 100 | Y71: 0 | AD71: =SUM(G71:AC71) -> 120 | AE71: =SUM(D71:F71) -> 120 | AF71: =AD71-AE71 -> 0
A72: 17.04.14 | B72: Accommodation | C72: 2 | F72: 185 | I72: 185 | N72: 0 | AD72: =SUM(G72:AC72) -> 185 | AE72: =SUM(D72:F72) -> 185 | AF72: =AD72-AE72 -> 0
A73: 19.04.14 | B73: Flight | C73: 3 | F73: 235 | G73: 0 | I73: 235 | AD73: =SUM(G73:AC73) -> 235 | AE73: =SUM(D73:F73) -> 235 | AF73: =AD73-AE73 -> 0
A74: 25.04.14 | B74: Salary | C74: 4 | D74: 860 | L74: 860 | AD74: =SUM(G74:AC74) -> 860 | AE74: =SUM(D74:F74) -> 860 | AF74: =AD74-AE74 -> 0
A75: 25.04.14 | B75: Subscriptions | C75: 5 | D75: 72.5 | I75: 0 | T75: 72.5 | AD75: =SUM(G75:AC75) -> 72.5 | AE75: =SUM(D75:F75) -> 72.5 | AF75: =AD75-AE75 -> 0
A76: 27.04.14 | B76: Company Pension | D76: 1000 | K76: 1000 | AD76: =SUM(G76:AC76) -> 1000 | AE76: =SUM(D76:F76) -> 1000 | AF76: =AD76-AE76 -> 0
A77: 28.04.14 | B77: Accountancy | D77: 132 | G77: 22 | U77: 110 | AD77: =SUM(G77:AC77) -> 132 | AE77: =SUM(D77:F77) -> 132 | AF77: =AD77-AE77 -> 0
A78: 01.04.14 | B78: Transfer to Dep A/c | D78: 5000 | X78: 5000 | AD78: =SUM(G78:AC78) -> 5000 | AE78: =SUM(D78:F78) -> 5000 | AF78: =AD78-AE78 -> 0
B79: Expenses reclaimed | C79: 6 | D79: 57 | E79: -57 | AD79: =SUM(G79:AC79) -> 0 | AE79: =SUM(D79:F79) -> 0 | AF79: =AD79-AE79 -> 0
A80: 30.04.14 | B80: Payment to clear Credit Card | D80: 420 | F80: -420 | AD80: =SUM(G80:AC80) -> 0 | AE80: =SUM(D80:F80) -> 0 | AF80: =AD80-AE80 -> 0 | AJ80: =IF(AF80=0,0,"ERROR HERE") -> 0 | AK80: =IF(OR(ISERROR(+H80/($D80+$E80-$G80)*$G80+H80),LEFT(F80,1)="x"),0,+H80/($D80+$E80-$G80)*$G80+H80) -> 0 | AL80: =IF(OR(ISERROR(+I80/($D80+$E80-$G80)*$G80+I80),LEFT(G80,1)="x"),0,+I80/($D80+$E80-$G80)*$G80+I80) -> 0 | AM80: =IF(OR(ISERROR(+J80/($D80+$E80-$G80)*$G80+J80),LEFT(H80,1)="x"),0,+J80/($D80+$E80-$G80)*$G80+J80) -> 0 | AN80: =IF(OR(ISERROR(+K80/($D80+$E80-$G80)*$G80+K80),LEFT(I80,1)="x"),0,+K80/($D80+$E80-$G80)*$G80+K80) -> 0 | AO80: =IF(OR(ISERROR(+L80/($D80+$E80-$G80)*$G80+L80),LEFT(J80,1)="x"),0,+L80/($D80+$E80-$G80)*$G80+L80) -> 0 | AP80: =IF(OR(ISERROR(+M80/($D80+$E80-$G80)*$G80+M80),LEFT(K80,1)="x"),0,+M80/($D80+$E80-$G80)*$G80+M80) -> 0 | AQ80: =IF(OR(ISERROR(+N80/($D80+$E80-$G80)*$G80+N80),LEFT(L80,1)="x"),0,+N80/($D80+$E80-$G80)*$G80+N80) -> 0 | AR80: =IF(OR(ISERROR(+O80/($D80+$E80-$G80)*$G80+O80),LEFT(M80,1)="x"),0,+O80/($D80+$E80-$G80)*$G80+O80) -> 0 | ... BC80: =IF(OR(ISERROR(+Z80/($D80+$E80-$G80)*$G80+Z80),LEFT(X80,1)="x"),0,+Z80/($D80+$E80-$G80)*$G80+Z80) -> 0 | BD80: =IF(OR(ISERROR(+Y80/($D80+$E80-$G80)*$G80+Y80),LEFT(W80,1)="x"),0,+Y80/($D80+$E80-$G80)*$G80+Y80) -> 0 | BE80: =IF(OR(ISERROR(+Z80/($D80+$E80-$G80)*$G80+Z80),LEFT(X80,1)="x"),0,+Z80/($D80+$E80-$G80)*$G80+Z80) -> 0 | BF80: =IF(OR(ISERROR(+AA80/($D80+$E80-$G80)*$G80+AA80),LEFT(Y80,1)="x"),0,+AA80/($D80+$E80-$G80)*$G80+AA80) -> 0 | BI80: =IF(OR(ISERROR(+#REF!/($D80+$E80-$G80)*$G80+#REF!),LEFT(Z80,1)="x"),0,+#REF!/($D80+$E80-$G80)*$G80+#REF!) -> 0
AD81: =SUM(G81:AC81) -> 0 | AE81: =SUM(D81:F81) -> 0 | AF81: =AD81-AE81 -> 0 | AJ81: =IF(AF81=0,0,"ERROR HERE") -> 0 | AK81: =IF(OR(ISERROR(+H81/($D81+$E81-$G81)*$G81+H81),LEFT(F81,1)="x"),0,+H81/($D81+$E81-$G81)*$G81+H81) -> 0 | AL81: =IF(OR(ISERROR(+I81/($D81+$E81-$G81)*$G81+I81),LEFT(G81,1)="x"),0,+I81/($D81+$E81-$G81)*$G81+I81) -> 0 | AM81: =IF(OR(ISERROR(+J81/($D81+$E81-$G81)*$G81+J81),LEFT(H81,1)="x"),0,+J81/($D81+$E81-$G81)*$G81+J81) -> 0 | AN81: =IF(OR(ISERROR(+K81/($D81+$E81-$G81)*$G81+K81),LEFT(I81,1)="x"),0,+K81/($D81+$E81-$G81)*$G81+K81) -> 0 | AO81: =IF(OR(ISERROR(+L81/($D81+$E81-$G81)*$G81+L81),LEFT(J81,1)="x"),0,+L81/($D81+$E81-$G81)*$G81+L81) -> 0 | AP81: =IF(OR(ISERROR(+M81/($D81+$E81-$G81)*$G81+M81),LEFT(K81,1)="x"),0,+M81/($D81+$E81-$G81)*$G81+M81) -> 0 | AQ81: =IF(OR(ISERROR(+N81/($D81+$E81-$G81)*$G81+N81),LEFT(L81,1)="x"),0,+N81/($D81+$E81-$G81)*$G81+N81) -> 0 | AR81: =IF(OR(ISERROR(+O81/($D81+$E81-$G81)*$G81+O81),LEFT(M81,1)="x"),0,+O81/($D81+$E81-$G81)*$G81+O81) -> 0 | ... BC81: =IF(OR(ISERROR(+Z81/($D81+$E81-$G81)*$G81+Z81),LEFT(X81,1)="x"),0,+Z81/($D81+$E81-$G81)*$G81+Z81) -> 0 | BD81: =IF(OR(ISERROR(+Y81/($D81+$E81-$G81)*$G81+Y81),LEFT(W81,1)="x"),0,+Y81/($D81+$E81-$G81)*$G81+Y81) -> 0 | BE81: =IF(OR(ISERROR(+Z81/($D81+$E81-$G81)*$G81+Z81),LEFT(X81,1)="x"),0,+Z81/($D81+$E81-$G81)*$G81+Z81) -> 0 | BF81: =IF(OR(ISERROR(+AA81/($D81+$E81-$G81)*$G81+AA81),LEFT(Y81,1)="x"),0,+AA81/($D81+$E81-$G81)*$G81+AA81) -> 0 | BI81: =IF(OR(ISERROR(+#REF!/($D81+$E81-$G81)*$G81+#REF!),LEFT(Z81,1)="x"),0,+#REF!/($D81+$E81-$G81)*$G81+#REF!) -> 0
AD82: =SUM(G82:AC82) -> 0 | AE82: =SUM(D82:F82) -> 0 | AF82: =AD82-AE82 -> 0 | AJ82: =IF(AF82=0,0,"ERROR HERE") -> 0 | AK82: =IF(OR(ISERROR(+H82/($D82+$E82-$G82)*$G82+H82),LEFT(F82,1)="x"),0,+H82/($D82+$E82-$G82)*$G82+H82) -> 0 | AL82: =IF(OR(ISERROR(+I82/($D82+$E82-$G82)*$G82+I82),LEFT(G82,1)="x"),0,+I82/($D82+$E82-$G82)*$G82+I82) -> 0 | AM82: =IF(OR(ISERROR(+J82/($D82+$E82-$G82)*$G82+J82),LEFT(H82,1)="x"),0,+J82/($D82+$E82-$G82)*$G82+J82) -> 0 | AN82: =IF(OR(ISERROR(+K82/($D82+$E82-$G82)*$G82+K82),LEFT(I82,1)="x"),0,+K82/($D82+$E82-$G82)*$G82+K82) -> 0 | AO82: =IF(OR(ISERROR(+L82/($D82+$E82-$G82)*$G82+L82),LEFT(J82,1)="x"),0,+L82/($D82+$E82-$G82)*$G82+L82) -> 0 | AP82: =IF(OR(ISERROR(+M82/($D82+$E82-$G82)*$G82+M82),LEFT(K82,1)="x"),0,+M82/($D82+$E82-$G82)*$G82+M82) -> 0 | AQ82: =IF(OR(ISERROR(+N82/($D82+$E82-$G82)*$G82+N82),LEFT(L82,1)="x"),0,+N82/($D82+$E82-$G82)*$G82+N82) -> 0 | AR82: =IF(OR(ISERROR(+O82/($D82+$E82-$G82)*$G82+O82),LEFT(M82,1)="x"),0,+O82/($D82+$E82-$G82)*$G82+O82) -> 0 | ... BC82: =IF(OR(ISERROR(+Z82/($D82+$E82-$G82)*$G82+Z82),LEFT(X82,1)="x"),0,+Z82/($D82+$E82-$G82)*$G82+Z82) -> 0 | BD82: =IF(OR(ISERROR(+Y82/($D82+$E82-$G82)*$G82+Y82),LEFT(W82,1)="x"),0,+Y82/($D82+$E82-$G82)*$G82+Y82) -> 0 | BE82: =IF(OR(ISERROR(+Z82/($D82+$E82-$G82)*$G82+Z82),LEFT(X82,1)="x"),0,+Z82/($D82+$E82-$G82)*$G82+Z82) -> 0 | BF82: =IF(OR(ISERROR(+AA82/($D82+$E82-$G82)*$G82+AA82),LEFT(Y82,1)="x"),0,+AA82/($D82+$E82-$G82)*$G82+AA82) -> 0 | BI82: =IF(OR(ISERROR(+#REF!/($D82+$E82-$G82)*$G82+#REF!),LEFT(Z82,1)="x"),0,+#REF!/($D82+$E82-$G82)*$G82+#REF!) -> 0
AD83: =SUM(G83:AC83) -> 0 | AE83: =SUM(D83:F83) -> 0 | AF83: =AD83-AE83 -> 0 | AJ83: =IF(AF83=0,0,"ERROR HERE") -> 0 | AK83: =IF(OR(ISERROR(+H83/($D83+$E83-$G83)*$G83+H83),LEFT(F83,1)="x"),0,+H83/($D83+$E83-$G83)*$G83+H83) -> 0 | AL83: =IF(OR(ISERROR(+I83/($D83+$E83-$G83)*$G83+I83),LEFT(G83,1)="x"),0,+I83/($D83+$E83-$G83)*$G83+I83) -> 0 | AM83: =IF(OR(ISERROR(+J83/($D83+$E83-$G83)*$G83+J83),LEFT(H83,1)="x"),0,+J83/($D83+$E83-$G83)*$G83+J83) -> 0 | AN83: =IF(OR(ISERROR(+K83/($D83+$E83-$G83)*$G83+K83),LEFT(I83,1)="x"),0,+K83/($D83+$E83-$G83)*$G83+K83) -> 0 | AO83: =IF(OR(ISERROR(+L83/($D83+$E83-$G83)*$G83+L83),LEFT(J83,1)="x"),0,+L83/($D83+$E83-$G83)*$G83+L83) -> 0 | AP83: =IF(OR(ISERROR(+M83/($D83+$E83-$G83)*$G83+M83),LEFT(K83,1)="x"),0,+M83/($D83+$E83-$G83)*$G83+M83) -> 0 | AQ83: =IF(OR(ISERROR(+N83/($D83+$E83-$G83)*$G83+N83),LEFT(L83,1)="x"),0,+N83/($D83+$E83-$G83)*$G83+N83) -> 0 | AR83: =IF(OR(ISERROR(+O83/($D83+$E83-$G83)*$G83+O83),LEFT(M83,1)="x"),0,+O83/($D83+$E83-$G83)*$G83+O83) -> 0 | ... BC83: =IF(OR(ISERROR(+Z83/($D83+$E83-$G83)*$G83+Z83),LEFT(X83,1)="x"),0,+Z83/($D83+$E83-$G83)*$G83+Z83) -> 0 | BD83: =IF(OR(ISERROR(+Y83/($D83+$E83-$G83)*$G83+Y83),LEFT(W83,1)="x"),0,+Y83/($D83+$E83-$G83)*$G83+Y83) -> 0 | BE83: =IF(OR(ISERROR(+Z83/($D83+$E83-$G83)*$G83+Z83),LEFT(X83,1)="x"),0,+Z83/($D83+$E83-$G83)*$G83+Z83) -> 0 | BF83: =IF(OR(ISERROR(+AA83/($D83+$E83-$G83)*$G83+AA83),LEFT(Y83,1)="x"),0,+AA83/($D83+$E83-$G83)*$G83+AA83) -> 0 | BI83: =IF(OR(ISERROR(+#REF!/($D83+$E83-$G83)*$G83+#REF!),LEFT(Z83,1)="x"),0,+#REF!/($D83+$E83-$G83)*$G83+#REF!) -> 0
AD84: =SUM(G84:AC84) -> 0 | AE84: =SUM(D84:F84) -> 0 | AF84: =AD84-AE84 -> 0 | AJ84: =IF(AF84=0,0,"ERROR HERE") -> 0 | AK84: =IF(OR(ISERROR(+H84/($D84+$E84-$G84)*$G84+H84),LEFT(F84,1)="x"),0,+H84/($D84+$E84-$G84)*$G84+H84) -> 0 | AL84: =IF(OR(ISERROR(+I84/($D84+$E84-$G84)*$G84+I84),LEFT(G84,1)="x"),0,+I84/($D84+$E84-$G84)*$G84+I84) -> 0 | AM84: =IF(OR(ISERROR(+J84/($D84+$E84-$G84)*$G84+J84),LEFT(H84,1)="x"),0,+J84/($D84+$E84-$G84)*$G84+J84) -> 0 | AN84: =IF(OR(ISERROR(+K84/($D84+$E84-$G84)*$G84+K84),LEFT(I84,1)="x"),0,+K84/($D84+$E84-$G84)*$G84+K84) -> 0 | AO84: =IF(OR(ISERROR(+L84/($D84+$E84-$G84)*$G84+L84),LEFT(J84,1)="x"),0,+L84/($D84+$E84-$G84)*$G84+L84) -> 0 | AP84: =IF(OR(ISERROR(+M84/($D84+$E84-$G84)*$G84+M84),LEFT(K84,1)="x"),0,+M84/($D84+$E84-$G84)*$G84+M84) -> 0 | AQ84: =IF(OR(ISERROR(+N84/($D84+$E84-$G84)*$G84+N84),LEFT(L84,1)="x"),0,+N84/($D84+$E84-$G84)*$G84+N84) -> 0 | AR84: =IF(OR(ISERROR(+O84/($D84+$E84-$G84)*$G84+O84),LEFT(M84,1)="x"),0,+O84/($D84+$E84-$G84)*$G84+O84) -> 0 | ... BC84: =IF(OR(ISERROR(+Z84/($D84+$E84-$G84)*$G84+Z84),LEFT(X84,1)="x"),0,+Z84/($D84+$E84-$G84)*$G84+Z84) -> 0 | BD84: =IF(OR(ISERROR(+Y84/($D84+$E84-$G84)*$G84+Y84),LEFT(W84,1)="x"),0,+Y84/($D84+$E84-$G84)*$G84+Y84) -> 0 | BE84: =IF(OR(ISERROR(+Z84/($D84+$E84-$G84)*$G84+Z84),LEFT(X84,1)="x"),0,+Z84/($D84+$E84-$G84)*$G84+Z84) -> 0 | BF84: =IF(OR(ISERROR(+AA84/($D84+$E84-$G84)*$G84+AA84),LEFT(Y84,1)="x"),0,+AA84/($D84+$E84-$G84)*$G84+AA84) -> 0 | BI84: =IF(OR(ISERROR(+#REF!/($D84+$E84-$G84)*$G84+#REF!),LEFT(Z84,1)="x"),0,+#REF!/($D84+$E84-$G84)*$G84+#REF!) -> 0
AD85: =SUM(G85:AC85) -> 0 | AE85: =SUM(D85:F85) -> 0 | AF85: =AD85-AE85 -> 0 | AJ85: =IF(AF85=0,0,"ERROR HERE") -> 0 | AK85: =IF(OR(ISERROR(+H85/($D85+$E85-$G85)*$G85+H85),LEFT(F85,1)="x"),0,+H85/($D85+$E85-$G85)*$G85+H85) -> 0 | AL85: =IF(OR(ISERROR(+I85/($D85+$E85-$G85)*$G85+I85),LEFT(G85,1)="x"),0,+I85/($D85+$E85-$G85)*$G85+I85) -> 0 | AM85: =IF(OR(ISERROR(+J85/($D85+$E85-$G85)*$G85+J85),LEFT(H85,1)="x"),0,+J85/($D85+$E85-$G85)*$G85+J85) -> 0 | AN85: =IF(OR(ISERROR(+K85/($D85+$E85-$G85)*$G85+K85),LEFT(I85,1)="x"),0,+K85/($D85+$E85-$G85)*$G85+K85) -> 0 | AO85: =IF(OR(ISERROR(+L85/($D85+$E85-$G85)*$G85+L85),LEFT(J85,1)="x"),0,+L85/($D85+$E85-$G85)*$G85+L85) -> 0 | AP85: =IF(OR(ISERROR(+M85/($D85+$E85-$G85)*$G85+M85),LEFT(K85,1)="x"),0,+M85/($D85+$E85-$G85)*$G85+M85) -> 0 | AQ85: =IF(OR(ISERROR(+N85/($D85+$E85-$G85)*$G85+N85),LEFT(L85,1)="x"),0,+N85/($D85+$E85-$G85)*$G85+N85) -> 0 | AR85: =IF(OR(ISERROR(+O85/($D85+$E85-$G85)*$G85+O85),LEFT(M85,1)="x"),0,+O85/($D85+$E85-$G85)*$G85+O85) -> 0 | ... BC85: =IF(OR(ISERROR(+Z85/($D85+$E85-$G85)*$G85+Z85),LEFT(X85,1)="x"),0,+Z85/($D85+$E85-$G85)*$G85+Z85) -> 0 | BD85: =IF(OR(ISERROR(+Y85/($D85+$E85-$G85)*$G85+Y85),LEFT(W85,1)="x"),0,+Y85/($D85+$E85-$G85)*$G85+Y85) -> 0 | BE85: =IF(OR(ISERROR(+Z85/($D85+$E85-$G85)*$G85+Z85),LEFT(X85,1)="x"),0,+Z85/($D85+$E85-$G85)*$G85+Z85) -> 0 | BF85: =IF(OR(ISERROR(+AA85/($D85+$E85-$G85)*$G85+AA85),LEFT(Y85,1)="x"),0,+AA85/($D85+$E85-$G85)*$G85+AA85) -> 0 | BI85: =IF(OR(ISERROR(+#REF!/($D85+$E85-$G85)*$G85+#REF!),LEFT(Z85,1)="x"),0,+#REF!/($D85+$E85-$G85)*$G85+#REF!) -> 0
AD86: =SUM(G86:AC86) -> 0 | AE86: =SUM(D86:F86) -> 0 | AF86: =AD86-AE86 -> 0 | AJ86: =IF(AF86=0,0,"ERROR HERE") -> 0 | AK86: =IF(OR(ISERROR(+H86/($D86+$E86-$G86)*$G86+H86),LEFT(F86,1)="x"),0,+H86/($D86+$E86-$G86)*$G86+H86) -> 0 | AL86: =IF(OR(ISERROR(+I86/($D86+$E86-$G86)*$G86+I86),LEFT(G86,1)="x"),0,+I86/($D86+$E86-$G86)*$G86+I86) -> 0 | AM86: =IF(OR(ISERROR(+J86/($D86+$E86-$G86)*$G86+J86),LEFT(H86,1)="x"),0,+J86/($D86+$E86-$G86)*$G86+J86) -> 0 | AN86: =IF(OR(ISERROR(+K86/($D86+$E86-$G86)*$G86+K86),LEFT(I86,1)="x"),0,+K86/($D86+$E86-$G86)*$G86+K86) -> 0 | AO86: =IF(OR(ISERROR(+L86/($D86+$E86-$G86)*$G86+L86),LEFT(J86,1)="x"),0,+L86/($D86+$E86-$G86)*$G86+L86) -> 0 | AP86: =IF(OR(ISERROR(+M86/($D86+$E86-$G86)*$G86+M86),LEFT(K86,1)="x"),0,+M86/($D86+$E86-$G86)*$G86+M86) -> 0 | AQ86: =IF(OR(ISERROR(+N86/($D86+$E86-$G86)*$G86+N86),LEFT(L86,1)="x"),0,+N86/($D86+$E86-$G86)*$G86+N86) -> 0 | AR86: =IF(OR(ISERROR(+O86/($D86+$E86-$G86)*$G86+O86),LEFT(M86,1)="x"),0,+O86/($D86+$E86-$G86)*$G86+O86) -> 0 | ... BC86: =IF(OR(ISERROR(+Z86/($D86+$E86-$G86)*$G86+Z86),LEFT(X86,1)="x"),0,+Z86/($D86+$E86-$G86)*$G86+Z86) -> 0 | BD86: =IF(OR(ISERROR(+Y86/($D86+$E86-$G86)*$G86+Y86),LEFT(W86,1)="x"),0,+Y86/($D86+$E86-$G86)*$G86+Y86) -> 0 | BE86: =IF(OR(ISERROR(+Z86/($D86+$E86-$G86)*$G86+Z86),LEFT(X86,1)="x"),0,+Z86/($D86+$E86-$G86)*$G86+Z86) -> 0 | BF86: =IF(OR(ISERROR(+AA86/($D86+$E86-$G86)*$G86+AA86),LEFT(Y86,1)="x"),0,+AA86/($D86+$E86-$G86)*$G86+AA86) -> 0 | BI86: =IF(OR(ISERROR(+#REF!/($D86+$E86-$G86)*$G86+#REF!),LEFT(Z86,1)="x"),0,+#REF!/($D86+$E86-$G86)*$G86+#REF!) -> 0
AD87: =SUM(G87:AC87) -> 0 | AE87: =SUM(D87:F87) -> 0 | AF87: =AD87-AE87 -> 0 | AJ87: =IF(AF87=0,0,"ERROR HERE") -> 0 | AK87: =IF(OR(ISERROR(+H87/($D87+$E87-$G87)*$G87+H87),LEFT(F87,1)="x"),0,+H87/($D87+$E87-$G87)*$G87+H87) -> 0 | AL87: =IF(OR(ISERROR(+I87/($D87+$E87-$G87)*$G87+I87),LEFT(G87,1)="x"),0,+I87/($D87+$E87-$G87)*$G87+I87) -> 0 | AM87: =IF(OR(ISERROR(+J87/($D87+$E87-$G87)*$G87+J87),LEFT(H87,1)="x"),0,+J87/($D87+$E87-$G87)*$G87+J87) -> 0 | AN87: =IF(OR(ISERROR(+K87/($D87+$E87-$G87)*$G87+K87),LEFT(I87,1)="x"),0,+K87/($D87+$E87-$G87)*$G87+K87) -> 0 | AO87: =IF(OR(ISERROR(+L87/($D87+$E87-$G87)*$G87+L87),LEFT(J87,1)="x"),0,+L87/($D87+$E87-$G87)*$G87+L87) -> 0 | AP87: =IF(OR(ISERROR(+M87/($D87+$E87-$G87)*$G87+M87),LEFT(K87,1)="x"),0,+M87/($D87+$E87-$G87)*$G87+M87) -> 0 | AQ87: =IF(OR(ISERROR(+N87/($D87+$E87-$G87)*$G87+N87),LEFT(L87,1)="x"),0,+N87/($D87+$E87-$G87)*$G87+N87) -> 0 | AR87: =IF(OR(ISERROR(+O87/($D87+$E87-$G87)*$G87+O87),LEFT(M87,1)="x"),0,+O87/($D87+$E87-$G87)*$G87+O87) -> 0 | ... BC87: =IF(OR(ISERROR(+Z87/($D87+$E87-$G87)*$G87+Z87),LEFT(X87,1)="x"),0,+Z87/($D87+$E87-$G87)*$G87+Z87) -> 0 | BD87: =IF(OR(ISERROR(+Y87/($D87+$E87-$G87)*$G87+Y87),LEFT(W87,1)="x"),0,+Y87/($D87+$E87-$G87)*$G87+Y87) -> 0 | BE87: =IF(OR(ISERROR(+Z87/($D87+$E87-$G87)*$G87+Z87),LEFT(X87,1)="x"),0,+Z87/($D87+$E87-$G87)*$G87+Z87) -> 0 | BF87: =IF(OR(ISERROR(+AA87/($D87+$E87-$G87)*$G87+AA87),LEFT(Y87,1)="x"),0,+AA87/($D87+$E87-$G87)*$G87+AA87) -> 0 | BI87: =IF(OR(ISERROR(+#REF!/($D87+$E87-$G87)*$G87+#REF!),LEFT(Z87,1)="x"),0,+#REF!/($D87+$E87-$G87)*$G87+#REF!) -> 0
AD88: =SUM(G88:AC88) -> 0 | AE88: =SUM(D88:F88) -> 0 | AF88: =AD88-AE88 -> 0 | AJ88: =IF(AF88=0,0,"ERROR HERE") -> 0 | AK88: =IF(OR(ISERROR(+H88/($D88+$E88-$G88)*$G88+H88),LEFT(F88,1)="x"),0,+H88/($D88+$E88-$G88)*$G88+H88) -> 0 | AL88: =IF(OR(ISERROR(+I88/($D88+$E88-$G88)*$G88+I88),LEFT(G88,1)="x"),0,+I88/($D88+$E88-$G88)*$G88+I88) -> 0 | AM88: =IF(OR(ISERROR(+J88/($D88+$E88-$G88)*$G88+J88),LEFT(H88,1)="x"),0,+J88/($D88+$E88-$G88)*$G88+J88) -> 0 | AN88: =IF(OR(ISERROR(+K88/($D88+$E88-$G88)*$G88+K88),LEFT(I88,1)="x"),0,+K88/($D88+$E88-$G88)*$G88+K88) -> 0 | AO88: =IF(OR(ISERROR(+L88/($D88+$E88-$G88)*$G88+L88),LEFT(J88,1)="x"),0,+L88/($D88+$E88-$G88)*$G88+L88) -> 0 | AP88: =IF(OR(ISERROR(+M88/($D88+$E88-$G88)*$G88+M88),LEFT(K88,1)="x"),0,+M88/($D88+$E88-$G88)*$G88+M88) -> 0 | AQ88: =IF(OR(ISERROR(+N88/($D88+$E88-$G88)*$G88+N88),LEFT(L88,1)="x"),0,+N88/($D88+$E88-$G88)*$G88+N88) -> 0 | AR88: =IF(OR(ISERROR(+O88/($D88+$E88-$G88)*$G88+O88),LEFT(M88,1)="x"),0,+O88/($D88+$E88-$G88)*$G88+O88) -> 0 | ... BC88: =IF(OR(ISERROR(+Z88/($D88+$E88-$G88)*$G88+Z88),LEFT(X88,1)="x"),0,+Z88/($D88+$E88-$G88)*$G88+Z88) -> 0 | BD88: =IF(OR(ISERROR(+Y88/($D88+$E88-$G88)*$G88+Y88),LEFT(W88,1)="x"),0,+Y88/($D88+$E88-$G88)*$G88+Y88) -> 0 | BE88: =IF(OR(ISERROR(+Z88/($D88+$E88-$G88)*$G88+Z88),LEFT(X88,1)="x"),0,+Z88/($D88+$E88-$G88)*$G88+Z88) -> 0 | BF88: =IF(OR(ISERROR(+AA88/($D88+$E88-$G88)*$G88+AA88),LEFT(Y88,1)="x"),0,+AA88/($D88+$E88-$G88)*$G88+AA88) -> 0 | BI88: =IF(OR(ISERROR(+#REF!/($D88+$E88-$G88)*$G88+#REF!),LEFT(Z88,1)="x"),0,+#REF!/($D88+$E88-$G88)*$G88+#REF!) -> 0
AD89: =SUM(G89:AC89) -> 0 | AE89: =SUM(D89:F89) -> 0 | AF89: =AD89-AE89 -> 0 | AJ89: =IF(AF89=0,0,"ERROR HERE") -> 0 | AK89: =IF(OR(ISERROR(+H89/($D89+$E89-$G89)*$G89+H89),LEFT(F89,1)="x"),0,+H89/($D89+$E89-$G89)*$G89+H89) -> 0 | AL89: =IF(OR(ISERROR(+I89/($D89+$E89-$G89)*$G89+I89),LEFT(G89,1)="x"),0,+I89/($D89+$E89-$G89)*$G89+I89) -> 0 | AM89: =IF(OR(ISERROR(+J89/($D89+$E89-$G89)*$G89+J89),LEFT(H89,1)="x"),0,+J89/($D89+$E89-$G89)*$G89+J89) -> 0 | AN89: =IF(OR(ISERROR(+K89/($D89+$E89-$G89)*$G89+K89),LEFT(I89,1)="x"),0,+K89/($D89+$E89-$G89)*$G89+K89) -> 0 | AO89: =IF(OR(ISERROR(+L89/($D89+$E89-$G89)*$G89+L89),LEFT(J89,1)="x"),0,+L89/($D89+$E89-$G89)*$G89+L89) -> 0 | AP89: =IF(OR(ISERROR(+M89/($D89+$E89-$G89)*$G89+M89),LEFT(K89,1)="x"),0,+M89/($D89+$E89-$G89)*$G89+M89) -> 0 | AQ89: =IF(OR(ISERROR(+N89/($D89+$E89-$G89)*$G89+N89),LEFT(L89,1)="x"),0,+N89/($D89+$E89-$G89)*$G89+N89) -> 0 | AR89: =IF(OR(ISERROR(+O89/($D89+$E89-$G89)*$G89+O89),LEFT(M89,1)="x"),0,+O89/($D89+$E89-$G89)*$G89+O89) -> 0 | ... BC89: =IF(OR(ISERROR(+Z89/($D89+$E89-$G89)*$G89+Z89),LEFT(X89,1)="x"),0,+Z89/($D89+$E89-$G89)*$G89+Z89) -> 0 | BD89: =IF(OR(ISERROR(+Y89/($D89+$E89-$G89)*$G89+Y89),LEFT(W89,1)="x"),0,+Y89/($D89+$E89-$G89)*$G89+Y89) -> 0 | BE89: =IF(OR(ISERROR(+Z89/($D89+$E89-$G89)*$G89+Z89),LEFT(X89,1)="x"),0,+Z89/($D89+$E89-$G89)*$G89+Z89) -> 0 | BF89: =IF(OR(ISERROR(+AA89/($D89+$E89-$G89)*$G89+AA89),LEFT(Y89,1)="x"),0,+AA89/($D89+$E89-$G89)*$G89+AA89) -> 0 | BI89: =IF(OR(ISERROR(+#REF!/($D89+$E89-$G89)*$G89+#REF!),LEFT(Z89,1)="x"),0,+#REF!/($D89+$E89-$G89)*$G89+#REF!) -> 0
AD90: =SUM(G90:AC90) -> 0 | AE90: =SUM(D90:F90) -> 0 | AF90: =AD90-AE90 -> 0 | AJ90: =IF(AF90=0,0,"ERROR HERE") -> 0 | AK90: =IF(OR(ISERROR(+H90/($D90+$E90-$G90)*$G90+H90),LEFT(F90,1)="x"),0,+H90/($D90+$E90-$G90)*$G90+H90) -> 0 | AL90: =IF(OR(ISERROR(+I90/($D90+$E90-$G90)*$G90+I90),LEFT(G90,1)="x"),0,+I90/($D90+$E90-$G90)*$G90+I90) -> 0 | AM90: =IF(OR(ISERROR(+J90/($D90+$E90-$G90)*$G90+J90),LEFT(H90,1)="x"),0,+J90/($D90+$E90-$G90)*$G90+J90) -> 0 | AN90: =IF(OR(ISERROR(+K90/($D90+$E90-$G90)*$G90+K90),LEFT(I90,1)="x"),0,+K90/($D90+$E90-$G90)*$G90+K90) -> 0 | AO90: =IF(OR(ISERROR(+L90/($D90+$E90-$G90)*$G90+L90),LEFT(J90,1)="x"),0,+L90/($D90+$E90-$G90)*$G90+L90) -> 0 | AP90: =IF(OR(ISERROR(+M90/($D90+$E90-$G90)*$G90+M90),LEFT(K90,1)="x"),0,+M90/($D90+$E90-$G90)*$G90+M90) -> 0 | AQ90: =IF(OR(ISERROR(+N90/($D90+$E90-$G90)*$G90+N90),LEFT(L90,1)="x"),0,+N90/($D90+$E90-$G90)*$G90+N90) -> 0 | AR90: =IF(OR(ISERROR(+O90/($D90+$E90-$G90)*$G90+O90),LEFT(M90,1)="x"),0,+O90/($D90+$E90-$G90)*$G90+O90) -> 0 | ... BC90: =IF(OR(ISERROR(+Z90/($D90+$E90-$G90)*$G90+Z90),LEFT(X90,1)="x"),0,+Z90/($D90+$E90-$G90)*$G90+Z90) -> 0 | BD90: =IF(OR(ISERROR(+Y90/($D90+$E90-$G90)*$G90+Y90),LEFT(W90,1)="x"),0,+Y90/($D90+$E90-$G90)*$G90+Y90) -> 0 | BE90: =IF(OR(ISERROR(+Z90/($D90+$E90-$G90)*$G90+Z90),LEFT(X90,1)="x"),0,+Z90/($D90+$E90-$G90)*$G90+Z90) -> 0 | BF90: =IF(OR(ISERROR(+AA90/($D90+$E90-$G90)*$G90+AA90),LEFT(Y90,1)="x"),0,+AA90/($D90+$E90-$G90)*$G90+AA90) -> 0 | BI90: =IF(OR(ISERROR(+#REF!/($D90+$E90-$G90)*$G90+#REF!),LEFT(Z90,1)="x"),0,+#REF!/($D90+$E90-$G90)*$G90+#REF!) -> 0
AD91: =SUM(G91:AC91) -> 0 | AE91: =SUM(D91:F91) -> 0 | AF91: =AD91-AE91 -> 0 | AJ91: =IF(AF91=0,0,"ERROR HERE") -> 0 | AK91: =IF(OR(ISERROR(+H91/($D91+$E91-$G91)*$G91+H91),LEFT(F91,1)="x"),0,+H91/($D91+$E91-$G91)*$G91+H91) -> 0 | AL91: =IF(OR(ISERROR(+I91/($D91+$E91-$G91)*$G91+I91),LEFT(G91,1)="x"),0,+I91/($D91+$E91-$G91)*$G91+I91) -> 0 | AM91: =IF(OR(ISERROR(+J91/($D91+$E91-$G91)*$G91+J91),LEFT(H91,1)="x"),0,+J91/($D91+$E91-$G91)*$G91+J91) -> 0 | AN91: =IF(OR(ISERROR(+K91/($D91+$E91-$G91)*$G91+K91),LEFT(I91,1)="x"),0,+K91/($D91+$E91-$G91)*$G91+K91) -> 0 | AO91: =IF(OR(ISERROR(+L91/($D91+$E91-$G91)*$G91+L91),LEFT(J91,1)="x"),0,+L91/($D91+$E91-$G91)*$G91+L91) -> 0 | AP91: =IF(OR(ISERROR(+M91/($D91+$E91-$G91)*$G91+M91),LEFT(K91,1)="x"),0,+M91/($D91+$E91-$G91)*$G91+M91) -> 0 | AQ91: =IF(OR(ISERROR(+N91/($D91+$E91-$G91)*$G91+N91),LEFT(L91,1)="x"),0,+N91/($D91+$E91-$G91)*$G91+N91) -> 0 | AR91: =IF(OR(ISERROR(+O91/($D91+$E91-$G91)*$G91+O91),LEFT(M91,1)="x"),0,+O91/($D91+$E91-$G91)*$G91+O91) -> 0 | ... BC91: =IF(OR(ISERROR(+Z91/($D91+$E91-$G91)*$G91+Z91),LEFT(X91,1)="x"),0,+Z91/($D91+$E91-$G91)*$G91+Z91) -> 0 | BD91: =IF(OR(ISERROR(+Y91/($D91+$E91-$G91)*$G91+Y91),LEFT(W91,1)="x"),0,+Y91/($D91+$E91-$G91)*$G91+Y91) -> 0 | BE91: =IF(OR(ISERROR(+Z91/($D91+$E91-$G91)*$G91+Z91),LEFT(X91,1)="x"),0,+Z91/($D91+$E91-$G91)*$G91+Z91) -> 0 | BF91: =IF(OR(ISERROR(+AA91/($D91+$E91-$G91)*$G91+AA91),LEFT(Y91,1)="x"),0,+AA91/($D91+$E91-$G91)*$G91+AA91) -> 0 | BI91: =IF(OR(ISERROR(+#REF!/($D91+$E91-$G91)*$G91+#REF!),LEFT(Z91,1)="x"),0,+#REF!/($D91+$E91-$G91)*$G91+#REF!) -> 0
AD92: =SUM(G92:AC92) -> 0 | AE92: =SUM(D92:F92) -> 0 | AF92: =AD92-AE92 -> 0 | AJ92: =IF(AF92=0,0,"ERROR HERE") -> 0 | AK92: =IF(OR(ISERROR(+H92/($D92+$E92-$G92)*$G92+H92),LEFT(F92,1)="x"),0,+H92/($D92+$E92-$G92)*$G92+H92) -> 0 | AL92: =IF(OR(ISERROR(+I92/($D92+$E92-$G92)*$G92+I92),LEFT(G92,1)="x"),0,+I92/($D92+$E92-$G92)*$G92+I92) -> 0 | AM92: =IF(OR(ISERROR(+J92/($D92+$E92-$G92)*$G92+J92),LEFT(H92,1)="x"),0,+J92/($D92+$E92-$G92)*$G92+J92) -> 0 | AN92: =IF(OR(ISERROR(+K92/($D92+$E92-$G92)*$G92+K92),LEFT(I92,1)="x"),0,+K92/($D92+$E92-$G92)*$G92+K92) -> 0 | AO92: =IF(OR(ISERROR(+L92/($D92+$E92-$G92)*$G92+L92),LEFT(J92,1)="x"),0,+L92/($D92+$E92-$G92)*$G92+L92) -> 0 | AP92: =IF(OR(ISERROR(+M92/($D92+$E92-$G92)*$G92+M92),LEFT(K92,1)="x"),0,+M92/($D92+$E92-$G92)*$G92+M92) -> 0 | AQ92: =IF(OR(ISERROR(+N92/($D92+$E92-$G92)*$G92+N92),LEFT(L92,1)="x"),0,+N92/($D92+$E92-$G92)*$G92+N92) -> 0 | AR92: =IF(OR(ISERROR(+O92/($D92+$E92-$G92)*$G92+O92),LEFT(M92,1)="x"),0,+O92/($D92+$E92-$G92)*$G92+O92) -> 0 | ... BC92: =IF(OR(ISERROR(+Z92/($D92+$E92-$G92)*$G92+Z92),LEFT(X92,1)="x"),0,+Z92/($D92+$E92-$G92)*$G92+Z92) -> 0 | BD92: =IF(OR(ISERROR(+Y92/($D92+$E92-$G92)*$G92+Y92),LEFT(W92,1)="x"),0,+Y92/($D92+$E92-$G92)*$G92+Y92) -> 0 | BE92: =IF(OR(ISERROR(+Z92/($D92+$E92-$G92)*$G92+Z92),LEFT(X92,1)="x"),0,+Z92/($D92+$E92-$G92)*$G92+Z92) -> 0 | BF92: =IF(OR(ISERROR(+AA92/($D92+$E92-$G92)*$G92+AA92),LEFT(Y92,1)="x"),0,+AA92/($D92+$E92-$G92)*$G92+AA92) -> 0 | BI92: =IF(OR(ISERROR(+#REF!/($D92+$E92-$G92)*$G92+#REF!),LEFT(Z92,1)="x"),0,+#REF!/($D92+$E92-$G92)*$G92+#REF!) -> 0
... AD97: =SUM(G97:AC97) -> 0 | AE97: =SUM(D97:F97) -> 0 | AF97: =AD97-AE97 -> 0 | AJ97: =IF(AF97=0,0,"ERROR HERE") -> 0 | AK97: =IF(OR(ISERROR(+H97/($D97+$E97-$G97)*$G97+H97),LEFT(F97,1)="x"),0,+H97/($D97+$E97-$G97)*$G97+H97) -> 0 | AL97: =IF(OR(ISERROR(+I97/($D97+$E97-$G97)*$G97+I97),LEFT(G97,1)="x"),0,+I97/($D97+$E97-$G97)*$G97+I97) -> 0 | AM97: =IF(OR(ISERROR(+J97/($D97+$E97-$G97)*$G97+J97),LEFT(H97,1)="x"),0,+J97/($D97+$E97-$G97)*$G97+J97) -> 0 | AN97: =IF(OR(ISERROR(+K97/($D97+$E97-$G97)*$G97+K97),LEFT(I97,1)="x"),0,+K97/($D97+$E97-$G97)*$G97+K97) -> 0 | AO97: =IF(OR(ISERROR(+L97/($D97+$E97-$G97)*$G97+L97),LEFT(J97,1)="x"),0,+L97/($D97+$E97-$G97)*$G97+L97) -> 0 | AP97: =IF(OR(ISERROR(+M97/($D97+$E97-$G97)*$G97+M97),LEFT(K97,1)="x"),0,+M97/($D97+$E97-$G97)*$G97+M97) -> 0 | AQ97: =IF(OR(ISERROR(+N97/($D97+$E97-$G97)*$G97+N97),LEFT(L97,1)="x"),0,+N97/($D97+$E97-$G97)*$G97+N97) -> 0 | AR97: =IF(OR(ISERROR(+O97/($D97+$E97-$G97)*$G97+O97),LEFT(M97,1)="x"),0,+O97/($D97+$E97-$G97)*$G97+O97) -> 0 | ... BC97: =IF(OR(ISERROR(+Z97/($D97+$E97-$G97)*$G97+Z97),LEFT(X97,1)="x"),0,+Z97/($D97+$E97-$G97)*$G97+Z97) -> 0 | BD97: =IF(OR(ISERROR(+Y97/($D97+$E97-$G97)*$G97+Y97),LEFT(W97,1)="x"),0,+Y97/($D97+$E97-$G97)*$G97+Y97) -> 0 | BE97: =IF(OR(ISERROR(+Z97/($D97+$E97-$G97)*$G97+Z97),LEFT(X97,1)="x"),0,+Z97/($D97+$E97-$G97)*$G97+Z97) -> 0 | BF97: =IF(OR(ISERROR(+AA97/($D97+$E97-$G97)*$G97+AA97),LEFT(Y97,1)="x"),0,+AA97/($D97+$E97-$G97)*$G97+AA97) -> 0 | BI97: =IF(OR(ISERROR(+#REF!/($D97+$E97-$G97)*$G97+#REF!),LEFT(Z97,1)="x"),0,+#REF!/($D97+$E97-$G97)*$G97+#REF!) -> 0
R98: 0 | S98: 0 | T98: 0 | V98: 0 | W98: 0 | AD98: =SUM(G98:AC98) -> 0 | AE98: =SUM(D98:F98) -> 0 | AF98: =AD98-AE98 -> 0 | AJ98: =IF(AF98=0,0,"ERROR HERE") -> 0 | AK98: =IF(OR(ISERROR(+H98/($D98+$E98-$G98)*$G98+H98),LEFT(F98,1)="x"),0,+H98/($D98+$E98-$G98)*$G98+H98) -> 0 | AL98: =IF(OR(ISERROR(+I98/($D98+$E98-$G98)*$G98+I98),LEFT(G98,1)="x"),0,+I98/($D98+$E98-$G98)*$G98+I98) -> 0 | AM98: =IF(OR(ISERROR(+J98/($D98+$E98-$G98)*$G98+J98),LEFT(H98,1)="x"),0,+J98/($D98+$E98-$G98)*$G98+J98) -> 0 | AN98: =IF(OR(ISERROR(+K98/($D98+$E98-$G98)*$G98+K98),LEFT(I98,1)="x"),0,+K98/($D98+$E98-$G98)*$G98+K98) -> 0 | AO98: =IF(OR(ISERROR(+L98/($D98+$E98-$G98)*$G98+L98),LEFT(J98,1)="x"),0,+L98/($D98+$E98-$G98)*$G98+L98) -> 0 | AP98: =IF(OR(ISERROR(+M98/($D98+$E98-$G98)*$G98+M98),LEFT(K98,1)="x"),0,+M98/($D98+$E98-$G98)*$G98+M98) -> 0 | AQ98: =IF(OR(ISERROR(+N98/($D98+$E98-$G98)*$G98+N98),LEFT(L98,1)="x"),0,+N98/($D98+$E98-$G98)*$G98+N98) -> 0 | AR98: =IF(OR(ISERROR(+O98/($D98+$E98-$G98)*$G98+O98),LEFT(M98,1)="x"),0,+O98/($D98+$E98-$G98)*$G98+O98) -> 0 | ... BC98: =IF(OR(ISERROR(+Z98/($D98+$E98-$G98)*$G98+Z98),LEFT(X98,1)="x"),0,+Z98/($D98+$E98-$G98)*$G98+Z98) -> 0 | BD98: =IF(OR(ISERROR(+Y98/($D98+$E98-$G98)*$G98+Y98),LEFT(W98,1)="x"),0,+Y98/($D98+$E98-$G98)*$G98+Y98) -> 0 | BE98: =IF(OR(ISERROR(+Z98/($D98+$E98-$G98)*$G98+Z98),LEFT(X98,1)="x"),0,+Z98/($D98+$E98-$G98)*$G98+Z98) -> 0 | BF98: =IF(OR(ISERROR(+AA98/($D98+$E98-$G98)*$G98+AA98),LEFT(Y98,1)="x"),0,+AA98/($D98+$E98-$G98)*$G98+AA98) -> 0 | BI98: =IF(OR(ISERROR(+#REF!/($D98+$E98-$G98)*$G98+#REF!),LEFT(Z98,1)="x"),0,+#REF!/($D98+$E98-$G98)*$G98+#REF!) -> 0
R99: 0 | AD99: =SUM(G99:AC99) -> 0 | AE99: =SUM(D99:F99) -> 0 | AF99: =AD99-AE99 -> 0 | AJ99: =IF(AF99=0,0,"ERROR HERE") -> 0 | AK99: =IF(OR(ISERROR(+H99/($D99+$E99-$G99)*$G99+H99),LEFT(F99,1)="x"),0,+H99/($D99+$E99-$G99)*$G99+H99) -> 0 | AL99: =IF(OR(ISERROR(+I99/($D99+$E99-$G99)*$G99+I99),LEFT(G99,1)="x"),0,+I99/($D99+$E99-$G99)*$G99+I99) -> 0 | AM99: =IF(OR(ISERROR(+J99/($D99+$E99-$G99)*$G99+J99),LEFT(H99,1)="x"),0,+J99/($D99+$E99-$G99)*$G99+J99) -> 0 | AN99: =IF(OR(ISERROR(+K99/($D99+$E99-$G99)*$G99+K99),LEFT(I99,1)="x"),0,+K99/($D99+$E99-$G99)*$G99+K99) -> 0 | AO99: =IF(OR(ISERROR(+L99/($D99+$E99-$G99)*$G99+L99),LEFT(J99,1)="x"),0,+L99/($D99+$E99-$G99)*$G99+L99) -> 0 | AP99: =IF(OR(ISERROR(+M99/($D99+$E99-$G99)*$G99+M99),LEFT(K99,1)="x"),0,+M99/($D99+$E99-$G99)*$G99+M99) -> 0 | AQ99: =IF(OR(ISERROR(+N99/($D99+$E99-$G99)*$G99+N99),LEFT(L99,1)="x"),0,+N99/($D99+$E99-$G99)*$G99+N99) -> 0 | AR99: =IF(OR(ISERROR(+O99/($D99+$E99-$G99)*$G99+O99),LEFT(M99,1)="x"),0,+O99/($D99+$E99-$G99)*$G99+O99) -> 0 | ... BC99: =IF(OR(ISERROR(+Z99/($D99+$E99-$G99)*$G99+Z99),LEFT(X99,1)="x"),0,+Z99/($D99+$E99-$G99)*$G99+Z99) -> 0 | BD99: =IF(OR(ISERROR(+Y99/($D99+$E99-$G99)*$G99+Y99),LEFT(W99,1)="x"),0,+Y99/($D99+$E99-$G99)*$G99+Y99) -> 0 | BE99: =IF(OR(ISERROR(+Z99/($D99+$E99-$G99)*$G99+Z99),LEFT(X99,1)="x"),0,+Z99/($D99+$E99-$G99)*$G99+Z99) -> 0 | BF99: =IF(OR(ISERROR(+AA99/($D99+$E99-$G99)*$G99+AA99),LEFT(Y99,1)="x"),0,+AA99/($D99+$E99-$G99)*$G99+AA99) -> 0 | BI99: =IF(OR(ISERROR(+#REF!/($D99+$E99-$G99)*$G99+#REF!),LEFT(Z99,1)="x"),0,+#REF!/($D99+$E99-$G99)*$G99+#REF!) -> 0
C100: Total | D100: =SUM(D69:D99) -> 7661.5 | E100: =SUM(E69:E99) -> 0 | F100: =SUM(F69:F99) -> 0 | G100: =SUM(G69:G99) -> 47 | H100: =SUM(H69:H99) -> 42 | I100: =SUM(I69:I99) -> 420 | J100: =SUM(J69:J99) -> 0 | K100: =SUM(K69:K99) -> 1000 | ... AC100: =SUM(AC69:AC99) -> 0 | AK100: =IF(OR(ISERROR(+H100/($D100+$E100-$G100)*$G100+H100),LEFT(F100,1)="x"),0,+H100/($D100+$E100-$G100)*$G100+H100) -> 42.259242 | AL100: =IF(OR(ISERROR(+I100/($D100+$E100-$G100)*$G100+I100),LEFT(G100,1)="x"),0,+I100/($D100+$E100-$G100)*$G100+I100) -> 422.59242 | AM100: =IF(OR(ISERROR(+J100/($D100+$E100-$G100)*$G100+J100),LEFT(H100,1)="x"),0,+J100/($D100+$E100-$G100)*$G100+J100) -> 0 | AN100: =IF(OR(ISERROR(+K100/($D100+$E100-$G100)*$G100+K100),LEFT(I100,1)="x"),0,+K100/($D100+$E100-$G100)*$G100+K100) -> 1006.1724 | AO100: =IF(OR(ISERROR(+L100/($D100+$E100-$G100)*$G100+L100),LEFT(J100,1)="x"),0,+L100/($D100+$E100-$G100)*$G100+L100) -> 865.30829 | AP100: =IF(OR(ISERROR(+M100/($D100+$E100-$G100)*$G100+M100),LEFT(K100,1)="x"),0,+M100/($D100+$E100-$G100)*$G100+M100) -> 0 | AQ100: =IF(OR(ISERROR(+N100/($D100+$E100-$G100)*$G100+N100),LEFT(L100,1)="x"),0,+N100/($D100+$E100-$G100)*$G100+N100) -> 0 | AR100: =IF(OR(ISERROR(+O100/($D100+$E100-$G100)*$G100+O100),LEFT(M100,1)="x"),0,+O100/($D100+$E100-$G100)*$G100+O100) -> 0 | ... BC100: =IF(OR(ISERROR(+Z100/($D100+$E100-$G100)*$G100+Z100),LEFT(X100,1)="x"),0,+Z100/($D100+$E100-$G100)*$G100+Z100) -> 0 | BD100: =IF(OR(ISERROR(+Y100/($D100+$E100-$G100)*$G100+Y100),LEFT(W100,1)="x"),0,+Y100/($D100+$E100-$G100)*$G100+Y100) -> 0 | BE100: =IF(OR(ISERROR(+Z100/($D100+$E100-$G100)*$G100+Z100),LEFT(X100,1)="x"),0,+Z100/($D100+$E100-$G100)*$G100+Z100) -> 0 | BF100: =IF(OR(ISERROR(+AA100/($D100+$E100-$G100)*$G100+AA100),LEFT(Y100,1)="x"),0,+AA100/($D100+$E100-$G100)*$G100+AA100) -> 0 | BI100: =IF(OR(ISERROR(+#REF!/($D100+$E100-$G100)*$G100+#REF!),LEFT(Z100,1)="x"),0,+#REF!/($D100+$E100-$G100)*$G100+#REF!) -> 0
C101: C/fwd | D101: =SUM(D68:D99) -> 7661.5 | E101: =SUM(E68:E99) -> 0 | F101: =SUM(F68:F99) -> 0 | G101: =SUM(G68:G99) -> 47 | H101: =SUM(H68:H99) -> 42 | I101: =SUM(I68:I99) -> 420 | J101: =SUM(J68:J99) -> 0 | K101: =SUM(K68:K99) -> 1000 | ... AC101: =SUM(AC68:AC99) -> 0 | AK101: =IF(OR(ISERROR(+H101/($D101+$E101-$G101)*$G101+H101),LEFT(F101,1)="x"),0,+H101/($D101+$E101-$G101)*$G101+H101) -> 42.259242 | AL101: =IF(OR(ISERROR(+I101/($D101+$E101-$G101)*$G101+I101),LEFT(G101,1)="x"),0,+I101/($D101+$E101-$G101)*$G101+I101) -> 422.59242 | AM101: =IF(OR(ISERROR(+J101/($D101+$E101-$G101)*$G101+J101),LEFT(H101,1)="x"),0,+J101/($D101+$E101-$G101)*$G101+J101) -> 0 | AN101: =IF(OR(ISERROR(+K101/($D101+$E101-$G101)*$G101+K101),LEFT(I101,1)="x"),0,+K101/($D101+$E101-$G101)*$G101+K101) -> 1006.1724 | AO101: =IF(OR(ISERROR(+L101/($D101+$E101-$G101)*$G101+L101),LEFT(J101,1)="x"),0,+L101/($D101+$E101-$G101)*$G101+L101) -> 865.30829 | AP101: =IF(OR(ISERROR(+M101/($D101+$E101-$G101)*$G101+M101),LEFT(K101,1)="x"),0,+M101/($D101+$E101-$G101)*$G101+M101) -> 0 | AQ101: =IF(OR(ISERROR(+N101/($D101+$E101-$G101)*$G101+N101),LEFT(L101,1)="x"),0,+N101/($D101+$E101-$G101)*$G101+N101) -> 0 | AR101: =IF(OR(ISERROR(+O101/($D101+$E101-$G101)*$G101+O101),LEFT(M101,1)="x"),0,+O101/($D101+$E101-$G101)*$G101+O101) -> 0 | ... BC101: =IF(OR(ISERROR(+Z101/($D101+$E101-$G101)*$G101+Z101),LEFT(X101,1)="x"),0,+Z101/($D101+$E101-$G101)*$G101+Z101) -> 0 | BD101: =IF(OR(ISERROR(+Y101/($D101+$E101-$G101)*$G101+Y101),LEFT(W101,1)="x"),0,+Y101/($D101+$E101-$G101)*$G101+Y101) -> 0 | BE101: =IF(OR(ISERROR(+Z101/($D101+$E101-$G101)*$G101+Z101),LEFT(X101,1)="x"),0,+Z101/($D101+$E101-$G101)*$G101+Z101) -> 0 | BF101: =IF(OR(ISERROR(+AA101/($D101+$E101-$G101)*$G101+AA101),LEFT(Y101,1)="x"),0,+AA101/($D101+$E101-$G101)*$G101+AA101) -> 0 | BI101: =IF(OR(ISERROR(+#REF!/($D101+$E101-$G101)*$G101+#REF!),LEFT(Z101,1)="x"),0,+#REF!/($D101+$E101-$G101)*$G101+#REF!) -> 0
AK102: =IF(OR(ISERROR(+H102/($D102+$E102-$G102)*$G102+H102),LEFT(F102,1)="x"),0,+H102/($D102+$E102-$G102)*$G102+H102) -> 0 | AL102: =IF(OR(ISERROR(+I102/($D102+$E102-$G102)*$G102+I102),LEFT(G102,1)="x"),0,+I102/($D102+$E102-$G102)*$G102+I102) -> 0 | AM102: =IF(OR(ISERROR(+J102/($D102+$E102-$G102)*$G102+J102),LEFT(H102,1)="x"),0,+J102/($D102+$E102-$G102)*$G102+J102) -> 0 | AN102: =IF(OR(ISERROR(+K102/($D102+$E102-$G102)*$G102+K102),LEFT(I102,1)="x"),0,+K102/($D102+$E102-$G102)*$G102+K102) -> 0 | AO102: =IF(OR(ISERROR(+L102/($D102+$E102-$G102)*$G102+L102),LEFT(J102,1)="x"),0,+L102/($D102+$E102-$G102)*$G102+L102) -> 0 | AP102: =IF(OR(ISERROR(+M102/($D102+$E102-$G102)*$G102+M102),LEFT(K102,1)="x"),0,+M102/($D102+$E102-$G102)*$G102+M102) -> 0 | AQ102: =IF(OR(ISERROR(+N102/($D102+$E102-$G102)*$G102+N102),LEFT(L102,1)="x"),0,+N102/($D102+$E102-$G102)*$G102+N102) -> 0 | AR102: =IF(OR(ISERROR(+O102/($D102+$E102-$G102)*$G102+O102),LEFT(M102,1)="x"),0,+O102/($D102+$E102-$G102)*$G102+O102) -> 0 | ... BC102: =IF(OR(ISERROR(+Z102/($D102+$E102-$G102)*$G102+Z102),LEFT(X102,1)="x"),0,+Z102/($D102+$E102-$G102)*$G102+Z102) -> 0 | BD102: =IF(OR(ISERROR(+Y102/($D102+$E102-$G102)*$G102+Y102),LEFT(W102,1)="x"),0,+Y102/($D102+$E102-$G102)*$G102+Y102) -> 0 | BE102: =IF(OR(ISERROR(+Z102/($D102+$E102-$G102)*$G102+Z102),LEFT(X102,1)="x"),0,+Z102/($D102+$E102-$G102)*$G102+Z102) -> 0 | BF102: =IF(OR(ISERROR(+AA102/($D102+$E102-$G102)*$G102+AA102),LEFT(Y102,1)="x"),0,+AA102/($D102+$E102-$G102)*$G102+AA102) -> 0 | BI102: =IF(OR(ISERROR(+#REF!/($D102+$E102-$G102)*$G102+#REF!),LEFT(Z102,1)="x"),0,+#REF!/($D102+$E102-$G102)*$G102+#REF!) -> 0
AK103: =IF(OR(ISERROR(+H103/($D103+$E103-$G103)*$G103+H103),LEFT(F103,1)="x"),0,+H103/($D103+$E103-$G103)*$G103+H103) -> 0 | AL103: =IF(OR(ISERROR(+I103/($D103+$E103-$G103)*$G103+I103),LEFT(G103,1)="x"),0,+I103/($D103+$E103-$G103)*$G103+I103) -> 0 | AM103: =IF(OR(ISERROR(+J103/($D103+$E103-$G103)*$G103+J103),LEFT(H103,1)="x"),0,+J103/($D103+$E103-$G103)*$G103+J103) -> 0 | AN103: =IF(OR(ISERROR(+K103/($D103+$E103-$G103)*$G103+K103),LEFT(I103,1)="x"),0,+K103/($D103+$E103-$G103)*$G103+K103) -> 0 | AO103: =IF(OR(ISERROR(+L103/($D103+$E103-$G103)*$G103+L103),LEFT(J103,1)="x"),0,+L103/($D103+$E103-$G103)*$G103+L103) -> 0 | AP103: =IF(OR(ISERROR(+M103/($D103+$E103-$G103)*$G103+M103),LEFT(K103,1)="x"),0,+M103/($D103+$E103-$G103)*$G103+M103) -> 0 | AQ103: =IF(OR(ISERROR(+N103/($D103+$E103-$G103)*$G103+N103),LEFT(L103,1)="x"),0,+N103/($D103+$E103-$G103)*$G103+N103) -> 0 | AR103: =IF(OR(ISERROR(+O103/($D103+$E103-$G103)*$G103+O103),LEFT(M103,1)="x"),0,+O103/($D103+$E103-$G103)*$G103+O103) -> 0 | ... BC103: =IF(OR(ISERROR(+Z103/($D103+$E103-$G103)*$G103+Z103),LEFT(X103,1)="x"),0,+Z103/($D103+$E103-$G103)*$G103+Z103) -> 0 | BD103: =IF(OR(ISERROR(+Y103/($D103+$E103-$G103)*$G103+Y103),LEFT(W103,1)="x"),0,+Y103/($D103+$E103-$G103)*$G103+Y103) -> 0 | BE103: =IF(OR(ISERROR(+Z103/($D103+$E103-$G103)*$G103+Z103),LEFT(X103,1)="x"),0,+Z103/($D103+$E103-$G103)*$G103+Z103) -> 0 | BF103: =IF(OR(ISERROR(+AA103/($D103+$E103-$G103)*$G103+AA103),LEFT(Y103,1)="x"),0,+AA103/($D103+$E103-$G103)*$G103+AA103) -> 0 | BI103: =IF(OR(ISERROR(+#REF!/($D103+$E103-$G103)*$G103+#REF!),LEFT(Z103,1)="x"),0,+#REF!/($D103+$E103-$G103)*$G103+#REF!) -> 0
AK104: =IF(OR(ISERROR(+H104/($D104+$E104-$G104)*$G104+H104),LEFT(F104,1)="x"),0,+H104/($D104+$E104-$G104)*$G104+H104) -> 0 | AL104: =IF(OR(ISERROR(+I104/($D104+$E104-$G104)*$G104+I104),LEFT(G104,1)="x"),0,+I104/($D104+$E104-$G104)*$G104+I104) -> 0 | AM104: =IF(OR(ISERROR(+J104/($D104+$E104-$G104)*$G104+J104),LEFT(H104,1)="x"),0,+J104/($D104+$E104-$G104)*$G104+J104) -> 0 | AN104: =IF(OR(ISERROR(+K104/($D104+$E104-$G104)*$G104+K104),LEFT(I104,1)="x"),0,+K104/($D104+$E104-$G104)*$G104+K104) -> 0 | AO104: =IF(OR(ISERROR(+L104/($D104+$E104-$G104)*$G104+L104),LEFT(J104,1)="x"),0,+L104/($D104+$E104-$G104)*$G104+L104) -> 0 | AP104: =IF(OR(ISERROR(+M104/($D104+$E104-$G104)*$G104+M104),LEFT(K104,1)="x"),0,+M104/($D104+$E104-$G104)*$G104+M104) -> 0 | AQ104: =IF(OR(ISERROR(+N104/($D104+$E104-$G104)*$G104+N104),LEFT(L104,1)="x"),0,+N104/($D104+$E104-$G104)*$G104+N104) -> 0 | AR104: =IF(OR(ISERROR(+O104/($D104+$E104-$G104)*$G104+O104),LEFT(M104,1)="x"),0,+O104/($D104+$E104-$G104)*$G104+O104) -> 0 | ... BC104: =IF(OR(ISERROR(+Z104/($D104+$E104-$G104)*$G104+Z104),LEFT(X104,1)="x"),0,+Z104/($D104+$E104-$G104)*$G104+Z104) -> 0 | BD104: =IF(OR(ISERROR(+Y104/($D104+$E104-$G104)*$G104+Y104),LEFT(W104,1)="x"),0,+Y104/($D104+$E104-$G104)*$G104+Y104) -> 0 | BE104: =IF(OR(ISERROR(+Z104/($D104+$E104-$G104)*$G104+Z104),LEFT(X104,1)="x"),0,+Z104/($D104+$E104-$G104)*$G104+Z104) -> 0 | BF104: =IF(OR(ISERROR(+AA104/($D104+$E104-$G104)*$G104+AA104),LEFT(Y104,1)="x"),0,+AA104/($D104+$E104-$G104)*$G104+AA104) -> 0 | BI104: =IF(OR(ISERROR(+#REF!/($D104+$E104-$G104)*$G104+#REF!),LEFT(Z104,1)="x"),0,+#REF!/($D104+$E104-$G104)*$G104+#REF!) -> 0
A105: Check Totals | D105: =E105-H105 -> 0 | E105: =D100+E100+F100 -> 7661.5 | H105: =SUM(G100:AC100) -> 7661.5
D106: =IF(D105=0,0,"Error - check totals do not balance, please see column AC - at the right side of the expenditure table for corrections to be made") -> 0
A108: Bank Reconciliation - use this section to check your spreadsheet reconciles to your bank statement(s)
A110: Bank Reconciliation
E111: Current Account | F111: Deposit Account
A112: Bank Account Balance calculated per spreadsheet | E112: =K10+K43+L43+M43+N43-D101 -> 946 | F112: =K11+O43+X101-N43 -> 3016
A114: Add: Unpresented cheques
B115: (Items included on spreadsheet
B116: that do not appear on bank
B117: statement as at month end)
A119: Balance per bank statement | E119: =E112+SUM(E113:E117) -> 946 | F119: =F112+SUM(F113:F117) -> 3016
A126: 2005/06
A129: =($C$47+$C$48-407.33)/112.8*12.8 -> -46.221844 | B129: 0 | C129: Employers NI | E129: =MAX(A129:B129) -> 0
A131: =$C$47+$C$48-A129 -> 46.221844 | C131: Employees NI | D131: =SUM(A131-407.33)*0.11 -> -39.721897 | E131: =IF(D131<0,0,MIN(D131,D132)) -> 0
D132: 255.49 | E132: 0
C133: Employee NI HR | D133: =SUM(A131-2730)*0.01 -> -26.837782 | E133: =MAX(D133,E132) -> 0
C134: Employee Tax at higher rate | D134: =(A131-407.92-174.17-2525.83)*0.4 -> -1224.6793 | E134: =MAX(D134,D135) -> 0
D135: 0
C136: Employee Tax at basic rate | D136: =(A131-407.92-174.17)*0.22 -> -117.89099 | E136: =IF(D136<0,0,MIN(D136,D137)) -> 0
D137: 555.68
C138: Employee Tax at lower rate | D138: =(A131-407.92)*0.1 -> -36.169816 | E138: =IF(D138<0,0,MIN(D138,D139)) -> 0
D139: 17.42
C141: Total all taxes and NI payable | E141: =SUM(E129:E139) -> 0
A144: 2006/07
A147: =($C$47+$C$48-420.33)/112.8*12.8 -> -47.697021 | B147: 0 | C147: Employers NI | E147: =MAX(A147:B147) -> 0
A149: =$C$47+$C$48-A147 -> 47.697021 | C149: Employees NI | D149: =SUM(A149-420.33)*0.11 -> -40.989628 | E149: =IF(D149<0,0,MIN(D149,D150)) -> 0
...

Sheet Nov 17
A1: 0
A2: Design-spectrum Limited
A4: Month | C4: 43040
A7: Sales Invoices | I7: Bankings - Receipts
A9: Does this months income fall within IR35? (Y/N/both) | E9: n
I10: Opening Bank Balance: | J10: Current Account | K10: 28875.31
A11: Is the Company VAT registered (Y/N) | E11: y | J11: Deposit Account | K11: 87011.69
A12: VAT Flat rate scheme percentage | E12: 0.165 | J12: (If overdrawn enter a negative figure)
A13: (leave blank or zero if not using flat rate scheme) | M13: Interest | O13: Transfers from | P13: Interest
L14: Sales Invoice | M14: Received on | O14: Deposit | P14: Received on
A15: Date | B15: Details | C15: Sales Invoice No | D15: IR35 | E15: Non IR35 | F15: Gross | G15: VAT | I15: Date | J15: Details | K15: Sales Invoice no | L15: Amount £ | M15: Current Account | N15: Other bankings | O15: Account | P15: Deposit Account
C16: Balance b/f | D16: 0 | E16: 0 | G16: 0 | J16: Balance b/f
B17: Raised in next month | D17: =IF(E$9="y",F17-G17,0) -> 0 | E17: =IF(E$9="n",F17-G17,0) -> 0 | G17: =IF(($E$11="n"),0,IF((LEFT(C17,1)="v"),F17,IF((LEFT(C17,1)="z"),0,F17*1/6))) -> 0 | J17: R S C S LTD | L17: 23100
D18: =IF(E$9="y",F18-G18,0) -> 0 | E18: =IF(E$9="n",F18-G18,0) -> 0 | G18: =IF(($E$11="n"),0,IF((LEFT(C18,1)="v"),F18,IF((LEFT(C18,1)="z"),0,F18*1/6))) -> 0 | P18: 1.43
D19: =IF(E$9="y",F19-G19,0) -> 0 | E19: =IF(E$9="n",F19-G19,0) -> 0 | G19: =IF(($E$11="n"),0,IF((LEFT(C19,1)="v"),F19,IF((LEFT(C19,1)="z"),0,F19*1/6))) -> 0
D20: =IF(E$9="y",F20-G20,0) -> 0 | E20: =IF(E$9="n",F20-G20,0) -> 0 | G20: =IF(($E$11="n"),0,IF((LEFT(C20,1)="v"),F20,IF((LEFT(C20,1)="z"),0,F20*1/6))) -> 0
D21: =IF(E$9="y",F21-G21,0) -> 0 | E21: =IF(E$9="n",F21-G21,0) -> 0 | G21: =IF(($E$11="n"),0,IF((LEFT(C21,1)="v"),F21,IF((LEFT(C21,1)="z"),0,F21*1/6))) -> 0
D22: =IF(E$9="y",F22-G22,0) -> 0 | E22: =IF(E$9="n",F22-G22,0) -> 0 | G22: =IF(($E$11="n"),0,IF((LEFT(C22,1)="v"),F22,IF((LEFT(C22,1)="z"),0,F22*1/6))) -> 0
D23: =IF(E$9="y",F23-G23,0) -> 0 | E23: =IF(E$9="n",F23-G23,0) -> 0 | G23: =IF(($E$11="n"),0,IF((LEFT(C23,1)="v"),F23,IF((LEFT(C23,1)="z"),0,F23*1/6))) -> 0
D24: =IF(E$9="y",F24-G24,0) -> 0 | E24: =IF(E$9="n",F24-G24,0) -> 0 | G24: =IF(($E$11="n"),0,IF((LEFT(C24,1)="v"),F24,IF((LEFT(C24,1)="z"),0,F24*1/6))) -> 0
D25: =IF(E$9="y",F25-G25,0) -> 0 | E25: =IF(E$9="n",F25-G25,0) -> 0 | G25: =IF(($E$11="n"),0,IF((LEFT(C25,1)="v"),F25,IF((LEFT(C25,1)="z"),0,F25*1/6))) -> 0
D26: =IF(E$9="y",F26-G26,0) -> 0 | E26: =IF(E$9="n",F26-G26,0) -> 0 | G26: =IF(($E$11="n"),0,IF((LEFT(C26,1)="v"),F26,IF((LEFT(C26,1)="z"),0,F26*1/6))) -> 0
D27: =IF(E$9="y",F27-G27,0) -> 0 | E27: =IF(E$9="n",F27-G27,0) -> 0 | G27: =IF(($E$11="n"),0,IF((LEFT(C27,1)="v"),F27,IF((LEFT(C27,1)="z"),0,F27*1/6))) -> 0
D28: =IF(E$9="y",F28-G28,0) -> 0 | E28: =IF(E$9="n",F28-G28,0) -> 0 | G28: =IF(($E$11="n"),0,IF((LEFT(C28,1)="v"),F28,IF((LEFT(C28,1)="z"),0,F28*1/6))) -> 0
D29: =IF(E$9="y",F29-G29,0) -> 0 | E29: =IF(E$9="n",F29-G29,0) -> 0 | G29: =IF(($E$11="n"),0,IF((LEFT(C29,1)="v"),F29,IF((LEFT(C29,1)="z"),0,F29*1/6))) -> 0
D30: =IF(E$9="y",F30-G30,0) -> 0 | E30: =IF(E$9="n",F30-G30,0) -> 0 | G30: =IF(($E$11="n"),0,IF((LEFT(C30,1)="v"),F30,IF((LEFT(C30,1)="z"),0,F30*1/6))) -> 0
... D40: =IF(E$9="y",F40-G40,0) -> 0 | E40: =IF(E$9="n",F40-G40,0) -> 0 | G40: =IF(($E$11="n"),0,IF((LEFT(C40,1)="v"),F40,IF((LEFT(C40,1)="z"),0,F40*1/6))) -> 0
B41: =IF(E9="Both","Enter manual values here",0) -> 0 | D41: =IF(E$9="y",F41-G41,0) -> 0 | E41: =IF(E$9="n",F41-G41,0) -> 0 | G41: =IF(($E$11="n"),0,IF((LEFT(C41,1)="v"),F41,IF((LEFT(C41,1)="z"),0,F41*1/6))) -> 0
D42: =IF(E$9="y",F42-G42,0) -> 0 | E42: =IF(E$9="n",F42-G42,0) -> 0 | G42: =IF(($E$11="n"),0,IF((LEFT(C42,1)="v"),F42,IF((LEFT(C42,1)="z"),0,F42*1/6))) -> 0
D43: =IF(E$9="y",F43-G43,0) -> 0 | E43: =IF(E$9="n",F43-G43,0) -> 0 | G43: =IF(($E$11="n"),0,IF((LEFT(C43,1)="v"),F43,IF((LEFT(C43,1)="z"),0,F43*1/6))) -> 0
D44: =IF(E$9="y",F44-G44,0) -> 0 | E44: =IF(E$9="n",F44-G44,0) -> 0 | G44: =IF(($E$11="n"),0,IF((LEFT(C44,1)="v"),F44,IF((LEFT(C44,1)="z"),0,F44*1/6))) -> 0
D45: =IF(E$9="y",F45-G45,0) -> 0 | E45: =IF(E$9="n",F45-G45,0) -> 0 | G45: =IF(($E$11="n"),0,IF((LEFT(C45,1)="v"),F45,IF((LEFT(C45,1)="z"),0,F45*1/6))) -> 0
D46: =IF(E$9="y",F46-G46,0) -> 0 | E46: =IF(E$9="n",F46-G46,0) -> 0 | G46: =IF(($E$11="n"),0,IF((LEFT(C46,1)="v"),F46,IF((LEFT(C46,1)="z"),0,F46*1/6))) -> 0
D47: =IF(E$9="y",F47-G47,0) -> 0 | E47: =IF(E$9="n",F47-G47,0) -> 0 | G47: =IF(($E$11="n"),0,IF((LEFT(C47,1)="v"),F47,IF((LEFT(C47,1)="z"),0,F47*1/6))) -> 0
D48: =IF(E$9="y",F48-G48,0) -> 0 | E48: =IF(E$9="n",F48-G48,0) -> 0 | G48: =IF(($E$11="n"),0,IF((LEFT(C48,1)="v"),F48,IF((LEFT(C48,1)="z"),0,F48*1/6))) -> 0
D49: =IF(E$9="y",F49-G49,0) -> 0 | E49: =IF(E$9="n",F49-G49,0) -> 0 | G49: =IF(($E$11="n"),0,IF((LEFT(C49,1)="v"),F49,IF((LEFT(C49,1)="z"),0,F49*1/6))) -> 0
D50: =IF(E$9="y",F50-G50,0) -> 0 | E50: =IF(E$9="n",F50-G50,0) -> 0 | G50: =IF(($E$11="n"),0,IF((LEFT(C50,1)="v"),F50,IF((LEFT(C50,1)="z"),0,F50*1/6))) -> 0
D51: =IF(E$9="y",F51-G51,0) -> 0 | E51: =IF(E$9="n",F51-G51,0) -> 0 | G51: =IF(($E$11="n"),0,IF((LEFT(C51,1)="v"),F51,IF((LEFT(C51,1)="z"),0,F51*1/6))) -> 0
D52: =IF(E$9="y",F52-G52,0) -> 0 | E52: =IF(E$9="n",F52-G52,0) -> 0 | G52: =IF(($E$11="n"),0,IF((LEFT(C52,1)="v"),F52,IF((LEFT(C52,1)="z"),0,F52*1/6))) -> 0
A53: Total | D53: =SUM(D17:D52) -> 0 | E53: =SUM(E17:E52) -> 0 | F53: =SUM(F17:F52) -> 0 | G53: =SUM(G17:G52) -> 0 | I53: Total | L53: =SUM(L17:L52) -> 23100 | M53: =SUM(M17:M52) -> 0 | N53: =SUM(N17:N52) -> 0 | O53: =SUM(O17:O52) -> 0 | P53: =SUM(P17:P52) -> 1.43
A54: C/fwd | D54: =SUM(D16:D52) -> 0 | E54: =SUM(E16:E52) -> 0 | F54: =SUM(F16:F52) -> 0 | G54: =SUM(G16:G52) -> 0 | I54: C/fwd | L54: =SUM(L16:L52) -> 23100 | M54: =SUM(M16:M52) -> 0 | N54: =SUM(N16:N52) -> 0 | O54: =SUM(O16:O52) -> 0 | P54: =SUM(P16:P52) -> 1.43
A56: IR35 Details (ignore if outside IR35): | D56: Flat Rate Scheme Details (ignore if outside FRS):
A58: Deemed Salary | C58: =IF(E9="y",G59*0.95-(SUM(H197:K197)),0) -> 0 | E58: Per List Above | F58: FRS | G58: VAT figures
A59: Deemed Salary | C59: =IF(E9="both",G59*0.95-(SUM(H197:K197)),0) -> 0 | D59: IR35 | E59: =+D53 -> 0 | F59: =+G59-E59 -> 0 | G59: =IF(E59+E60<>0,E59/(E59+E60)*(G61-G62),0) -> 0
D60: Non IR35 | E60: =+E53 -> 0 | F60: =+G60-E60 -> 0 | G60: =IF(E59+E60<>0,E60/(E59+E60)*(G61-G62),0) -> 0
D61: Gross | E61: =+F53 -> 0 | F61: =+G61-E61 -> 0 | G61: =+E61 -> 0
A62: Total PAYE & NI Due on deemed salary | C62: =IF(E243<=0,0,IF(C4<42095,E265,E243)) -> 0 | D62: VAT | E62: =+G53 -> 0 | F62: =+G62-E62 -> 0 | G62: =IF(E12>0,(G61)*E12,E62) -> 0
A63: 41730 = Numerical Value of 01 April 2014
A65: Tax provision to be made
A66: (payable by 19th April 2016) | C66: =C62 -> 0
A69: Net salary available to draw | C69: =C58+C59-C66 -> 0
A70: (after all taxes, NI and allowable expenses)
A74: Expenditure
H76: Motor | I76: Travelling, | J76: Professional, Public | P76: Printing, | S76: Computer | T76: Books, | V76: Bank Charges | X76: Transfers to | Z76: Corporation | AA76: Directors
C77: Reference / | D77: Company | E77: Cash/Personal | F77: Company | H77: Expenses Or | I77: Accommodation | J77: and Employers | K77: Company | M77: PAYE & NIC | O77: Cost of | P77: Postage & | Q77: Internet & | R77: Assets | S77: Related | T77: Journals & | V77: & Interest | X77: Deposit | Y77: VAT paid to | Z77: Tax paid to | AA77: Loan | AB77: Business
A78: Date | B78: Details | C78: Cheque No | D78: Bank | E78: Expenses | F78: Credit Card | G78: VAT | H78: Mileage Claims | I78: & Subsistence | J78: Liability Insurance | K78: Pension | L78: Net salary paid | M78: paid to HMR&C | N78: Dividends | O78: Goods sold | P78: Stationery | Q78: Telephone | R78: Purchased | S78: Costs | T78: Subscriptions | U78: Accountancy | V78: Payable | W78: Use of Home | X78: Account | Y78: HMC&E | Z78: HMR&C | AA78: Account | AB78: Entertainment | AC78: Sundries | AF78: error line?
B79: Balance b/f | E79: ='Accountant Calculations'!C54 -> 0 | F79: ='Accountant Calculations'!C57 -> 0 | AG79: =IF(AF79=0,0,"ERROR HERE") -> 0 | AH79: =IF(OR(ISERROR(+H79/($D79+$E79-$G79)*$G79+H79),LEFT(F79,1)="x"),0,+H79/($D79+$E79-$G79)*$G79+H79) -> 0 | AI79: =IF(OR(ISERROR(+I79/($D79+$E79-$G79)*$G79+I79),LEFT(G79,1)="x"),0,+I79/($D79+$E79-$G79)*$G79+I79) -> 0 | AJ79: =IF(OR(ISERROR(+J79/($D79+$E79-$G79)*$G79+J79),LEFT(H79,1)="x"),0,+J79/($D79+$E79-$G79)*$G79+J79) -> 0 | AK79: =IF(OR(ISERROR(+K79/($D79+$E79-$G79)*$G79+K79),LEFT(I79,1)="x"),0,+K79/($D79+$E79-$G79)*$G79+K79) -> 0 | AL79: =IF(OR(ISERROR(+L79/($D79+$E79-$G79)*$G79+L79),LEFT(J79,1)="x"),0,+L79/($D79+$E79-$G79)*$G79+L79) -> 0 | AM79: =IF(OR(ISERROR(+M79/($D79+$E79-$G79)*$G79+M79),LEFT(K79,1)="x"),0,+M79/($D79+$E79-$G79)*$G79+M79) -> 0 | AN79: =IF(OR(ISERROR(+N79/($D79+$E79-$G79)*$G79+N79),LEFT(L79,1)="x"),0,+N79/($D79+$E79-$G79)*$G79+N79) -> 0 | AO79: =IF(OR(ISERROR(+O79/($D79+$E79-$G79)*$G79+O79),LEFT(M79,1)="x"),0,+O79/($D79+$E79-$G79)*$G79+O79) -> 0 | ... AX79: =IF(OR(ISERROR(+X79/($D79+$E79-$G79)*$G79+X79),LEFT(V79,1)="x"),0,+X79/($D79+$E79-$G79)*$G79+X79) -> 0 | AY79: =IF(OR(ISERROR(+Z79/($D79+$E79-$G79)*$G79+Z79),LEFT(W79,1)="x"),0,+Z79/($D79+$E79-$G79)*$G79+Z79) -> 0 | AZ79: =IF(OR(ISERROR(+#REF!/($D79+$E79-$G79)*$G79+#REF!),LEFT(X79,1)="x"),0,+#REF!/($D79+$E79-$G79)*$G79+#REF!) -> 0 | BA79: =IF(OR(ISERROR(+#REF!/($D79+$E79-$G79)*$G79+#REF!),LEFT(Z79,1)="x"),0,+#REF!/($D79+$E79-$G79)*$G79+#REF!) -> 0 | BB79: =IF(OR(ISERROR(+#REF!/($D79+$E79-$G79)*$G79+#REF!),LEFT(#REF!,1)="x"),0,+#REF!/($D79+$E79-$G79)*$G79+#REF!) -> #REF! | BC79: =IF(OR(ISERROR(+AA79/($D79+$E79-$G79)*$G79+AA79),LEFT(#REF!,1)="x"),0,+AA79/($D79+$E79-$G79)*$G79+AA79) -> #REF! | BD79: =IF(OR(ISERROR(+AC79/($D79+$E79-$G79)*$G79+AC79),LEFT(#REF!,1)="x"),0,+AC79/($D79+$E79-$G79)*$G79+AC79) -> #REF!
B80: Salary Director S Haldar | D80: 924 | L80: 924 | AD80: =SUM(G80:AC80) -> 924 | AE80: =SUM(D80:F80) -> 924 | AF80: =AD80-AE80 -> 0 | AG80: =IF(AF80=0,0,"ERROR HERE") -> 0 | AH80: =IF(OR(ISERROR(+H80/($D80+$E80-$G80)*$G80+H80),LEFT(F80,1)="x"),0,+H80/($D80+$E80-$G80)*$G80+H80) -> 0 | AI80: =IF(OR(ISERROR(+I80/($D80+$E80-$G80)*$G80+I80),LEFT(G80,1)="x"),0,+I80/($D80+$E80-$G80)*$G80+I80) -> 0 | AJ80: =IF(OR(ISERROR(+J80/($D80+$E80-$G80)*$G80+J80),LEFT(H80,1)="x"),0,+J80/($D80+$E80-$G80)*$G80+J80) -> 0 | AK80: =IF(OR(ISERROR(+K80/($D80+$E80-$G80)*$G80+K80),LEFT(I80,1)="x"),0,+K80/($D80+$E80-$G80)*$G80+K80) -> 0 | AL80: =IF(OR(ISERROR(+L80/($D80+$E80-$G80)*$G80+L80),LEFT(J80,1)="x"),0,+L80/($D80+$E80-$G80)*$G80+L80) -> 924 | AM80: =IF(OR(ISERROR(+M80/($D80+$E80-$G80)*$G80+M80),LEFT(K80,1)="x"),0,+M80/($D80+$E80-$G80)*$G80+M80) -> 0 | AN80: =IF(OR(ISERROR(+N80/($D80+$E80-$G80)*$G80+N80),LEFT(L80,1)="x"),0,+N80/($D80+$E80-$G80)*$G80+N80) -> 0 | AO80: =IF(OR(ISERROR(+O80/($D80+$E80-$G80)*$G80+O80),LEFT(M80,1)="x"),0,+O80/($D80+$E80-$G80)*$G80+O80) -> 0 | ... AX80: =IF(OR(ISERROR(+X80/($D80+$E80-$G80)*$G80+X80),LEFT(V80,1)="x"),0,+X80/($D80+$E80-$G80)*$G80+X80) -> 0 | AY80: =IF(OR(ISERROR(+Z80/($D80+$E80-$G80)*$G80+Z80),LEFT(W80,1)="x"),0,+Z80/($D80+$E80-$G80)*$G80+Z80) -> 0 | AZ80: =IF(OR(ISERROR(+#REF!/($D80+$E80-$G80)*$G80+#REF!),LEFT(X80,1)="x"),0,+#REF!/($D80+$E80-$G80)*$G80+#REF!) -> 0 | BA80: =IF(OR(ISERROR(+#REF!/($D80+$E80-$G80)*$G80+#REF!),LEFT(Z80,1)="x"),0,+#REF!/($D80+$E80-$G80)*$G80+#REF!) -> 0 | BB80: =IF(OR(ISERROR(+#REF!/($D80+$E80-$G80)*$G80+#REF!),LEFT(#REF!,1)="x"),0,+#REF!/($D80+$E80-$G80)*$G80+#REF!) -> #REF! | BC80: =IF(OR(ISERROR(+AA80/($D80+$E80-$G80)*$G80+AA80),LEFT(#REF!,1)="x"),0,+AA80/($D80+$E80-$G80)*$G80+AA80) -> #REF! | BD80: =IF(OR(ISERROR(+AC80/($D80+$E80-$G80)*$G80+AC80),LEFT(#REF!,1)="x"),0,+AC80/($D80+$E80-$G80)*$G80+AC80) -> #REF!
B81: Salary Director S Deb | D81: 900 | L81: 900 | AD81: =SUM(G81:AC81) -> 900 | AE81: =SUM(D81:F81) -> 900 | AF81: =AD81-AE81 -> 0
B82: Accountancy fees | D82: 138 | U82: 138 | AD82: =SUM(G82:AC82) -> 138 | AE82: =SUM(D82:F82) -> 138 | AF82: =AD82-AE82 -> 0
B83: Bus & Tube fare | E83: 164 | I83: 164 | AD83: =SUM(G83:AC83) -> 164 | AE83: =SUM(D83:F83) -> 164 | AF83: =AD83-AE83 -> 0
B84: Postage | E84: 20 | P84: 20 | AD84: =SUM(G84:AC84) -> 20 | AE84: =SUM(D84:F84) -> 20 | AF84: =AD84-AE84 -> 0
B85: use of residence as office | E85: 95 | W85: 95 | AD85: =SUM(G85:AC85) -> 95 | AE85: =SUM(D85:F85) -> 95 | AF85: =AD85-AE85 -> 0
B86: Subscriptions | E86: 85 | T86: 85 | AD86: =SUM(G86:AC86) -> 85 | AE86: =SUM(D86:F86) -> 85 | AF86: =AD86-AE86 -> 0
B87: Motor expenses (Parking, Maintainance) | E87: 225 | H87: 225 | AD87: =SUM(G87:AC87) -> 225 | AE87: =SUM(D87:F87) -> 225 | AF87: =AD87-AE87 -> 0
B88: Business lunch | E88: 157 | AB88: 157 | AD88: =SUM(G88:AC88) -> 157 | AE88: =SUM(D88:F88) -> 157 | AF88: =AD88-AE88 -> 0
B89: Computer related costs | E89: 55 | S89: 55 | AD89: =SUM(G89:AC89) -> 55 | AE89: =SUM(D89:F89) -> 55 | AF89: =AD89-AE89 -> 0
B90: Telephone Costs | E90: 65 | R90: 65 | AD90: =SUM(G90:AC90) -> 65 | AE90: =SUM(D90:F90) -> 65 | AF90: =AD90-AE90 -> 0
B91: Insurance | E91: 35 | J91: 35 | N91: . | AD91: =SUM(G91:AC91) -> 35 | AE91: =SUM(D91:F91) -> 35 | AF91: =AD91-AE91 -> 0
B92: Bank Charges | D92: 5.5 | V92: 5.5 | AD92: =SUM(G92:AC92) -> 5.5 | AE92: =SUM(D92:F92) -> 5.5 | AF92: =AD92-AE92 -> 0
B93: Expenses reclaimed | D93: 901 | E93: -901 | AD93: =SUM(G93:AC93) -> 0 | AE93: =SUM(D93:F93) -> 0 | AF93: =AD93-AE93 -> 0
AD94: =SUM(G94:AC94) -> 0 | AE94: =SUM(D94:F94) -> 0 | AF94: =AD94-AE94 -> 0
D95: 901 | E95: -901 | AD95: =SUM(G95:AC95) -> 0 | AE95: =SUM(D95:F95) -> 0 | AF95: =AD95-AE95 -> 0
AD96: =SUM(G96:AC96) -> 0 | AE96: =SUM(D96:F96) -> 0 | AF96: =AD96-AE96 -> 0
D97: 924 | L97: 924 | AD97: =SUM(G97:AC97) -> 924 | AE97: =SUM(D97:F97) -> 924 | AF97: =AD97-AE97 -> 0
D98: 900 | L98: 900 | AD98: =SUM(G98:AC98) -> 900 | AE98: =SUM(D98:F98) -> 900 | AF98: =AD98-AE98 -> 0
AD99: =SUM(G99:AC99) -> 0 | AE99: =SUM(D99:F99) -> 0 | AF99: =AD99-AE99 -> 0
AD100: =SUM(G100:AC100) -> 0 | AE100: =SUM(D100:F100) -> 0 | AF100: =AD100-AE100 -> 0
AD101: =SUM(G101:AC101) -> 0 | AE101: =SUM(D101:F101) -> 0 | AF101: =AD101-AE101 -> 0
AD102: =SUM(G102:AC102) -> 0 | AE102: =SUM(D102:F102) -> 0 | AF102: =AD102-AE102 -> 0
AD103: =SUM(G103:AC103) -> 0 | AE103: =SUM(D103:F103) -> 0 | AF103: =AD103-AE103 -> 0
AD104: =SUM(G104:AC104) -> 0 | AE104: =SUM(D104:F104) -> 0 | AF104: =AD104-AE104 -> 0
AD105: =SUM(G105:AC105) -> 0 | AE105: =SUM(D105:F105) -> 0 | AF105: =AD105-AE105 -> 0
AD106: =SUM(G106:AC106) -> 0 | AE106: =SUM(D106:F106) -> 0 | AF106: =AD106-AE106 -> 0
AD107: =SUM(G107:AC107) -> 0 | AE107: =SUM(D107:F107) -> 0 | AF107: =AD107-AE107 -> 0
AD108: =SUM(G108:AC108) -> 0 | AE108: =SUM(D108:F108) -> 0 | AF108: =AD108-AE108 -> 0
AD109: =SUM(G109:AC109) -> 0 | AE109: =SUM(D109:F109) -> 0 | AF109: =AD109-AE109 -> 0
AD110: =SUM(G110:AC110) -> 0 | AE110: =SUM(D110:F110) -> 0 | AF110: =AD110-AE110 -> 0
... AD166: =SUM(G166:AC166) -> 0 | AE166: =SUM(D166:F166) -> 0 | AF166: =AD166-AE166 -> 0
AD167: =SUM(G167:AC167) -> 0 | AE167: =SUM(D167:F167) -> 0 | AF167: =AD167-AE167 -> 0 | AG167: =IF(AF167=0,0,"ERROR HERE") -> 0 | AH167: =IF(OR(ISERROR(+H167/($D167+$E167-$G167)*$G167+H167),LEFT(F167,1)="x"),0,+H167/($D167+$E167-$G167)*$G167+H167) -> 0 | AI167: =IF(OR(ISERROR(+I167/($D167+$E167-$G167)*$G167+I167),LEFT(G167,1)="x"),0,+I167/($D167+$E167-$G167)*$G167+I167) -> 0 | AJ167: =IF(OR(ISERROR(+J167/($D167+$E167-$G167)*$G167+J167),LEFT(H167,1)="x"),0,+J167/($D167+$E167-$G167)*$G167+J167) -> 0 | AK167: =IF(OR(ISERROR(+K167/($D167+$E167-$G167)*$G167+K167),LEFT(I167,1)="x"),0,+K167/($D167+$E167-$G167)*$G167+K167) -> 0 | AL167: =IF(OR(ISERROR(+L167/($D167+$E167-$G167)*$G167+L167),LEFT(J167,1)="x"),0,+L167/($D167+$E167-$G167)*$G167+L167) -> 0 | AM167: =IF(OR(ISERROR(+M167/($D167+$E167-$G167)*$G167+M167),LEFT(K167,1)="x"),0,+M167/($D167+$E167-$G167)*$G167+M167) -> 0 | AN167: =IF(OR(ISERROR(+N167/($D167+$E167-$G167)*$G167+N167),LEFT(L167,1)="x"),0,+N167/($D167+$E167-$G167)*$G167+N167) -> 0 | AO167: =IF(OR(ISERROR(+O167/($D167+$E167-$G167)*$G167+O167),LEFT(M167,1)="x"),0,+O167/($D167+$E167-$G167)*$G167+O167) -> 0 | ... AX167: =IF(OR(ISERROR(+X167/($D167+$E167-$G167)*$G167+X167),LEFT(V167,1)="x"),0,+X167/($D167+$E167-$G167)*$G167+X167) -> 0 | AY167: =IF(OR(ISERROR(+Z167/($D167+$E167-$G167)*$G167+Z167),LEFT(W167,1)="x"),0,+Z167/($D167+$E167-$G167)*$G167+Z167) -> 0 | AZ167: =IF(OR(ISERROR(+#REF!/($D167+$E167-$G167)*$G167+#REF!),LEFT(X167,1)="x"),0,+#REF!/($D167+$E167-$G167)*$G167+#REF!) -> 0 | BA167: =IF(OR(ISERROR(+#REF!/($D167+$E167-$G167)*$G167+#REF!),LEFT(Z167,1)="x"),0,+#REF!/($D167+$E167-$G167)*$G167+#REF!) -> 0 | BB167: =IF(OR(ISERROR(+#REF!/($D167+$E167-$G167)*$G167+#REF!),LEFT(#REF!,1)="x"),0,+#REF!/($D167+$E167-$G167)*$G167+#REF!) -> #REF! | BC167: =IF(OR(ISERROR(+AA167/($D167+$E167-$G167)*$G167+AA167),LEFT(#REF!,1)="x"),0,+AA167/($D167+$E167-$G167)*$G167+AA167) -> #REF! | BD167: =IF(OR(ISERROR(+AC167/($D167+$E167-$G167)*$G167+AC167),LEFT(#REF!,1)="x"),0,+AC167/($D167+$E167-$G167)*$G167+AC167) -> #REF!
AD168: =SUM(G168:AC168) -> 0 | AE168: =SUM(D168:F168) -> 0 | AF168: =AD168-AE168 -> 0 | AG168: =IF(AF168=0,0,"ERROR HERE - CHECK NUMBER IS CORRECTLY EXTENDED") -> 0 | AH168: =IF(OR(ISERROR(+H168/($D168+$E168-$G168)*$G168+H168),LEFT(F168,1)="x"),0,+H168/($D168+$E168-$G168)*$G168+H168) -> 0 | AI168: =IF(OR(ISERROR(+I168/($D168+$E168-$G168)*$G168+I168),LEFT(G168,1)="x"),0,+I168/($D168+$E168-$G168)*$G168+I168) -> 0 | AJ168: =IF(OR(ISERROR(+J168/($D168+$E168-$G168)*$G168+J168),LEFT(H168,1)="x"),0,+J168/($D168+$E168-$G168)*$G168+J168) -> 0 | AK168: =IF(OR(ISERROR(+K168/($D168+$E168-$G168)*$G168+K168),LEFT(I168,1)="x"),0,+K168/($D168+$E168-$G168)*$G168+K168) -> 0 | AL168: =IF(OR(ISERROR(+L168/($D168+$E168-$G168)*$G168+L168),LEFT(J168,1)="x"),0,+L168/($D168+$E168-$G168)*$G168+L168) -> 0 | AM168: =IF(OR(ISERROR(+M168/($D168+$E168-$G168)*$G168+M168),LEFT(K168,1)="x"),0,+M168/($D168+$E168-$G168)*$G168+M168) -> 0 | AN168: =IF(OR(ISERROR(+N168/($D168+$E168-$G168)*$G168+N168),LEFT(L168,1)="x"),0,+N168/($D168+$E168-$G168)*$G168+N168) -> 0 | AO168: =IF(OR(ISERROR(+O168/($D168+$E168-$G168)*$G168+O168),LEFT(M168,1)="x"),0,+O168/($D168+$E168-$G168)*$G168+O168) -> 0 | ... AX168: =IF(OR(ISERROR(+X168/($D168+$E168-$G168)*$G168+X168),LEFT(V168,1)="x"),0,+X168/($D168+$E168-$G168)*$G168+X168) -> 0 | AY168: =IF(OR(ISERROR(+Z168/($D168+$E168-$G168)*$G168+Z168),LEFT(W168,1)="x"),0,+Z168/($D168+$E168-$G168)*$G168+Z168) -> 0 | AZ168: =IF(OR(ISERROR(+#REF!/($D168+$E168-$G168)*$G168+#REF!),LEFT(X168,1)="x"),0,+#REF!/($D168+$E168-$G168)*$G168+#REF!) -> 0 | BA168: =IF(OR(ISERROR(+#REF!/($D168+$E168-$G168)*$G168+#REF!),LEFT(Z168,1)="x"),0,+#REF!/($D168+$E168-$G168)*$G168+#REF!) -> 0 | BB168: =IF(OR(ISERROR(+#REF!/($D168+$E168-$G168)*$G168+#REF!),LEFT(#REF!,1)="x"),0,+#REF!/($D168+$E168-$G168)*$G168+#REF!) -> #REF! | BC168: =IF(OR(ISERROR(+AA168/($D168+$E168-$G168)*$G168+AA168),LEFT(#REF!,1)="x"),0,+AA168/($D168+$E168-$G168)*$G168+AA168) -> #REF! | BD168: =IF(OR(ISERROR(+AB168/($D168+$E168-$G168)*$G168+AB168),LEFT(#REF!,1)="x"),0,+AB168/($D168+$E168-$G168)*$G168+AB168) -> #REF! | BE168: =IF(OR(ISERROR(+AC168/($D168+$E168-$G168)*$G168+AC168),LEFT(AA168,1)="x"),0,+AC168/($D168+$E168-$G168)*$G168+AC168) -> 0
AD169: =SUM(G169:AC169) -> 0 | AE169: =SUM(D169:F169) -> 0 | AF169: =AD169-AE169 -> 0 | AG169: =IF(AF169=0,0,"ERROR HERE") -> 0 | AH169: =IF(OR(ISERROR(+H169/($D169+$E169-$G169)*$G169+H169),LEFT(F169,1)="x"),0,+H169/($D169+$E169-$G169)*$G169+H169) -> 0 | AI169: =IF(OR(ISERROR(+I169/($D169+$E169-$G169)*$G169+I169),LEFT(G169,1)="x"),0,+I169/($D169+$E169-$G169)*$G169+I169) -> 0 | AJ169: =IF(OR(ISERROR(+J169/($D169+$E169-$G169)*$G169+J169),LEFT(H169,1)="x"),0,+J169/($D169+$E169-$G169)*$G169+J169) -> 0 | AK169: =IF(OR(ISERROR(+K169/($D169+$E169-$G169)*$G169+K169),LEFT(I169,1)="x"),0,+K169/($D169+$E169-$G169)*$G169+K169) -> 0 | AL169: =IF(OR(ISERROR(+L169/($D169+$E169-$G169)*$G169+L169),LEFT(J169,1)="x"),0,+L169/($D169+$E169-$G169)*$G169+L169) -> 0 | AM169: =IF(OR(ISERROR(+M169/($D169+$E169-$G169)*$G169+M169),LEFT(K169,1)="x"),0,+M169/($D169+$E169-$G169)*$G169+M169) -> 0 | AN169: =IF(OR(ISERROR(+N169/($D169+$E169-$G169)*$G169+N169),LEFT(L169,1)="x"),0,+N169/($D169+$E169-$G169)*$G169+N169) -> 0 | AO169: =IF(OR(ISERROR(+O169/($D169+$E169-$G169)*$G169+O169),LEFT(M169,1)="x"),0,+O169/($D169+$E169-$G169)*$G169+O169) -> 0 | ... AX169: =IF(OR(ISERROR(+X169/($D169+$E169-$G169)*$G169+X169),LEFT(V169,1)="x"),0,+X169/($D169+$E169-$G169)*$G169+X169) -> 0 | AY169: =IF(OR(ISERROR(+Z169/($D169+$E169-$G169)*$G169+Z169),LEFT(W169,1)="x"),0,+Z169/($D169+$E169-$G169)*$G169+Z169) -> 0 | AZ169: =IF(OR(ISERROR(+#REF!/($D169+$E169-$G169)*$G169+#REF!),LEFT(X169,1)="x"),0,+#REF!/($D169+$E169-$G169)*$G169+#REF!) -> 0 | BA169: =IF(OR(ISERROR(+#REF!/($D169+$E169-$G169)*$G169+#REF!),LEFT(Z169,1)="x"),0,+#REF!/($D169+$E169-$G169)*$G169+#REF!) -> 0 | BB169: =IF(OR(ISERROR(+#REF!/($D169+$E169-$G169)*$G169+#REF!),LEFT(#REF!,1)="x"),0,+#REF!/($D169+$E169-$G169)*$G169+#REF!) -> #REF! | BC169: =IF(OR(ISERROR(+AA169/($D169+$E169-$G169)*$G169+AA169),LEFT(#REF!,1)="x"),0,+AA169/($D169+$E169-$G169)*$G169+AA169) -> #REF! | BD169: =IF(OR(ISERROR(+AB169/($D169+$E169-$G169)*$G169+AB169),LEFT(#REF!,1)="x"),0,+AB169/($D169+$E169-$G169)*$G169+AB169) -> #REF! | BE169: =IF(OR(ISERROR(+AC169/($D169+$E169-$G169)*$G169+AC169),LEFT(AA169,1)="x"),0,+AC169/($D169+$E169-$G169)*$G169+AC169) -> 0
AD170: =SUM(G170:AC170) -> 0 | AE170: =SUM(D170:F170) -> 0 | AF170: =AD170-AE170 -> 0 | AG170: =IF(AF170=0,0,"ERROR HERE") -> 0 | AH170: =IF(OR(ISERROR(+H170/($D170+$E170-$G170)*$G170+H170),LEFT(F170,1)="x"),0,+H170/($D170+$E170-$G170)*$G170+H170) -> 0 | AI170: =IF(OR(ISERROR(+I170/($D170+$E170-$G170)*$G170+I170),LEFT(G170,1)="x"),0,+I170/($D170+$E170-$G170)*$G170+I170) -> 0 | AJ170: =IF(OR(ISERROR(+J170/($D170+$E170-$G170)*$G170+J170),LEFT(H170,1)="x"),0,+J170/($D170+$E170-$G170)*$G170+J170) -> 0 | AK170: =IF(OR(ISERROR(+K170/($D170+$E170-$G170)*$G170+K170),LEFT(I170,1)="x"),0,+K170/($D170+$E170-$G170)*$G170+K170) -> 0 | AL170: =IF(OR(ISERROR(+L170/($D170+$E170-$G170)*$G170+L170),LEFT(J170,1)="x"),0,+L170/($D170+$E170-$G170)*$G170+L170) -> 0 | AM170: =IF(OR(ISERROR(+M170/($D170+$E170-$G170)*$G170+M170),LEFT(K170,1)="x"),0,+M170/($D170+$E170-$G170)*$G170+M170) -> 0 | AN170: =IF(OR(ISERROR(+N170/($D170+$E170-$G170)*$G170+N170),LEFT(L170,1)="x"),0,+N170/($D170+$E170-$G170)*$G170+N170) -> 0 | AO170: =IF(OR(ISERROR(+O170/($D170+$E170-$G170)*$G170+O170),LEFT(M170,1)="x"),0,+O170/($D170+$E170-$G170)*$G170+O170) -> 0 | ... AX170: =IF(OR(ISERROR(+X170/($D170+$E170-$G170)*$G170+X170),LEFT(V170,1)="x"),0,+X170/($D170+$E170-$G170)*$G170+X170) -> 0 | AY170: =IF(OR(ISERROR(+Z170/($D170+$E170-$G170)*$G170+Z170),LEFT(W170,1)="x"),0,+Z170/($D170+$E170-$G170)*$G170+Z170) -> 0 | AZ170: =IF(OR(ISERROR(+#REF!/($D170+$E170-$G170)*$G170+#REF!),LEFT(X170,1)="x"),0,+#REF!/($D170+$E170-$G170)*$G170+#REF!) -> 0 | BA170: =IF(OR(ISERROR(+#REF!/($D170+$E170-$G170)*$G170+#REF!),LEFT(Z170,1)="x"),0,+#REF!/($D170+$E170-$G170)*$G170+#REF!) -> 0 | BB170: =IF(OR(ISERROR(+#REF!/($D170+$E170-$G170)*$G170+#REF!),LEFT(#REF!,1)="x"),0,+#REF!/($D170+$E170-$G170)*$G170+#REF!) -> #REF! | BC170: =IF(OR(ISERROR(+AA170/($D170+$E170-$G170)*$G170+AA170),LEFT(#REF!,1)="x"),0,+AA170/($D170+$E170-$G170)*$G170+AA170) -> #REF! | BD170: =IF(OR(ISERROR(+AB170/($D170+$E170-$G170)*$G170+AB170),LEFT(#REF!,1)="x"),0,+AB170/($D170+$E170-$G170)*$G170+AB170) -> #REF! | BE170: =IF(OR(ISERROR(+AC170/($D170+$E170-$G170)*$G170+AC170),LEFT(AA170,1)="x"),0,+AC170/($D170+$E170-$G170)*$G170+AC170) -> 0
AD171: =SUM(G171:AC171) -> 0 | AE171: =SUM(D171:F171) -> 0 | AF171: =AD171-AE171 -> 0 | AG171: =IF(AF171=0,0,"ERROR HERE") -> 0 | AH171: =IF(OR(ISERROR(+H171/($D171+$E171-$G171)*$G171+H171),LEFT(F171,1)="x"),0,+H171/($D171+$E171-$G171)*$G171+H171) -> 0 | AI171: =IF(OR(ISERROR(+I171/($D171+$E171-$G171)*$G171+I171),LEFT(G171,1)="x"),0,+I171/($D171+$E171-$G171)*$G171+I171) -> 0 | AJ171: =IF(OR(ISERROR(+J171/($D171+$E171-$G171)*$G171+J171),LEFT(H171,1)="x"),0,+J171/($D171+$E171-$G171)*$G171+J171) -> 0 | AK171: =IF(OR(ISERROR(+K171/($D171+$E171-$G171)*$G171+K171),LEFT(I171,1)="x"),0,+K171/($D171+$E171-$G171)*$G171+K171) -> 0 | AL171: =IF(OR(ISERROR(+L171/($D171+$E171-$G171)*$G171+L171),LEFT(J171,1)="x"),0,+L171/($D171+$E171-$G171)*$G171+L171) -> 0 | AM171: =IF(OR(ISERROR(+M171/($D171+$E171-$G171)*$G171+M171),LEFT(K171,1)="x"),0,+M171/($D171+$E171-$G171)*$G171+M171) -> 0 | AN171: =IF(OR(ISERROR(+N171/($D171+$E171-$G171)*$G171+N171),LEFT(L171,1)="x"),0,+N171/($D171+$E171-$G171)*$G171+N171) -> 0 | AO171: =IF(OR(ISERROR(+O171/($D171+$E171-$G171)*$G171+O171),LEFT(M171,1)="x"),0,+O171/($D171+$E171-$G171)*$G171+O171) -> 0 | ... AX171: =IF(OR(ISERROR(+X171/($D171+$E171-$G171)*$G171+X171),LEFT(V171,1)="x"),0,+X171/($D171+$E171-$G171)*$G171+X171) -> 0 | AY171: =IF(OR(ISERROR(+Z171/($D171+$E171-$G171)*$G171+Z171),LEFT(W171,1)="x"),0,+Z171/($D171+$E171-$G171)*$G171+Z171) -> 0 | AZ171: =IF(OR(ISERROR(+#REF!/($D171+$E171-$G171)*$G171+#REF!),LEFT(X171,1)="x"),0,+#REF!/($D171+$E171-$G171)*$G171+#REF!) -> 0 | BA171: =IF(OR(ISERROR(+#REF!/($D171+$E171-$G171)*$G171+#REF!),LEFT(Z171,1)="x"),0,+#REF!/($D171+$E171-$G171)*$G171+#REF!) -> 0 | BB171: =IF(OR(ISERROR(+#REF!/($D171+$E171-$G171)*$G171+#REF!),LEFT(#REF!,1)="x"),0,+#REF!/($D171+$E171-$G171)*$G171+#REF!) -> #REF! | BC171: =IF(OR(ISERROR(+AA171/($D171+$E171-$G171)*$G171+AA171),LEFT(#REF!,1)="x"),0,+AA171/($D171+$E171-$G171)*$G171+AA171) -> #REF! | BD171: =IF(OR(ISERROR(+AB171/($D171+$E171-$G171)*$G171+AB171),LEFT(#REF!,1)="x"),0,+AB171/($D171+$E171-$G171)*$G171+AB171) -> #REF! | BE171: =IF(OR(ISERROR(+AC171/($D171+$E171-$G171)*$G171+AC171),LEFT(AA171,1)="x"),0,+AC171/($D171+$E171-$G171)*$G171+AC171) -> 0
AD172: =SUM(G172:AC172) -> 0 | AE172: =SUM(D172:F172) -> 0 | AF172: =AD172-AE172 -> 0 | AG172: =IF(AF172=0,0,"ERROR HERE") -> 0 | AH172: =IF(OR(ISERROR(+H172/($D172+$E172-$G172)*$G172+H172),LEFT(F172,1)="x"),0,+H172/($D172+$E172-$G172)*$G172+H172) -> 0 | AI172: =IF(OR(ISERROR(+I172/($D172+$E172-$G172)*$G172+I172),LEFT(G172,1)="x"),0,+I172/($D172+$E172-$G172)*$G172+I172) -> 0 | AJ172: =IF(OR(ISERROR(+J172/($D172+$E172-$G172)*$G172+J172),LEFT(H172,1)="x"),0,+J172/($D172+$E172-$G172)*$G172+J172) -> 0 | AK172: =IF(OR(ISERROR(+K172/($D172+$E172-$G172)*$G172+K172),LEFT(I172,1)="x"),0,+K172/($D172+$E172-$G172)*$G172+K172) -> 0 | AL172: =IF(OR(ISERROR(+L172/($D172+$E172-$G172)*$G172+L172),LEFT(J172,1)="x"),0,+L172/($D172+$E172-$G172)*$G172+L172) -> 0 | AM172: =IF(OR(ISERROR(+M172/($D172+$E172-$G172)*$G172+M172),LEFT(K172,1)="x"),0,+M172/($D172+$E172-$G172)*$G172+M172) -> 0 | AN172: =IF(OR(ISERROR(+N172/($D172+$E172-$G172)*$G172+N172),LEFT(L172,1)="x"),0,+N172/($D172+$E172-$G172)*$G172+N172) -> 0 | AO172: =IF(OR(ISERROR(+O172/($D172+$E172-$G172)*$G172+O172),LEFT(M172,1)="x"),0,+O172/($D172+$E172-$G172)*$G172+O172) -> 0 | ... AX172: =IF(OR(ISERROR(+X172/($D172+$E172-$G172)*$G172+X172),LEFT(V172,1)="x"),0,+X172/($D172+$E172-$G172)*$G172+X172) -> 0 | AY172: =IF(OR(ISERROR(+Z172/($D172+$E172-$G172)*$G172+Z172),LEFT(W172,1)="x"),0,+Z172/($D172+$E172-$G172)*$G172+Z172) -> 0 | AZ172: =IF(OR(ISERROR(+#REF!/($D172+$E172-$G172)*$G172+#REF!),LEFT(X172,1)="x"),0,+#REF!/($D172+$E172-$G172)*$G172+#REF!) -> 0 | BA172: =IF(OR(ISERROR(+#REF!/($D172+$E172-$G172)*$G172+#REF!),LEFT(Z172,1)="x"),0,+#REF!/($D172+$E172-$G172)*$G172+#REF!) -> 0 | BB172: =IF(OR(ISERROR(+#REF!/($D172+$E172-$G172)*$G172+#REF!),LEFT(#REF!,1)="x"),0,+#REF!/($D172+$E172-$G172)*$G172+#REF!) -> #REF! | BC172: =IF(OR(ISERROR(+AA172/($D172+$E172-$G172)*$G172+AA172),LEFT(#REF!,1)="x"),0,+AA172/($D172+$E172-$G172)*$G172+AA172) -> #REF! | BD172: =IF(OR(ISERROR(+AB172/($D172+$E172-$G172)*$G172+AB172),LEFT(#REF!,1)="x"),0,+AB172/($D172+$E172-$G172)*$G172+AB172) -> #REF! | BE172: =IF(OR(ISERROR(+AC172/($D172+$E172-$G172)*$G172+AC172),LEFT(AA172,1)="x"),0,+AC172/($D172+$E172-$G172)*$G172+AC172) -> 0
AD173: =SUM(G173:AC173) -> 0 | AE173: =SUM(D173:F173) -> 0 | AF173: =AD173-AE173 -> 0 | AG173: =IF(AF173=0,0,"ERROR HERE") -> 0 | AH173: =IF(OR(ISERROR(+H173/($D173+$E173-$G173)*$G173+H173),LEFT(F173,1)="x"),0,+H173/($D173+$E173-$G173)*$G173+H173) -> 0 | AI173: =IF(OR(ISERROR(+I173/($D173+$E173-$G173)*$G173+I173),LEFT(G173,1)="x"),0,+I173/($D173+$E173-$G173)*$G173+I173) -> 0 | AJ173: =IF(OR(ISERROR(+J173/($D173+$E173-$G173)*$G173+J173),LEFT(H173,1)="x"),0,+J173/($D173+$E173-$G173)*$G173+J173) -> 0 | AK173: =IF(OR(ISERROR(+K173/($D173+$E173-$G173)*$G173+K173),LEFT(I173,1)="x"),0,+K173/($D173+$E173-$G173)*$G173+K173) -> 0 | AL173: =IF(OR(ISERROR(+L173/($D173+$E173-$G173)*$G173+L173),LEFT(J173,1)="x"),0,+L173/($D173+$E173-$G173)*$G173+L173) -> 0 | AM173: =IF(OR(ISERROR(+M173/($D173+$E173-$G173)*$G173+M173),LEFT(K173,1)="x"),0,+M173/($D173+$E173-$G173)*$G173+M173) -> 0 | AN173: =IF(OR(ISERROR(+N173/($D173+$E173-$G173)*$G173+N173),LEFT(L173,1)="x"),0,+N173/($D173+$E173-$G173)*$G173+N173) -> 0 | AO173: =IF(OR(ISERROR(+O173/($D173+$E173-$G173)*$G173+O173),LEFT(M173,1)="x"),0,+O173/($D173+$E173-$G173)*$G173+O173) -> 0 | ... AX173: =IF(OR(ISERROR(+X173/($D173+$E173-$G173)*$G173+X173),LEFT(V173,1)="x"),0,+X173/($D173+$E173-$G173)*$G173+X173) -> 0 | AY173: =IF(OR(ISERROR(+Z173/($D173+$E173-$G173)*$G173+Z173),LEFT(W173,1)="x"),0,+Z173/($D173+$E173-$G173)*$G173+Z173) -> 0 | AZ173: =IF(OR(ISERROR(+#REF!/($D173+$E173-$G173)*$G173+#REF!),LEFT(X173,1)="x"),0,+#REF!/($D173+$E173-$G173)*$G173+#REF!) -> 0 | BA173: =IF(OR(ISERROR(+#REF!/($D173+$E173-$G173)*$G173+#REF!),LEFT(Z173,1)="x"),0,+#REF!/($D173+$E173-$G173)*$G173+#REF!) -> 0 | BB173: =IF(OR(ISERROR(+#REF!/($D173+$E173-$G173)*$G173+#REF!),LEFT(#REF!,1)="x"),0,+#REF!/($D173+$E173-$G173)*$G173+#REF!) -> #REF! | BC173: =IF(OR(ISERROR(+AA173/($D173+$E173-$G173)*$G173+AA173),LEFT(#REF!,1)="x"),0,+AA173/($D173+$E173-$G173)*$G173+AA173) -> #REF! | BD173: =IF(OR(ISERROR(+AB173/($D173+$E173-$G173)*$G173+AB173),LEFT(#REF!,1)="x"),0,+AB173/($D173+$E173-$G173)*$G173+AB173) -> #REF! | BE173: =IF(OR(ISERROR(+AC173/($D173+$E173-$G173)*$G173+AC173),LEFT(AA173,1)="x"),0,+AC173/($D173+$E173-$G173)*$G173+AC173) -> 0
AD174: =SUM(G174:AC174) -> 0 | AE174: =SUM(D174:F174) -> 0 | AF174: =AD174-AE174 -> 0 | AG174: =IF(AF174=0,0,"ERROR HERE") -> 0 | AH174: =IF(OR(ISERROR(+H174/($D174+$E174-$G174)*$G174+H174),LEFT(F174,1)="x"),0,+H174/($D174+$E174-$G174)*$G174+H174) -> 0 | AI174: =IF(OR(ISERROR(+I174/($D174+$E174-$G174)*$G174+I174),LEFT(G174,1)="x"),0,+I174/($D174+$E174-$G174)*$G174+I174) -> 0 | AJ174: =IF(OR(ISERROR(+J174/($D174+$E174-$G174)*$G174+J174),LEFT(H174,1)="x"),0,+J174/($D174+$E174-$G174)*$G174+J174) -> 0 | AK174: =IF(OR(ISERROR(+K174/($D174+$E174-$G174)*$G174+K174),LEFT(I174,1)="x"),0,+K174/($D174+$E174-$G174)*$G174+K174) -> 0 | AL174: =IF(OR(ISERROR(+L174/($D174+$E174-$G174)*$G174+L174),LEFT(J174,1)="x"),0,+L174/($D174+$E174-$G174)*$G174+L174) -> 0 | AM174: =IF(OR(ISERROR(+M174/($D174+$E174-$G174)*$G174+M174),LEFT(K174,1)="x"),0,+M174/($D174+$E174-$G174)*$G174+M174) -> 0 | AN174: =IF(OR(ISERROR(+N174/($D174+$E174-$G174)*$G174+N174),LEFT(L174,1)="x"),0,+N174/($D174+$E174-$G174)*$G174+N174) -> 0 | AO174: =IF(OR(ISERROR(+O174/($D174+$E174-$G174)*$G174+O174),LEFT(M174,1)="x"),0,+O174/($D174+$E174-$G174)*$G174+O174) -> 0 | ... AX174: =IF(OR(ISERROR(+X174/($D174+$E174-$G174)*$G174+X174),LEFT(V174,1)="x"),0,+X174/($D174+$E174-$G174)*$G174+X174) -> 0 | AY174: =IF(OR(ISERROR(+Z174/($D174+$E174-$G174)*$G174+Z174),LEFT(W174,1)="x"),0,+Z174/($D174+$E174-$G174)*$G174+Z174) -> 0 | AZ174: =IF(OR(ISERROR(+#REF!/($D174+$E174-$G174)*$G174+#REF!),LEFT(X174,1)="x"),0,+#REF!/($D174+$E174-$G174)*$G174+#REF!) -> 0 | BA174: =IF(OR(ISERROR(+#REF!/($D174+$E174-$G174)*$G174+#REF!),LEFT(Z174,1)="x"),0,+#REF!/($D174+$E174-$G174)*$G174+#REF!) -> 0 | BB174: =IF(OR(ISERROR(+#REF!/($D174+$E174-$G174)*$G174+#REF!),LEFT(#REF!,1)="x"),0,+#REF!/($D174+$E174-$G174)*$G174+#REF!) -> #REF! | BC174: =IF(OR(ISERROR(+AA174/($D174+$E174-$G174)*$G174+AA174),LEFT(#REF!,1)="x"),0,+AA174/($D174+$E174-$G174)*$G174+AA174) -> #REF! | BD174: =IF(OR(ISERROR(+AB174/($D174+$E174-$G174)*$G174+AB174),LEFT(#REF!,1)="x"),0,+AB174/($D174+$E174-$G174)*$G174+AB174) -> #REF! | BE174: =IF(OR(ISERROR(+AC174/($D174+$E174-$G174)*$G174+AC174),LEFT(AA174,1)="x"),0,+AC174/($D174+$E174-$G174)*$G174+AC174) -> 0
AD175: =SUM(G175:AC175) -> 0 | AE175: =SUM(D175:F175) -> 0 | AF175: =AD175-AE175 -> 0 | AG175: =IF(AF175=0,0,"ERROR HERE") -> 0 | AH175: =IF(OR(ISERROR(+H175/($D175+$E175-$G175)*$G175+H175),LEFT(F175,1)="x"),0,+H175/($D175+$E175-$G175)*$G175+H175) -> 0 | AI175: =IF(OR(ISERROR(+I175/($D175+$E175-$G175)*$G175+I175),LEFT(G175,1)="x"),0,+I175/($D175+$E175-$G175)*$G175+I175) -> 0 | AJ175: =IF(OR(ISERROR(+J175/($D175+$E175-$G175)*$G175+J175),LEFT(H175,1)="x"),0,+J175/($D175+$E175-$G175)*$G175+J175) -> 0 | AK175: =IF(OR(ISERROR(+K175/($D175+$E175-$G175)*$G175+K175),LEFT(I175,1)="x"),0,+K175/($D175+$E175-$G175)*$G175+K175) -> 0 | AL175: =IF(OR(ISERROR(+L175/($D175+$E175-$G175)*$G175+L175),LEFT(J175,1)="x"),0,+L175/($D175+$E175-$G175)*$G175+L175) -> 0 | AM175: =IF(OR(ISERROR(+M175/($D175+$E175-$G175)*$G175+M175),LEFT(K175,1)="x"),0,+M175/($D175+$E175-$G175)*$G175+M175) -> 0 | AN175: =IF(OR(ISERROR(+N175/($D175+$E175-$G175)*$G175+N175),LEFT(L175,1)="x"),0,+N175/($D175+$E175-$G175)*$G175+N175) -> 0 | AO175: =IF(OR(ISERROR(+O175/($D175+$E175-$G175)*$G175+O175),LEFT(M175,1)="x"),0,+O175/($D175+$E175-$G175)*$G175+O175) -> 0 | ... AX175: =IF(OR(ISERROR(+X175/($D175+$E175-$G175)*$G175+X175),LEFT(V175,1)="x"),0,+X175/($D175+$E175-$G175)*$G175+X175) -> 0 | AY175: =IF(OR(ISERROR(+Z175/($D175+$E175-$G175)*$G175+Z175),LEFT(W175,1)="x"),0,+Z175/($D175+$E175-$G175)*$G175+Z175) -> 0 | AZ175: =IF(OR(ISERROR(+#REF!/($D175+$E175-$G175)*$G175+#REF!),LEFT(X175,1)="x"),0,+#REF!/($D175+$E175-$G175)*$G175+#REF!) -> 0 | BA175: =IF(OR(ISERROR(+#REF!/($D175+$E175-$G175)*$G175+#REF!),LEFT(Z175,1)="x"),0,+#REF!/($D175+$E175-$G175)*$G175+#REF!) -> 0 | BB175: =IF(OR(ISERROR(+#REF!/($D175+$E175-$G175)*$G175+#REF!),LEFT(#REF!,1)="x"),0,+#REF!/($D175+$E175-$G175)*$G175+#REF!) -> #REF! | BC175: =IF(OR(ISERROR(+AA175/($D175+$E175-$G175)*$G175+AA175),LEFT(#REF!,1)="x"),0,+AA175/($D175+$E175-$G175)*$G175+AA175) -> #REF! | BD175: =IF(OR(ISERROR(+AB175/($D175+$E175-$G175)*$G175+AB175),LEFT(#REF!,1)="x"),0,+AB175/($D175+$E175-$G175)*$G175+AB175) -> #REF! | BE175: =IF(OR(ISERROR(+AC175/($D175+$E175-$G175)*$G175+AC175),LEFT(AA175,1)="x"),0,+AC175/($D175+$E175-$G175)*$G175+AC175) -> 0
AD176: =SUM(G176:AC176) -> 0 | AE176: =SUM(D176:F176) -> 0 | AF176: =AD176-AE176 -> 0 | AG176: =IF(AF176=0,0,"ERROR HERE") -> 0 | AH176: =IF(OR(ISERROR(+H176/($D176+$E176-$G176)*$G176+H176),LEFT(F176,1)="x"),0,+H176/($D176+$E176-$G176)*$G176+H176) -> 0 | AI176: =IF(OR(ISERROR(+I176/($D176+$E176-$G176)*$G176+I176),LEFT(G176,1)="x"),0,+I176/($D176+$E176-$G176)*$G176+I176) -> 0 | AJ176: =IF(OR(ISERROR(+J176/($D176+$E176-$G176)*$G176+J176),LEFT(H176,1)="x"),0,+J176/($D176+$E176-$G176)*$G176+J176) -> 0 | AK176: =IF(OR(ISERROR(+K176/($D176+$E176-$G176)*$G176+K176),LEFT(I176,1)="x"),0,+K176/($D176+$E176-$G176)*$G176+K176) -> 0 | AL176: =IF(OR(ISERROR(+L176/($D176+$E176-$G176)*$G176+L176),LEFT(J176,1)="x"),0,+L176/($D176+$E176-$G176)*$G176+L176) -> 0 | AM176: =IF(OR(ISERROR(+M176/($D176+$E176-$G176)*$G176+M176),LEFT(K176,1)="x"),0,+M176/($D176+$E176-$G176)*$G176+M176) -> 0 | AN176: =IF(OR(ISERROR(+N176/($D176+$E176-$G176)*$G176+N176),LEFT(L176,1)="x"),0,+N176/($D176+$E176-$G176)*$G176+N176) -> 0 | AO176: =IF(OR(ISERROR(+O176/($D176+$E176-$G176)*$G176+O176),LEFT(M176,1)="x"),0,+O176/($D176+$E176-$G176)*$G176+O176) -> 0 | ... AX176: =IF(OR(ISERROR(+X176/($D176+$E176-$G176)*$G176+X176),LEFT(V176,1)="x"),0,+X176/($D176+$E176-$G176)*$G176+X176) -> 0 | AY176: =IF(OR(ISERROR(+Z176/($D176+$E176-$G176)*$G176+Z176),LEFT(W176,1)="x"),0,+Z176/($D176+$E176-$G176)*$G176+Z176) -> 0 | AZ176: =IF(OR(ISERROR(+#REF!/($D176+$E176-$G176)*$G176+#REF!),LEFT(X176,1)="x"),0,+#REF!/($D176+$E176-$G176)*$G176+#REF!) -> 0 | BA176: =IF(OR(ISERROR(+#REF!/($D176+$E176-$G176)*$G176+#REF!),LEFT(Z176,1)="x"),0,+#REF!/($D176+$E176-$G176)*$G176+#REF!) -> 0 | BB176: =IF(OR(ISERROR(+#REF!/($D176+$E176-$G176)*$G176+#REF!),LEFT(#REF!,1)="x"),0,+#REF!/($D176+$E176-$G176)*$G176+#REF!) -> #REF! | BC176: =IF(OR(ISERROR(+AA176/($D176+$E176-$G176)*$G176+AA176),LEFT(#REF!,1)="x"),0,+AA176/($D176+$E176-$G176)*$G176+AA176) -> #REF! | BD176: =IF(OR(ISERROR(+AB176/($D176+$E176-$G176)*$G176+AB176),LEFT(#REF!,1)="x"),0,+AB176/($D176+$E176-$G176)*$G176+AB176) -> #REF! | BE176: =IF(OR(ISERROR(+AC176/($D176+$E176-$G176)*$G176+AC176),LEFT(AA176,1)="x"),0,+AC176/($D176+$E176-$G176)*$G176+AC176) -> 0
AD177: =SUM(G177:AC177) -> 0 | AE177: =SUM(D177:F177) -> 0 | AF177: =AD177-AE177 -> 0 | AG177: =IF(AF177=0,0,"ERROR HERE") -> 0 | AH177: =IF(OR(ISERROR(+H177/($D177+$E177-$G177)*$G177+H177),LEFT(F177,1)="x"),0,+H177/($D177+$E177-$G177)*$G177+H177) -> 0 | AI177: =IF(OR(ISERROR(+I177/($D177+$E177-$G177)*$G177+I177),LEFT(G177,1)="x"),0,+I177/($D177+$E177-$G177)*$G177+I177) -> 0 | AJ177: =IF(OR(ISERROR(+J177/($D177+$E177-$G177)*$G177+J177),LEFT(H177,1)="x"),0,+J177/($D177+$E177-$G177)*$G177+J177) -> 0 | AK177: =IF(OR(ISERROR(+K177/($D177+$E177-$G177)*$G177+K177),LEFT(I177,1)="x"),0,+K177/($D177+$E177-$G177)*$G177+K177) -> 0 | AL177: =IF(OR(ISERROR(+L177/($D177+$E177-$G177)*$G177+L177),LEFT(J177,1)="x"),0,+L177/($D177+$E177-$G177)*$G177+L177) -> 0 | AM177: =IF(OR(ISERROR(+M177/($D177+$E177-$G177)*$G177+M177),LEFT(K177,1)="x"),0,+M177/($D177+$E177-$G177)*$G177+M177) -> 0 | AN177: =IF(OR(ISERROR(+N177/($D177+$E177-$G177)*$G177+N177),LEFT(L177,1)="x"),0,+N177/($D177+$E177-$G177)*$G177+N177) -> 0 | AO177: =IF(OR(ISERROR(+O177/($D177+$E177-$G177)*$G177+O177),LEFT(M177,1)="x"),0,+O177/($D177+$E177-$G177)*$G177+O177) -> 0 | ... AX177: =IF(OR(ISERROR(+X177/($D177+$E177-$G177)*$G177+X177),LEFT(V177,1)="x"),0,+X177/($D177+$E177-$G177)*$G177+X177) -> 0 | AY177: =IF(OR(ISERROR(+Z177/($D177+$E177-$G177)*$G177+Z177),LEFT(W177,1)="x"),0,+Z177/($D177+$E177-$G177)*$G177+Z177) -> 0 | AZ177: =IF(OR(ISERROR(+#REF!/($D177+$E177-$G177)*$G177+#REF!),LEFT(X177,1)="x"),0,+#REF!/($D177+$E177-$G177)*$G177+#REF!) -> 0 | BA177: =IF(OR(ISERROR(+#REF!/($D177+$E177-$G177)*$G177+#REF!),LEFT(Z177,1)="x"),0,+#REF!/($D177+$E177-$G177)*$G177+#REF!) -> 0 | BB177: =IF(OR(ISERROR(+#REF!/($D177+$E177-$G177)*$G177+#REF!),LEFT(#REF!,1)="x"),0,+#REF!/($D177+$E177-$G177)*$G177+#REF!) -> #REF! | BC177: =IF(OR(ISERROR(+AA177/($D177+$E177-$G177)*$G177+AA177),LEFT(#REF!,1)="x"),0,+AA177/($D177+$E177-$G177)*$G177+AA177) -> #REF! | BD177: =IF(OR(ISERROR(+AB177/($D177+$E177-$G177)*$G177+AB177),LEFT(#REF!,1)="x"),0,+AB177/($D177+$E177-$G177)*$G177+AB177) -> #REF! | BE177: =IF(OR(ISERROR(+AC177/($D177+$E177-$G177)*$G177+AC177),LEFT(AA177,1)="x"),0,+AC177/($D177+$E177-$G177)*$G177+AC177) -> 0
...

Sheet Dec 17
A1: 0
A2: ='Nov 17'!A2 -> Design-spectrum Limited
A4: Month | C4: ='Nov 17'!C4+31 -> 43071
A7: Sales Invoices | I7: Bankings - Receipts
A9: Does this months income fall within IR35? (Y/N/both) | E9: ='Nov 17'!E9 -> n | F9: =IF(E9="Both","enter sales invoices manually at row 30 onwards",0) -> 0
A11: Is the Company VAT registered (Y/N) | E11: ='Nov 17'!E11 -> y
A12: VAT Flat rate scheme percentage | E12: ='Nov 17'!E12 -> 0.165
A13: (leave blank or zero if not using flat rate scheme) | M13: Interest | O13: Transfers from | P13: Interest
L14: Sales Invoice | M14: Received on | O14: Deposit | P14: Received on
A15: Date | B15: Details | C15: Sales Invoice No | D15: IR35 | E15: Non IR35 | F15: Gross | G15: VAT | I15: Date | J15: Details | K15: Sales Invoice no | L15: Amount £ | M15: Current Account | N15: Other bankings | O15: Account | P15: Deposit Account
C16: Balance b/f | D16: ='Nov 17'!D54 -> 0 | E16: ='Nov 17'!E54 -> 0 | F16: ='Nov 17'!F54 -> 0 | G16: ='Nov 17'!G54 -> 0 | J16: Balance b/f | L16: ='Nov 17'!L54 -> 23100 | M16: ='Nov 17'!M54 -> 0 | N16: ='Nov 17'!N54 -> 0 | O16: ='Nov 17'!O54 -> 0 | P16: ='Nov 17'!P54 -> 1.43
B17: Invoice 30Oct-8Dec2017 | D17: =IF(E$9="y",F17-G17,0) -> 0 | E17: =IF(E$9="n",F17-G17,0) -> 16500 | F17: 19800 | G17: =IF(($E$11="n"),0,IF((LEFT(C17,1)="v"),F17,IF((LEFT(C17,1)="z"),0,F17*1/6))) -> 3300 | J17: MONEY MARKET MATURITY 40029090709255 | O17: 50488.86
B18: Invoice 11Dec-15Dec2017 | D18: =IF(E$9="y",F18-G18,0) -> 0 | E18: =IF(E$9="n",F18-G18,0) -> 2750 | F18: 3300 | G18: =IF(($E$11="n"),0,IF((LEFT(C18,1)="v"),F18,IF((LEFT(C18,1)="z"),0,F18*1/6))) -> 550 | J18: GROSS INTEREST TO 03DEC2017 FOR ACCOUNT 400290 90709255 | M18: 66.53 | P18: -66.53
D19: =IF(E$9="y",F19-G19,0) -> 0 | E19: =IF(E$9="n",F19-G19,0) -> 0 | G19: =IF(($E$11="n"),0,IF((LEFT(C19,1)="v"),F19,IF((LEFT(C19,1)="z"),0,F19*1/6))) -> 0 | J19: R S C S LTD | L19: 19800
D20: =IF(E$9="y",F20-G20,0) -> 0 | E20: =IF(E$9="n",F20-G20,0) -> 0 | G20: =IF(($E$11="n"),0,IF((LEFT(C20,1)="v"),F20,IF((LEFT(C20,1)="z"),0,F20*1/6))) -> 0 | P20: 1.52
D21: =IF(E$9="y",F21-G21,0) -> 0 | E21: =IF(E$9="n",F21-G21,0) -> 0 | G21: =IF(($E$11="n"),0,IF((LEFT(C21,1)="v"),F21,IF((LEFT(C21,1)="z"),0,F21*1/6))) -> 0
D22: =IF(E$9="y",F22-G22,0) -> 0 | E22: =IF(E$9="n",F22-G22,0) -> 0 | G22: =IF(($E$11="n"),0,IF((LEFT(C22,1)="v"),F22,IF((LEFT(C22,1)="z"),0,F22*1/6))) -> 0
D23: =IF(E$9="y",F23-G23,0) -> 0 | E23: =IF(E$9="n",F23-G23,0) -> 0 | G23: =IF(($E$11="n"),0,IF((LEFT(C23,1)="v"),F23,IF((LEFT(C23,1)="z"),0,F23*1/6))) -> 0
D24: =IF(E$9="y",F24-G24,0) -> 0 | E24: =IF(E$9="n",F24-G24,0) -> 0 | G24: =IF(($E$11="n"),0,IF((LEFT(C24,1)="v"),F24,IF((LEFT(C24,1)="z"),0,F24*1/6))) -> 0
D25: =IF(E$9="y",F25-G25,0) -> 0 | E25: =IF(E$9="n",F25-G25,0) -> 0 | G25: =IF(($E$11="n"),0,IF((LEFT(C25,1)="v"),F25,IF((LEFT(C25,1)="z"),0,F25*1/6))) -> 0
D26: =IF(E$9="y",F26-G26,0) -> 0 | E26: =IF(E$9="n",F26-G26,0) -> 0 | G26: =IF(($E$11="n"),0,IF((LEFT(C26,1)="v"),F26,IF((LEFT(C26,1)="z"),0,F26*1/6))) -> 0
D27: =IF(E$9="y",F27-G27,0) -> 0 | E27: =IF(E$9="n",F27-G27,0) -> 0 | G27: =IF(($E$11="n"),0,IF((LEFT(C27,1)="v"),F27,IF((LEFT(C27,1)="z"),0,F27*1/6))) -> 0
D28: =IF(E$9="y",F28-G28,0) -> 0 | E28: =IF(E$9="n",F28-G28,0) -> 0 | G28: =IF(($E$11="n"),0,IF((LEFT(C28,1)="v"),F28,IF((LEFT(C28,1)="z"),0,F28*1/6))) -> 0
D29: =IF(E$9="y",F29-G29,0) -> 0 | E29: =IF(E$9="n",F29-G29,0) -> 0 | G29: =IF(($E$11="n"),0,IF((LEFT(C29,1)="v"),F29,IF((LEFT(C29,1)="z"),0,F29*1/6))) -> 0
D30: =IF(E$9="y",F30-G30,0) -> 0 | E30: =IF(E$9="n",F30-G30,0) -> 0 | G30: =IF(($E$11="n"),0,IF((LEFT(C30,1)="v"),F30,IF((LEFT(C30,1)="z"),0,F30*1/6))) -> 0
D31: =IF(E$9="y",F31-G31,0) -> 0 | E31: =IF(E$9="n",F31-G31,0) -> 0 | G31: =IF(($E$11="n"),0,IF((LEFT(C31,1)="v"),F31,IF((LEFT(C31,1)="z"),0,F31*1/6))) -> 0
D32: =IF(E$9="y",F32-G32,0) -> 0 | E32: =IF(E$9="n",F32-G32,0) -> 0 | G32: =IF(($E$11="n"),0,IF((LEFT(C32,1)="v"),F32,IF((LEFT(C32,1)="z"),0,F32*1/6))) -> 0
... D40: =IF(E$9="y",F40-G40,0) -> 0 | E40: =IF(E$9="n",F40-G40,0) -> 0 | G40: =IF(($E$11="n"),0,IF((LEFT(C40,1)="v"),F40,IF((LEFT(C40,1)="z"),0,F40*1/6))) -> 0
B41: =IF(E9="Both","Enter manual values here",0) -> 0 | D41: =IF(E$9="y",F41-G41,0) -> 0 | E41: =IF(E$9="n",F41-G41,0) -> 0 | G41: =IF(($E$11="n"),0,IF((LEFT(C41,1)="v"),F41,IF((LEFT(C41,1)="z"),0,F41*1/6))) -> 0
D42: =IF(E$9="y",F42-G42,0) -> 0 | E42: =IF(E$9="n",F42-G42,0) -> 0 | G42: =IF(($E$11="n"),0,IF((LEFT(C42,1)="v"),F42,IF((LEFT(C42,1)="z"),0,F42*1/6))) -> 0
D43: =IF(E$9="y",F43-G43,0) -> 0 | E43: =IF(E$9="n",F43-G43,0) -> 0 | G43: =IF(($E$11="n"),0,IF((LEFT(C43,1)="v"),F43,IF((LEFT(C43,1)="z"),0,F43*1/6))) -> 0
D44: =IF(E$9="y",F44-G44,0) -> 0 | E44: =IF(E$9="n",F44-G44,0) -> 0 | G44: =IF(($E$11="n"),0,IF((LEFT(C44,1)="v"),F44,IF((LEFT(C44,1)="z"),0,F44*1/6))) -> 0
D45: =IF(E$9="y",F45-G45,0) -> 0 | E45: =IF(E$9="n",F45-G45,0) -> 0 | G45: =IF(($E$11="n"),0,IF((LEFT(C45,1)="v"),F45,IF((LEFT(C45,1)="z"),0,F45*1/6))) -> 0
D46: =IF(E$9="y",F46-G46,0) -> 0 | E46: =IF(E$9="n",F46-G46,0) -> 0 | G46: =IF(($E$11="n"),0,IF((LEFT(C46,1)="v"),F46,IF((LEFT(C46,1)="z"),0,F46*1/6))) -> 0
D47: =IF(E$9="y",F47-G47,0) -> 0 | E47: =IF(E$9="n",F47-G47,0) -> 0 | G47: =IF(($E$11="n"),0,IF((LEFT(C47,1)="v"),F47,IF((LEFT(C47,1)="z"),0,F47*1/6))) -> 0
D48: =IF(E$9="y",F48-G48,0) -> 0 | E48: =IF(E$9="n",F48-G48,0) -> 0 | G48: =IF(($E$11="n"),0,IF((LEFT(C48,1)="v"),F48,IF((LEFT(C48,1)="z"),0,F48*1/6))) -> 0
D49: =IF(E$9="y",F49-G49,0) -> 0 | E49: =IF(E$9="n",F49-G49,0) -> 0 | G49: =IF(($E$11="n"),0,IF((LEFT(C49,1)="v"),F49,IF((LEFT(C49,1)="z"),0,F49*1/6))) -> 0
D50: =IF(E$9="y",F50-G50,0) -> 0 | E50: =IF(E$9="n",F50-G50,0) -> 0 | G50: =IF(($E$11="n"),0,IF((LEFT(C50,1)="v"),F50,IF((LEFT(C50,1)="z"),0,F50*1/6))) -> 0
D51: =IF(E$9="y",F51-G51,0) -> 0 | E51: =IF(E$9="n",F51-G51,0) -> 0 | G51: =IF(($E$11="n"),0,IF((LEFT(C51,1)="v"),F51,IF((LEFT(C51,1)="z"),0,F51*1/6))) -> 0
D52: =IF(E$9="y",F52-G52,0) -> 0 | E52: =IF(E$9="n",F52-G52,0) -> 0 | G52: =IF(($E$11="n"),0,IF((LEFT(C52,1)="v"),F52,IF((LEFT(C52,1)="z"),0,F52*1/6))) -> 0
A53: Total | D53: =SUM(D17:D52) -> 0 | E53: =SUM(E17:E52) -> 19250 | F53: =SUM(F17:F52) -> 23100 | G53: =SUM(G17:G52) -> 3850 | I53: Total | L53: =SUM(L17:L52) -> 19800 | M53: =SUM(M17:M52) -> 66.53 | N53: =SUM(N17:N52) -> 0 | O53: =SUM(O17:O52) -> 50488.86 | P53: =SUM(P17:P52) -> -65.01
A54: C/fwd | D54: =SUM(D16:D52) -> 0 | E54: =SUM(E16:E52) -> 19250 | F54: =SUM(F16:F52) -> 23100 | G54: =SUM(G16:G52) -> 3850 | I54: C/fwd | L54: =SUM(L16:L52) -> 42900 | M54: =SUM(M16:M52) -> 66.53 | N54: =SUM(N16:N52) -> 0 | O54: =SUM(O16:O52) -> 50488.86 | P54: =SUM(P16:P52) -> -63.58
A56: IR35 Details (ignore if outside IR35): | D56: Flat Rate Scheme Details (ignore if outside FRS):
A58: Deemed Salary | C58: =IF(E9="y",G59*0.95-(SUM(H197:K197)),0) -> 0 | E58: Per List Above | F58: FRS | G58: VAT account figures
A59: Deemed Salary | C59: =IF(E9="both",G59*0.95-(SUM(H197:K197)),0) -> 0 | D59: IR35 | E59: =+D53 -> 0 | F59: =+G59-E59 -> 0 | G59: =IF(E59+E60<>0,E59/(E59+E60)*(G61-G62),0) -> 0
D60: Non IR35 | E60: =+E53 -> 19250 | F60: =+G60-E60 -> 38.5 | G60: =IF(E59+E60<>0,E60/(E59+E60)*(G61-G62),0) -> 19288.5
D61: Gross | E61: =+F53 -> 23100 | F61: =+G61-E61 -> 0 | G61: =+E61 -> 23100
A62: Total PAYE & NI Due on deemed salary | C62: =IF(E243<=0,0,IF(C4<42095,E265,E243)) -> 0 | D62: VAT | E62: =+G53 -> 3850 | F62: =+G62-E62 -> -38.5 | G62: =IF(E12>0,(G61)*E12,E62) -> 3811.5
A63: 41730 = Numerical Value of 01 April 2014
A65: Tax provision to be made
A66: (payable by 19th April 2016) | C66: =C62 -> 0
A69: Net salary available to draw | C69: =C58+C59-C66 -> 0
A70: (after all taxes, NI and allowable expenses)
A74: Expenditure
H76: Motor | I76: Travelling, | J76: Professional, Public | P76: Printing, | S76: Computer | T76: Books, | V76: Bank Charges | X76: Transfers to | Z76: Corporation | AA76: Directors
C77: Reference / | D77: Company | E77: Cash/Personal | F77: Company | H77: Expenses Or | I77: Accommodation | J77: and Employers | K77: Company | M77: PAYE & NIC | O77: Cost of | P77: Postage & | Q77: Internet & | R77: Assets | S77: Related | T77: Journals & | V77: & Interest | X77: Deposit | Y77: VAT paid to | Z77: Tax paid to | AA77: Loan | AB77: Business
A78: Date | B78: Details | C78: Cheque No | D78: Bank | E78: Expenses | F78: Credit Card | G78: VAT | H78: Mileage Claims | I78: & Subsistence | J78: Liability Insurance | K78: Pension | L78: Net salary paid | M78: paid to HMR&C | N78: Dividends | O78: Goods sold | P78: Stationery | Q78: Telephone | R78: Purchased | S78: Costs | T78: Subscriptions | U78: Accountancy | V78: Payable | W78: Use of Home | X78: Account | Y78: HMC&E | Z78: HMR&C | AA78: Account | AB78: Entertainment | AC78: Sundries | AF78: error line?
B79: Balance b/f | D79: ='Nov 17'!D198 -> 5593.5 | E79: ='Nov 17'!E198 -> -901 | F79: ='Nov 17'!F198 -> 0 | G79: ='Nov 17'!G198 -> 0 | H79: ='Nov 17'!H198 -> 225 | I79: ='Nov 17'!I198 -> 164 | J79: ='Nov 17'!J198 -> 35 | K79: ='Nov 17'!K198 -> 0 | ... AC79: ='Nov 17'!AC198 -> 0 | AG79: =IF(AF79=0,0,"ERROR HERE") -> 0 | AH79: =IF(OR(ISERROR(+H79/($D79+$E79-$G79)*$G79+H79),LEFT(F79,1)="x"),0,+H79/($D79+$E79-$G79)*$G79+H79) -> 225 | AI79: =IF(OR(ISERROR(+I79/($D79+$E79-$G79)*$G79+I79),LEFT(G79,1)="x"),0,+I79/($D79+$E79-$G79)*$G79+I79) -> 164 | AJ79: =IF(OR(ISERROR(+J79/($D79+$E79-$G79)*$G79+J79),LEFT(H79,1)="x"),0,+J79/($D79+$E79-$G79)*$G79+J79) -> 35 | AK79: =IF(OR(ISERROR(+K79/($D79+$E79-$G79)*$G79+K79),LEFT(I79,1)="x"),0,+K79/($D79+$E79-$G79)*$G79+K79) -> 0 | AL79: =IF(OR(ISERROR(+L79/($D79+$E79-$G79)*$G79+L79),LEFT(J79,1)="x"),0,+L79/($D79+$E79-$G79)*$G79+L79) -> 3648 | AM79: =IF(OR(ISERROR(+M79/($D79+$E79-$G79)*$G79+M79),LEFT(K79,1)="x"),0,+M79/($D79+$E79-$G79)*$G79+M79) -> 0 | AN79: =IF(OR(ISERROR(+N79/($D79+$E79-$G79)*$G79+N79),LEFT(L79,1)="x"),0,+N79/($D79+$E79-$G79)*$G79+N79) -> 0 | AO79: =IF(OR(ISERROR(+O79/($D79+$E79-$G79)*$G79+O79),LEFT(M79,1)="x"),0,+O79/($D79+$E79-$G79)*$G79+O79) -> 0 | ... BB79: =IF(OR(ISERROR(+AB79/($D79+$E79-$G79)*$G79+AB79),LEFT(Z79,1)="x"),0,+AB79/($D79+$E79-$G79)*$G79+AB79) -> 157 | BC79: =IF(OR(ISERROR(+#REF!/($D79+$E79-$G79)*$G79+#REF!),LEFT(AA79,1)="x"),0,+#REF!/($D79+$E79-$G79)*$G79+#REF!) -> 0 | BD79: =IF(OR(ISERROR(+AC79/($D79+$E79-$G79)*$G79+AC79),LEFT(Z79,1)="x"),0,+AC79/($D79+$E79-$G79)*$G79+AC79) -> 0
B80: Salary Director S Haldar | D80: 924 | L80: 924 | AD80: =SUM(G80:AC80) -> 924 | AE80: =SUM(D80:F80) -> 924 | AF80: =AD80-AE80 -> 0 | AG80: =IF(AF80=0,0,"ERROR HERE") -> 0 | AH80: =IF(OR(ISERROR(+H80/($D80+$E80-$G80)*$G80+H80),LEFT(F80,1)="x"),0,+H80/($D80+$E80-$G80)*$G80+H80) -> 0 | AI80: =IF(OR(ISERROR(+I80/($D80+$E80-$G80)*$G80+I80),LEFT(G80,1)="x"),0,+I80/($D80+$E80-$G80)*$G80+I80) -> 0 | AJ80: =IF(OR(ISERROR(+J80/($D80+$E80-$G80)*$G80+J80),LEFT(H80,1)="x"),0,+J80/($D80+$E80-$G80)*$G80+J80) -> 0 | AK80: =IF(OR(ISERROR(+K80/($D80+$E80-$G80)*$G80+K80),LEFT(I80,1)="x"),0,+K80/($D80+$E80-$G80)*$G80+K80) -> 0 | AL80: =IF(OR(ISERROR(+L80/($D80+$E80-$G80)*$G80+L80),LEFT(J80,1)="x"),0,+L80/($D80+$E80-$G80)*$G80+L80) -> 924 | AM80: =IF(OR(ISERROR(+M80/($D80+$E80-$G80)*$G80+M80),LEFT(K80,1)="x"),0,+M80/($D80+$E80-$G80)*$G80+M80) -> 0 | AN80: =IF(OR(ISERROR(+N80/($D80+$E80-$G80)*$G80+N80),LEFT(L80,1)="x"),0,+N80/($D80+$E80-$G80)*$G80+N80) -> 0 | AO80: =IF(OR(ISERROR(+O80/($D80+$E80-$G80)*$G80+O80),LEFT(M80,1)="x"),0,+O80/($D80+$E80-$G80)*$G80+O80) -> 0 | ... BB80: =IF(OR(ISERROR(+AB80/($D80+$E80-$G80)*$G80+AB80),LEFT(Z80,1)="x"),0,+AB80/($D80+$E80-$G80)*$G80+AB80) -> 0 | BC80: =IF(OR(ISERROR(+#REF!/($D80+$E80-$G80)*$G80+#REF!),LEFT(AA80,1)="x"),0,+#REF!/($D80+$E80-$G80)*$G80+#REF!) -> 0 | BD80: =IF(OR(ISERROR(+AC80/($D80+$E80-$G80)*$G80+AC80),LEFT(Z80,1)="x"),0,+AC80/($D80+$E80-$G80)*$G80+AC80) -> 0
B81: Salary Director S Deb | D81: 900 | L81: 900 | AD81: =SUM(G81:AC81) -> 900 | AE81: =SUM(D81:F81) -> 900 | AF81: =AD81-AE81 -> 0 | AG81: =IF(AF81=0,0,"ERROR HERE") -> 0 | AH81: =IF(OR(ISERROR(+H81/($D81+$E81-$G81)*$G81+H81),LEFT(F81,1)="x"),0,+H81/($D81+$E81-$G81)*$G81+H81) -> 0 | AI81: =IF(OR(ISERROR(+I81/($D81+$E81-$G81)*$G81+I81),LEFT(G81,1)="x"),0,+I81/($D81+$E81-$G81)*$G81+I81) -> 0 | AJ81: =IF(OR(ISERROR(+J81/($D81+$E81-$G81)*$G81+J81),LEFT(H81,1)="x"),0,+J81/($D81+$E81-$G81)*$G81+J81) -> 0 | AK81: =IF(OR(ISERROR(+K81/($D81+$E81-$G81)*$G81+K81),LEFT(I81,1)="x"),0,+K81/($D81+$E81-$G81)*$G81+K81) -> 0 | AL81: =IF(OR(ISERROR(+L81/($D81+$E81-$G81)*$G81+L81),LEFT(J81,1)="x"),0,+L81/($D81+$E81-$G81)*$G81+L81) -> 900 | AM81: =IF(OR(ISERROR(+M81/($D81+$E81-$G81)*$G81+M81),LEFT(K81,1)="x"),0,+M81/($D81+$E81-$G81)*$G81+M81) -> 0 | AN81: =IF(OR(ISERROR(+N81/($D81+$E81-$G81)*$G81+N81),LEFT(L81,1)="x"),0,+N81/($D81+$E81-$G81)*$G81+N81) -> 0 | AO81: =IF(OR(ISERROR(+O81/($D81+$E81-$G81)*$G81+O81),LEFT(M81,1)="x"),0,+O81/($D81+$E81-$G81)*$G81+O81) -> 0 | ... BB81: =IF(OR(ISERROR(+AB81/($D81+$E81-$G81)*$G81+AB81),LEFT(Z81,1)="x"),0,+AB81/($D81+$E81-$G81)*$G81+AB81) -> 0 | BC81: =IF(OR(ISERROR(+#REF!/($D81+$E81-$G81)*$G81+#REF!),LEFT(AA81,1)="x"),0,+#REF!/($D81+$E81-$G81)*$G81+#REF!) -> 0 | BD81: =IF(OR(ISERROR(+AC81/($D81+$E81-$G81)*$G81+AC81),LEFT(Z81,1)="x"),0,+AC81/($D81+$E81-$G81)*$G81+AC81) -> 0
B82: Accountancy fees | D82: 138 | U82: 138 | AD82: =SUM(G82:AC82) -> 138 | AE82: =SUM(D82:F82) -> 138 | AF82: =AD82-AE82 -> 0 | AG82: =IF(AF82=0,0,"ERROR HERE - CHECK NUMBER IS CORRECTLY EXTENDED") -> 0 | AH82: =IF(OR(ISERROR(+H82/($D82+$E82-$G82)*$G82+H82),LEFT(F82,1)="x"),0,+H82/($D82+$E82-$G82)*$G82+H82) -> 0 | AI82: =IF(OR(ISERROR(+I82/($D82+$E82-$G82)*$G82+I82),LEFT(G82,1)="x"),0,+I82/($D82+$E82-$G82)*$G82+I82) -> 0 | AJ82: =IF(OR(ISERROR(+J82/($D82+$E82-$G82)*$G82+J82),LEFT(H82,1)="x"),0,+J82/($D82+$E82-$G82)*$G82+J82) -> 0 | AK82: =IF(OR(ISERROR(+K82/($D82+$E82-$G82)*$G82+K82),LEFT(I82,1)="x"),0,+K82/($D82+$E82-$G82)*$G82+K82) -> 0 | AL82: =IF(OR(ISERROR(+L82/($D82+$E82-$G82)*$G82+L82),LEFT(J82,1)="x"),0,+L82/($D82+$E82-$G82)*$G82+L82) -> 0 | AM82: =IF(OR(ISERROR(+M82/($D82+$E82-$G82)*$G82+M82),LEFT(K82,1)="x"),0,+M82/($D82+$E82-$G82)*$G82+M82) -> 0 | AN82: =IF(OR(ISERROR(+N82/($D82+$E82-$G82)*$G82+N82),LEFT(L82,1)="x"),0,+N82/($D82+$E82-$G82)*$G82+N82) -> 0 | AO82: =IF(OR(ISERROR(+O82/($D82+$E82-$G82)*$G82+O82),LEFT(M82,1)="x"),0,+O82/($D82+$E82-$G82)*$G82+O82) -> 0 | ... BB82: =IF(OR(ISERROR(+AB82/($D82+$E82-$G82)*$G82+AB82),LEFT(Z82,1)="x"),0,+AB82/($D82+$E82-$G82)*$G82+AB82) -> 0 | BC82: =IF(OR(ISERROR(+#REF!/($D82+$E82-$G82)*$G82+#REF!),LEFT(AA82,1)="x"),0,+#REF!/($D82+$E82-$G82)*$G82+#REF!) -> 0 | BD82: =IF(OR(ISERROR(+#REF!/($D82+$E82-$G82)*$G82+#REF!),LEFT(AB82,1)="x"),0,+#REF!/($D82+$E82-$G82)*$G82+#REF!) -> 0 | BE82: =IF(OR(ISERROR(+AC82/($D82+$E82-$G82)*$G82+AC82),LEFT(#REF!,1)="x"),0,+AC82/($D82+$E82-$G82)*$G82+AC82) -> #REF!
B83: Bus & Tube fare | E83: 164 | I83: 164 | AD83: =SUM(G83:AC83) -> 164 | AE83: =SUM(D83:F83) -> 164 | AF83: =AD83-AE83 -> 0 | AG83: =IF(AF83=0,0,"ERROR HERE") -> 0 | AH83: =IF(OR(ISERROR(+H83/($D83+$E83-$G83)*$G83+H83),LEFT(F83,1)="x"),0,+H83/($D83+$E83-$G83)*$G83+H83) -> 0 | AI83: =IF(OR(ISERROR(+I83/($D83+$E83-$G83)*$G83+I83),LEFT(G83,1)="x"),0,+I83/($D83+$E83-$G83)*$G83+I83) -> 164 | AJ83: =IF(OR(ISERROR(+J83/($D83+$E83-$G83)*$G83+J83),LEFT(H83,1)="x"),0,+J83/($D83+$E83-$G83)*$G83+J83) -> 0 | AK83: =IF(OR(ISERROR(+K83/($D83+$E83-$G83)*$G83+K83),LEFT(I83,1)="x"),0,+K83/($D83+$E83-$G83)*$G83+K83) -> 0 | AL83: =IF(OR(ISERROR(+L83/($D83+$E83-$G83)*$G83+L83),LEFT(J83,1)="x"),0,+L83/($D83+$E83-$G83)*$G83+L83) -> 0 | AM83: =IF(OR(ISERROR(+M83/($D83+$E83-$G83)*$G83+M83),LEFT(K83,1)="x"),0,+M83/($D83+$E83-$G83)*$G83+M83) -> 0 | AN83: =IF(OR(ISERROR(+N83/($D83+$E83-$G83)*$G83+N83),LEFT(L83,1)="x"),0,+N83/($D83+$E83-$G83)*$G83+N83) -> 0 | AO83: =IF(OR(ISERROR(+O83/($D83+$E83-$G83)*$G83+O83),LEFT(M83,1)="x"),0,+O83/($D83+$E83-$G83)*$G83+O83) -> 0 | ... BB83: =IF(OR(ISERROR(+AB83/($D83+$E83-$G83)*$G83+AB83),LEFT(Z83,1)="x"),0,+AB83/($D83+$E83-$G83)*$G83+AB83) -> 0 | BC83: =IF(OR(ISERROR(+#REF!/($D83+$E83-$G83)*$G83+#REF!),LEFT(AA83,1)="x"),0,+#REF!/($D83+$E83-$G83)*$G83+#REF!) -> 0 | BD83: =IF(OR(ISERROR(+#REF!/($D83+$E83-$G83)*$G83+#REF!),LEFT(AB83,1)="x"),0,+#REF!/($D83+$E83-$G83)*$G83+#REF!) -> 0 | BE83: =IF(OR(ISERROR(+AC83/($D83+$E83-$G83)*$G83+AC83),LEFT(#REF!,1)="x"),0,+AC83/($D83+$E83-$G83)*$G83+AC83) -> #REF!
B84: Postage | E84: 20 | P84: 20 | AD84: =SUM(G84:AC84) -> 20 | AE84: =SUM(D84:F84) -> 20 | AF84: =AD84-AE84 -> 0 | AG84: =IF(AF84=0,0,"ERROR HERE") -> 0 | AH84: =IF(OR(ISERROR(+H84/($D84+$E84-$G84)*$G84+H84),LEFT(F84,1)="x"),0,+H84/($D84+$E84-$G84)*$G84+H84) -> 0 | AI84: =IF(OR(ISERROR(+I84/($D84+$E84-$G84)*$G84+I84),LEFT(G84,1)="x"),0,+I84/($D84+$E84-$G84)*$G84+I84) -> 0 | AJ84: =IF(OR(ISERROR(+J84/($D84+$E84-$G84)*$G84+J84),LEFT(H84,1)="x"),0,+J84/($D84+$E84-$G84)*$G84+J84) -> 0 | AK84: =IF(OR(ISERROR(+K84/($D84+$E84-$G84)*$G84+K84),LEFT(I84,1)="x"),0,+K84/($D84+$E84-$G84)*$G84+K84) -> 0 | AL84: =IF(OR(ISERROR(+L84/($D84+$E84-$G84)*$G84+L84),LEFT(J84,1)="x"),0,+L84/($D84+$E84-$G84)*$G84+L84) -> 0 | AM84: =IF(OR(ISERROR(+M84/($D84+$E84-$G84)*$G84+M84),LEFT(K84,1)="x"),0,+M84/($D84+$E84-$G84)*$G84+M84) -> 0 | AN84: =IF(OR(ISERROR(+N84/($D84+$E84-$G84)*$G84+N84),LEFT(L84,1)="x"),0,+N84/($D84+$E84-$G84)*$G84+N84) -> 0 | AO84: =IF(OR(ISERROR(+O84/($D84+$E84-$G84)*$G84+O84),LEFT(M84,1)="x"),0,+O84/($D84+$E84-$G84)*$G84+O84) -> 0 | ... BB84: =IF(OR(ISERROR(+AB84/($D84+$E84-$G84)*$G84+AB84),LEFT(Z84,1)="x"),0,+AB84/($D84+$E84-$G84)*$G84+AB84) -> 0 | BC84: =IF(OR(ISERROR(+#REF!/($D84+$E84-$G84)*$G84+#REF!),LEFT(AA84,1)="x"),0,+#REF!/($D84+$E84-$G84)*$G84+#REF!) -> 0 | BD84: =IF(OR(ISERROR(+#REF!/($D84+$E84-$G84)*$G84+#REF!),LEFT(AB84,1)="x"),0,+#REF!/($D84+$E84-$G84)*$G84+#REF!) -> 0 | BE84: =IF(OR(ISERROR(+AC84/($D84+$E84-$G84)*$G84+AC84),LEFT(#REF!,1)="x"),0,+AC84/($D84+$E84-$G84)*$G84+AC84) -> #REF!
B85: use of residence as office | E85: 95 | W85: 95 | AD85: =SUM(G85:AC85) -> 95 | AE85: =SUM(D85:F85) -> 95 | AF85: =AD85-AE85 -> 0 | AG85: =IF(AF85=0,0,"ERROR HERE") -> 0 | AH85: =IF(OR(ISERROR(+H85/($D85+$E85-$G85)*$G85+H85),LEFT(F85,1)="x"),0,+H85/($D85+$E85-$G85)*$G85+H85) -> 0 | AI85: =IF(OR(ISERROR(+I85/($D85+$E85-$G85)*$G85+I85),LEFT(G85,1)="x"),0,+I85/($D85+$E85-$G85)*$G85+I85) -> 0 | AJ85: =IF(OR(ISERROR(+J85/($D85+$E85-$G85)*$G85+J85),LEFT(H85,1)="x"),0,+J85/($D85+$E85-$G85)*$G85+J85) -> 0 | AK85: =IF(OR(ISERROR(+K85/($D85+$E85-$G85)*$G85+K85),LEFT(I85,1)="x"),0,+K85/($D85+$E85-$G85)*$G85+K85) -> 0 | AL85: =IF(OR(ISERROR(+L85/($D85+$E85-$G85)*$G85+L85),LEFT(J85,1)="x"),0,+L85/($D85+$E85-$G85)*$G85+L85) -> 0 | AM85: =IF(OR(ISERROR(+M85/($D85+$E85-$G85)*$G85+M85),LEFT(K85,1)="x"),0,+M85/($D85+$E85-$G85)*$G85+M85) -> 0 | AN85: =IF(OR(ISERROR(+N85/($D85+$E85-$G85)*$G85+N85),LEFT(L85,1)="x"),0,+N85/($D85+$E85-$G85)*$G85+N85) -> 0 | AO85: =IF(OR(ISERROR(+O85/($D85+$E85-$G85)*$G85+O85),LEFT(M85,1)="x"),0,+O85/($D85+$E85-$G85)*$G85+O85) -> 0 | ... BB85: =IF(OR(ISERROR(+AB85/($D85+$E85-$G85)*$G85+AB85),LEFT(Z85,1)="x"),0,+AB85/($D85+$E85-$G85)*$G85+AB85) -> 0 | BC85: =IF(OR(ISERROR(+#REF!/($D85+$E85-$G85)*$G85+#REF!),LEFT(AA85,1)="x"),0,+#REF!/($D85+$E85-$G85)*$G85+#REF!) -> 0 | BD85: =IF(OR(ISERROR(+#REF!/($D85+$E85-$G85)*$G85+#REF!),LEFT(AB85,1)="x"),0,+#REF!/($D85+$E85-$G85)*$G85+#REF!) -> 0 | BE85: =IF(OR(ISERROR(+AC85/($D85+$E85-$G85)*$G85+AC85),LEFT(#REF!,1)="x"),0,+AC85/($D85+$E85-$G85)*$G85+AC85) -> #REF!
B86: Subscriptions | E86: 85 | T86: 85 | AD86: =SUM(G86:AC86) -> 85 | AE86: =SUM(D86:F86) -> 85 | AF86: =AD86-AE86 -> 0 | AG86: =IF(AF86=0,0,"ERROR HERE") -> 0 | AH86: =IF(OR(ISERROR(+H86/($D86+$E86-$G86)*$G86+H86),LEFT(F86,1)="x"),0,+H86/($D86+$E86-$G86)*$G86+H86) -> 0 | AI86: =IF(OR(ISERROR(+I86/($D86+$E86-$G86)*$G86+I86),LEFT(G86,1)="x"),0,+I86/($D86+$E86-$G86)*$G86+I86) -> 0 | AJ86: =IF(OR(ISERROR(+J86/($D86+$E86-$G86)*$G86+J86),LEFT(H86,1)="x"),0,+J86/($D86+$E86-$G86)*$G86+J86) -> 0 | AK86: =IF(OR(ISERROR(+K86/($D86+$E86-$G86)*$G86+K86),LEFT(I86,1)="x"),0,+K86/($D86+$E86-$G86)*$G86+K86) -> 0 | AL86: =IF(OR(ISERROR(+L86/($D86+$E86-$G86)*$G86+L86),LEFT(J86,1)="x"),0,+L86/($D86+$E86-$G86)*$G86+L86) -> 0 | AM86: =IF(OR(ISERROR(+M86/($D86+$E86-$G86)*$G86+M86),LEFT(K86,1)="x"),0,+M86/($D86+$E86-$G86)*$G86+M86) -> 0 | AN86: =IF(OR(ISERROR(+N86/($D86+$E86-$G86)*$G86+N86),LEFT(L86,1)="x"),0,+N86/($D86+$E86-$G86)*$G86+N86) -> 0 | AO86: =IF(OR(ISERROR(+O86/($D86+$E86-$G86)*$G86+O86),LEFT(M86,1)="x"),0,+O86/($D86+$E86-$G86)*$G86+O86) -> 0 | ... BB86: =IF(OR(ISERROR(+AB86/($D86+$E86-$G86)*$G86+AB86),LEFT(Z86,1)="x"),0,+AB86/($D86+$E86-$G86)*$G86+AB86) -> 0 | BC86: =IF(OR(ISERROR(+#REF!/($D86+$E86-$G86)*$G86+#REF!),LEFT(AA86,1)="x"),0,+#REF!/($D86+$E86-$G86)*$G86+#REF!) -> 0 | BD86: =IF(OR(ISERROR(+#REF!/($D86+$E86-$G86)*$G86+#REF!),LEFT(AB86,1)="x"),0,+#REF!/($D86+$E86-$G86)*$G86+#REF!) -> 0 | BE86: =IF(OR(ISERROR(+AC86/($D86+$E86-$G86)*$G86+AC86),LEFT(#REF!,1)="x"),0,+AC86/($D86+$E86-$G86)*$G86+AC86) -> #REF!
B87: Motor expenses (Parking, Maintainance) | E87: 225 | H87: 225 | AD87: =SUM(G87:AC87) -> 225 | AE87: =SUM(D87:F87) -> 225 | AF87: =AD87-AE87 -> 0 | AG87: =IF(AF87=0,0,"ERROR HERE") -> 0 | AH87: =IF(OR(ISERROR(+H87/($D87+$E87-$G87)*$G87+H87),LEFT(F87,1)="x"),0,+H87/($D87+$E87-$G87)*$G87+H87) -> 225 | AI87: =IF(OR(ISERROR(+I87/($D87+$E87-$G87)*$G87+I87),LEFT(G87,1)="x"),0,+I87/($D87+$E87-$G87)*$G87+I87) -> 0 | AJ87: =IF(OR(ISERROR(+J87/($D87+$E87-$G87)*$G87+J87),LEFT(H87,1)="x"),0,+J87/($D87+$E87-$G87)*$G87+J87) -> 0 | AK87: =IF(OR(ISERROR(+K87/($D87+$E87-$G87)*$G87+K87),LEFT(I87,1)="x"),0,+K87/($D87+$E87-$G87)*$G87+K87) -> 0 | AL87: =IF(OR(ISERROR(+L87/($D87+$E87-$G87)*$G87+L87),LEFT(J87,1)="x"),0,+L87/($D87+$E87-$G87)*$G87+L87) -> 0 | AM87: =IF(OR(ISERROR(+M87/($D87+$E87-$G87)*$G87+M87),LEFT(K87,1)="x"),0,+M87/($D87+$E87-$G87)*$G87+M87) -> 0 | AN87: =IF(OR(ISERROR(+N87/($D87+$E87-$G87)*$G87+N87),LEFT(L87,1)="x"),0,+N87/($D87+$E87-$G87)*$G87+N87) -> 0 | AO87: =IF(OR(ISERROR(+O87/($D87+$E87-$G87)*$G87+O87),LEFT(M87,1)="x"),0,+O87/($D87+$E87-$G87)*$G87+O87) -> 0 | ... BB87: =IF(OR(ISERROR(+AB87/($D87+$E87-$G87)*$G87+AB87),LEFT(Z87,1)="x"),0,+AB87/($D87+$E87-$G87)*$G87+AB87) -> 0 | BC87: =IF(OR(ISERROR(+#REF!/($D87+$E87-$G87)*$G87+#REF!),LEFT(AA87,1)="x"),0,+#REF!/($D87+$E87-$G87)*$G87+#REF!) -> 0 | BD87: =IF(OR(ISERROR(+#REF!/($D87+$E87-$G87)*$G87+#REF!),LEFT(AB87,1)="x"),0,+#REF!/($D87+$E87-$G87)*$G87+#REF!) -> 0 | BE87: =IF(OR(ISERROR(+AC87/($D87+$E87-$G87)*$G87+AC87),LEFT(#REF!,1)="x"),0,+AC87/($D87+$E87-$G87)*$G87+AC87) -> #REF!
B88: Business lunch | E88: 157 | AB88: 157 | AD88: =SUM(G88:AC88) -> 157 | AE88: =SUM(D88:F88) -> 157 | AF88: =AD88-AE88 -> 0 | AG88: =IF(AF88=0,0,"ERROR HERE") -> 0 | AH88: =IF(OR(ISERROR(+H88/($D88+$E88-$G88)*$G88+H88),LEFT(F88,1)="x"),0,+H88/($D88+$E88-$G88)*$G88+H88) -> 0 | AI88: =IF(OR(ISERROR(+I88/($D88+$E88-$G88)*$G88+I88),LEFT(G88,1)="x"),0,+I88/($D88+$E88-$G88)*$G88+I88) -> 0 | AJ88: =IF(OR(ISERROR(+J88/($D88+$E88-$G88)*$G88+J88),LEFT(H88,1)="x"),0,+J88/($D88+$E88-$G88)*$G88+J88) -> 0 | AK88: =IF(OR(ISERROR(+K88/($D88+$E88-$G88)*$G88+K88),LEFT(I88,1)="x"),0,+K88/($D88+$E88-$G88)*$G88+K88) -> 0 | AL88: =IF(OR(ISERROR(+L88/($D88+$E88-$G88)*$G88+L88),LEFT(J88,1)="x"),0,+L88/($D88+$E88-$G88)*$G88+L88) -> 0 | AM88: =IF(OR(ISERROR(+M88/($D88+$E88-$G88)*$G88+M88),LEFT(K88,1)="x"),0,+M88/($D88+$E88-$G88)*$G88+M88) -> 0 | AN88: =IF(OR(ISERROR(+N88/($D88+$E88-$G88)*$G88+N88),LEFT(L88,1)="x"),0,+N88/($D88+$E88-$G88)*$G88+N88) -> 0 | AO88: =IF(OR(ISERROR(+O88/($D88+$E88-$G88)*$G88+O88),LEFT(M88,1)="x"),0,+O88/($D88+$E88-$G88)*$G88+O88) -> 0 | ... BB88: =IF(OR(ISERROR(+AB88/($D88+$E88-$G88)*$G88+AB88),LEFT(Z88,1)="x"),0,+AB88/($D88+$E88-$G88)*$G88+AB88) -> 157 | BC88: =IF(OR(ISERROR(+#REF!/($D88+$E88-$G88)*$G88+#REF!),LEFT(AA88,1)="x"),0,+#REF!/($D88+$E88-$G88)*$G88+#REF!) -> 0 | BD88: =IF(OR(ISERROR(+#REF!/($D88+$E88-$G88)*$G88+#REF!),LEFT(AB88,1)="x"),0,+#REF!/($D88+$E88-$G88)*$G88+#REF!) -> 0 | BE88: =IF(OR(ISERROR(+AC88/($D88+$E88-$G88)*$G88+AC88),LEFT(#REF!,1)="x"),0,+AC88/($D88+$E88-$G88)*$G88+AC88) -> #REF!
B89: Computer related costs | E89: 55 | S89: 55 | AD89: =SUM(G89:AC89) -> 55 | AE89: =SUM(D89:F89) -> 55 | AF89: =AD89-AE89 -> 0 | AG89: =IF(AF89=0,0,"ERROR HERE") -> 0 | AH89: =IF(OR(ISERROR(+H89/($D89+$E89-$G89)*$G89+H89),LEFT(F89,1)="x"),0,+H89/($D89+$E89-$G89)*$G89+H89) -> 0 | AI89: =IF(OR(ISERROR(+I89/($D89+$E89-$G89)*$G89+I89),LEFT(G89,1)="x"),0,+I89/($D89+$E89-$G89)*$G89+I89) -> 0 | AJ89: =IF(OR(ISERROR(+J89/($D89+$E89-$G89)*$G89+J89),LEFT(H89,1)="x"),0,+J89/($D89+$E89-$G89)*$G89+J89) -> 0 | AK89: =IF(OR(ISERROR(+K89/($D89+$E89-$G89)*$G89+K89),LEFT(I89,1)="x"),0,+K89/($D89+$E89-$G89)*$G89+K89) -> 0 | AL89: =IF(OR(ISERROR(+L89/($D89+$E89-$G89)*$G89+L89),LEFT(J89,1)="x"),0,+L89/($D89+$E89-$G89)*$G89+L89) -> 0 | AM89: =IF(OR(ISERROR(+M89/($D89+$E89-$G89)*$G89+M89),LEFT(K89,1)="x"),0,+M89/($D89+$E89-$G89)*$G89+M89) -> 0 | AN89: =IF(OR(ISERROR(+N89/($D89+$E89-$G89)*$G89+N89),LEFT(L89,1)="x"),0,+N89/($D89+$E89-$G89)*$G89+N89) -> 0 | AO89: =IF(OR(ISERROR(+O89/($D89+$E89-$G89)*$G89+O89),LEFT(M89,1)="x"),0,+O89/($D89+$E89-$G89)*$G89+O89) -> 0 | ... BB89: =IF(OR(ISERROR(+AB89/($D89+$E89-$G89)*$G89+AB89),LEFT(Z89,1)="x"),0,+AB89/($D89+$E89-$G89)*$G89+AB89) -> 0 | BC89: =IF(OR(ISERROR(+#REF!/($D89+$E89-$G89)*$G89+#REF!),LEFT(AA89,1)="x"),0,+#REF!/($D89+$E89-$G89)*$G89+#REF!) -> 0 | BD89: =IF(OR(ISERROR(+#REF!/($D89+$E89-$G89)*$G89+#REF!),LEFT(AB89,1)="x"),0,+#REF!/($D89+$E89-$G89)*$G89+#REF!) -> 0 | BE89: =IF(OR(ISERROR(+AC89/($D89+$E89-$G89)*$G89+AC89),LEFT(#REF!,1)="x"),0,+AC89/($D89+$E89-$G89)*$G89+AC89) -> #REF!
B90: Telephone Costs | E90: 65 | R90: 65 | AD90: =SUM(G90:AC90) -> 65 | AE90: =SUM(D90:F90) -> 65 | AF90: =AD90-AE90 -> 0 | AG90: =IF(AF90=0,0,"ERROR HERE") -> 0 | AH90: =IF(OR(ISERROR(+H90/($D90+$E90-$G90)*$G90+H90),LEFT(F90,1)="x"),0,+H90/($D90+$E90-$G90)*$G90+H90) -> 0 | AI90: =IF(OR(ISERROR(+I90/($D90+$E90-$G90)*$G90+I90),LEFT(G90,1)="x"),0,+I90/($D90+$E90-$G90)*$G90+I90) -> 0 | AJ90: =IF(OR(ISERROR(+J90/($D90+$E90-$G90)*$G90+J90),LEFT(H90,1)="x"),0,+J90/($D90+$E90-$G90)*$G90+J90) -> 0 | AK90: =IF(OR(ISERROR(+K90/($D90+$E90-$G90)*$G90+K90),LEFT(I90,1)="x"),0,+K90/($D90+$E90-$G90)*$G90+K90) -> 0 | AL90: =IF(OR(ISERROR(+L90/($D90+$E90-$G90)*$G90+L90),LEFT(J90,1)="x"),0,+L90/($D90+$E90-$G90)*$G90+L90) -> 0 | AM90: =IF(OR(ISERROR(+M90/($D90+$E90-$G90)*$G90+M90),LEFT(K90,1)="x"),0,+M90/($D90+$E90-$G90)*$G90+M90) -> 0 | AN90: =IF(OR(ISERROR(+N90/($D90+$E90-$G90)*$G90+N90),LEFT(L90,1)="x"),0,+N90/($D90+$E90-$G90)*$G90+N90) -> 0 | AO90: =IF(OR(ISERROR(+O90/($D90+$E90-$G90)*$G90+O90),LEFT(M90,1)="x"),0,+O90/($D90+$E90-$G90)*$G90+O90) -> 0 | ... BB90: =IF(OR(ISERROR(+AB90/($D90+$E90-$G90)*$G90+AB90),LEFT(Z90,1)="x"),0,+AB90/($D90+$E90-$G90)*$G90+AB90) -> 0 | BC90: =IF(OR(ISERROR(+#REF!/($D90+$E90-$G90)*$G90+#REF!),LEFT(AA90,1)="x"),0,+#REF!/($D90+$E90-$G90)*$G90+#REF!) -> 0 | BD90: =IF(OR(ISERROR(+#REF!/($D90+$E90-$G90)*$G90+#REF!),LEFT(AB90,1)="x"),0,+#REF!/($D90+$E90-$G90)*$G90+#REF!) -> 0 | BE90: =IF(OR(ISERROR(+AC90/($D90+$E90-$G90)*$G90+AC90),LEFT(#REF!,1)="x"),0,+AC90/($D90+$E90-$G90)*$G90+AC90) -> #REF!
B91: Insurance | E91: 35 | J91: 35 | N91: . | AD91: =SUM(G91:AC91) -> 35 | AE91: =SUM(D91:F91) -> 35 | AF91: =AD91-AE91 -> 0
B92: Bank Charges | D92: 5.5 | V92: 5.5 | AD92: =SUM(G92:AC92) -> 5.5 | AE92: =SUM(D92:F92) -> 5.5 | AF92: =AD92-AE92 -> 0
B93: MONEY MARKET REINVESTMENT 40029090709255 | D93: 50555.39 | X93: 50555.39 | AD93: =SUM(G93:AC93) -> 50555.39 | AE93: =SUM(D93:F93) -> 50555.39 | AF93: =AD93-AE93 -> 0
B94: HMRC VAT | D94: 6969.6 | Y94: 6969.6 | AD94: =SUM(G94:AC94) -> 6969.6 | AE94: =SUM(D94:F94) -> 6969.6 | AF94: =AD94-AE94 -> 0
B95: Expenses reclaimed | D95: 901 | E95: -901 | AD95: =SUM(G95:AC95) -> 0 | AE95: =SUM(D95:F95) -> 0 | AF95: =AD95-AE95 -> 0
AD96: =SUM(G96:AC96) -> 0 | AE96: =SUM(D96:F96) -> 0 | AF96: =AD96-AE96 -> 0
AD97: =SUM(G97:AC97) -> 0 | AE97: =SUM(D97:F97) -> 0 | AF97: =AD97-AE97 -> 0
AD98: =SUM(G98:AC98) -> 0 | AE98: =SUM(D98:F98) -> 0 | AF98: =AD98-AE98 -> 0
AD99: =SUM(G99:AC99) -> 0 | AE99: =SUM(D99:F99) -> 0 | AF99: =AD99-AE99 -> 0
AD100: =SUM(G100:AC100) -> 0 | AE100: =SUM(D100:F100) -> 0 | AF100: =AD100-AE100 -> 0
AD101: =SUM(G101:AC101) -> 0 | AE101: =SUM(D101:F101) -> 0 | AF101: =AD101-AE101 -> 0
AD102: =SUM(G102:AC102) -> 0 | AE102: =SUM(D102:F102) -> 0 | AF102: =AD102-AE102 -> 0
AD103: =SUM(G103:AC103) -> 0 | AE103: =SUM(D103:F103) -> 0 | AF103: =AD103-AE103 -> 0
AD104: =SUM(G104:AC104) -> 0 | AE104: =SUM(D104:F104) -> 0 | AF104: =AD104-AE104 -> 0
AD105: =SUM(G105:AC105) -> 0 | AE105: =SUM(D105:F105) -> 0 | AF105: =AD105-AE105 -> 0
AD106: =SUM(G106:AC106) -> 0 | AE106: =SUM(D106:F106) -> 0 | AF106: =AD106-AE106 -> 0
AD107: =SUM(G107:AC107) -> 0 | AE107: =SUM(D107:F107) -> 0 | AF107: =AD107-AE107 -> 0
... AD147: =SUM(G147:AC147) -> 0 | AE147: =SUM(D147:F147) -> 0 | AF147: =AD147-AE147 -> 0
AD148: =SUM(G148:AC148) -> 0 | AE148: =SUM(D148:F148) -> 0 | AF148: =AD148-AE148 -> 0 | AG148: =IF(AF148=0,0,"ERROR HERE") -> 0 | AH148: =IF(OR(ISERROR(+H148/($D148+$E148-$G148)*$G148+H148),LEFT(F148,1)="x"),0,+H148/($D148+$E148-$G148)*$G148+H148) -> 0 | AI148: =IF(OR(ISERROR(+I148/($D148+$E148-$G148)*$G148+I148),LEFT(G148,1)="x"),0,+I148/($D148+$E148-$G148)*$G148+I148) -> 0 | AJ148: =IF(OR(ISERROR(+J148/($D148+$E148-$G148)*$G148+J148),LEFT(H148,1)="x"),0,+J148/($D148+$E148-$G148)*$G148+J148) -> 0 | AK148: =IF(OR(ISERROR(+K148/($D148+$E148-$G148)*$G148+K148),LEFT(I148,1)="x"),0,+K148/($D148+$E148-$G148)*$G148+K148) -> 0 | AL148: =IF(OR(ISERROR(+L148/($D148+$E148-$G148)*$G148+L148),LEFT(J148,1)="x"),0,+L148/($D148+$E148-$G148)*$G148+L148) -> 0 | AM148: =IF(OR(ISERROR(+M148/($D148+$E148-$G148)*$G148+M148),LEFT(K148,1)="x"),0,+M148/($D148+$E148-$G148)*$G148+M148) -> 0 | AN148: =IF(OR(ISERROR(+N148/($D148+$E148-$G148)*$G148+N148),LEFT(L148,1)="x"),0,+N148/($D148+$E148-$G148)*$G148+N148) -> 0 | AO148: =IF(OR(ISERROR(+O148/($D148+$E148-$G148)*$G148+O148),LEFT(M148,1)="x"),0,+O148/($D148+$E148-$G148)*$G148+O148) -> 0 | ... BB148: =IF(OR(ISERROR(+AB148/($D148+$E148-$G148)*$G148+AB148),LEFT(Z148,1)="x"),0,+AB148/($D148+$E148-$G148)*$G148+AB148) -> 0 | BC148: =IF(OR(ISERROR(+#REF!/($D148+$E148-$G148)*$G148+#REF!),LEFT(AA148,1)="x"),0,+#REF!/($D148+$E148-$G148)*$G148+#REF!) -> 0 | BD148: =IF(OR(ISERROR(+#REF!/($D148+$E148-$G148)*$G148+#REF!),LEFT(AB148,1)="x"),0,+#REF!/($D148+$E148-$G148)*$G148+#REF!) -> 0 | BE148: =IF(OR(ISERROR(+AC148/($D148+$E148-$G148)*$G148+AC148),LEFT(#REF!,1)="x"),0,+AC148/($D148+$E148-$G148)*$G148+AC148) -> #REF!
AD149: =SUM(G149:AC149) -> 0 | AE149: =SUM(D149:F149) -> 0 | AF149: =AD149-AE149 -> 0
AD150: =SUM(G150:AC150) -> 0 | AE150: =SUM(D150:F150) -> 0 | AF150: =AD150-AE150 -> 0
AD151: =SUM(G151:AC151) -> 0 | AE151: =SUM(D151:F151) -> 0 | AF151: =AD151-AE151 -> 0
AD152: =SUM(G152:AC152) -> 0 | AE152: =SUM(D152:F152) -> 0 | AF152: =AD152-AE152 -> 0
AD153: =SUM(G153:AC153) -> 0 | AE153: =SUM(D153:F153) -> 0 | AF153: =AD153-AE153 -> 0
AD154: =SUM(G154:AC154) -> 0 | AE154: =SUM(D154:F154) -> 0 | AF154: =AD154-AE154 -> 0
AD155: =SUM(G155:AC155) -> 0 | AE155: =SUM(D155:F155) -> 0 | AF155: =AD155-AE155 -> 0
AD156: =SUM(G156:AC156) -> 0 | AE156: =SUM(D156:F156) -> 0 | AF156: =AD156-AE156 -> 0
AD157: =SUM(G157:AC157) -> 0 | AE157: =SUM(D157:F157) -> 0 | AF157: =AD157-AE157 -> 0
AD158: =SUM(G158:AC158) -> 0 | AE158: =SUM(D158:F158) -> 0 | AF158: =AD158-AE158 -> 0
AD159: =SUM(G159:AC159) -> 0 | AE159: =SUM(D159:F159) -> 0 | AF159: =AD159-AE159 -> 0
AD160: =SUM(G160:AC160) -> 0 | AE160: =SUM(D160:F160) -> 0 | AF160: =AD160-AE160 -> 0
...

Sheet Jan 18
A1: 0
A2: ='Nov 17'!A2 -> Design-spectrum Limited
A4: Month | C4: ='Dec 17'!C4+31 -> 43102
A7: Sales Invoices | I7: Bankings - Receipts
A9: Does this months income fall within IR35? (Y/N/both) | E9: ='Dec 17'!E9 -> n
A11: Is the Company VAT registered (Y/N) | E11: ='Dec 17'!E11 -> y
A12: VAT Flat rate scheme percentage | E12: ='Dec 17'!E12 -> 0.165
A13: (leave blank or zero if not using flat rate scheme) | M13: Interest | O13: Transfers from | P13: Interest
L14: Sales Invoice | M14: Received on | O14: Deposit | P14: Received on
A15: Date | B15: Details | C15: Sales Invoice No | D15: IR35 | E15: Non IR35 | F15: Gross | G15: VAT | I15: Date | J15: Details | K15: Sales Invoice no | L15: Amount £ | M15: Current Account | N15: Other bankings | O15: Account | P15: Deposit Account
C16: Balance b/f | D16: ='Dec 17'!D54 -> 0 | E16: ='Dec 17'!E54 -> 19250 | F16: ='Dec 17'!F54 -> 23100 | G16: ='Dec 17'!G54 -> 3850 | J16: Balance b/f | L16: ='Dec 17'!L54 -> 42900 | M16: ='Dec 17'!M54 -> 66.53 | N16: ='Dec 17'!N54 -> 0 | O16: ='Dec 17'!O54 -> 50488.86 | P16: ='Dec 17'!P54 -> -63.58
B17: Raised in next month | D17: =IF(E$9="y",F17-G17,0) -> 0 | E17: =IF(E$9="n",F17-G17,0) -> 0 | G17: =IF(($E$11="n"),0,IF((LEFT(C17,1)="v"),F17,IF((LEFT(C17,1)="z"),0,F17*1/6))) -> 0 | J17: R S C S LTD | L17: 3300
D18: =IF(E$9="y",F18-G18,0) -> 0 | E18: =IF(E$9="n",F18-G18,0) -> 0 | G18: =IF(($E$11="n"),0,IF((LEFT(C18,1)="v"),F18,IF((LEFT(C18,1)="z"),0,F18*1/6))) -> 0 | P18: 2.5
D19: =IF(E$9="y",F19-G19,0) -> 0 | E19: =IF(E$9="n",F19-G19,0) -> 0 | G19: =IF(($E$11="n"),0,IF((LEFT(C19,1)="v"),F19,IF((LEFT(C19,1)="z"),0,F19*1/6))) -> 0
D20: =IF(E$9="y",F20-G20,0) -> 0 | E20: =IF(E$9="n",F20-G20,0) -> 0 | G20: =IF(($E$11="n"),0,IF((LEFT(C20,1)="v"),F20,IF((LEFT(C20,1)="z"),0,F20*1/6))) -> 0
D21: =IF(E$9="y",F21-G21,0) -> 0 | E21: =IF(E$9="n",F21-G21,0) -> 0 | G21: =IF(($E$11="n"),0,IF((LEFT(C21,1)="v"),F21,IF((LEFT(C21,1)="z"),0,F21*1/6))) -> 0
D22: =IF(E$9="y",F22-G22,0) -> 0 | E22: =IF(E$9="n",F22-G22,0) -> 0 | G22: =IF(($E$11="n"),0,IF((LEFT(C22,1)="v"),F22,IF((LEFT(C22,1)="z"),0,F22*1/6))) -> 0
D23: =IF(E$9="y",F23-G23,0) -> 0 | E23: =IF(E$9="n",F23-G23,0) -> 0 | G23: =IF(($E$11="n"),0,IF((LEFT(C23,1)="v"),F23,IF((LEFT(C23,1)="z"),0,F23*1/6))) -> 0
D24: =IF(E$9="y",F24-G24,0) -> 0 | E24: =IF(E$9="n",F24-G24,0) -> 0 | G24: =IF(($E$11="n"),0,IF((LEFT(C24,1)="v"),F24,IF((LEFT(C24,1)="z"),0,F24*1/6))) -> 0
D25: =IF(E$9="y",F25-G25,0) -> 0 | E25: =IF(E$9="n",F25-G25,0) -> 0 | G25: =IF(($E$11="n"),0,IF((LEFT(C25,1)="v"),F25,IF((LEFT(C25,1)="z"),0,F25*1/6))) -> 0
D26: =IF(E$9="y",F26-G26,0) -> 0 | E26: =IF(E$9="n",F26-G26,0) -> 0 | G26: =IF(($E$11="n"),0,IF((LEFT(C26,1)="v"),F26,IF((LEFT(C26,1)="z"),0,F26*1/6))) -> 0
D27: =IF(E$9="y",F27-G27,0) -> 0 | E27: =IF(E$9="n",F27-G27,0) -> 0 | G27: =IF(($E$11="n"),0,IF((LEFT(C27,1)="v"),F27,IF((LEFT(C27,1)="z"),0,F27*1/6))) -> 0
D28: =IF(E$9="y",F28-G28,0) -> 0 | E28: =IF(E$9="n",F28-G28,0) -> 0 | G28: =IF(($E$11="n"),0,IF((LEFT(C28,1)="v"),F28,IF((LEFT(C28,1)="z"),0,F28*1/6))) -> 0
D29: =IF(E$9="y",F29-G29,0) -> 0 | E29: =IF(E$9="n",F29-G29,0) -> 0 | G29: =IF(($E$11="n"),0,IF((LEFT(C29,1)="v"),F29,IF((LEFT(C29,1)="z"),0,F29*1/6))) -> 0
D30: =IF(E$9="y",F30-G30,0) -> 0 | E30: =IF(E$9="n",F30-G30,0) -> 0 | G30: =IF(($E$11="n"),0,IF((LEFT(C30,1)="v"),F30,IF((LEFT(C30,1)="z"),0,F30*1/6))) -> 0
... D40: =IF(E$9="y",F40-G40,0) -> 0 | E40: =IF(E$9="n",F40-G40,0) -> 0 | G40: =IF(($E$11="n"),0,IF((LEFT(C40,1)="v"),F40,IF((LEFT(C40,1)="z"),0,F40*1/6))) -> 0
B41: =IF(E9="Both","Enter manual values here",0) -> 0 | D41: =IF(E$9="y",F41-G41,0) -> 0 | E41: =IF(E$9="n",F41-G41,0) -> 0 | G41: =IF(($E$11="n"),0,IF((LEFT(C41,1)="v"),F41,IF((LEFT(C41,1)="z"),0,F41*1/6))) -> 0
D42: =IF(E$9="y",F42-G42,0) -> 0 | E42: =IF(E$9="n",F42-G42,0) -> 0 | G42: =IF(($E$11="n"),0,IF((LEFT(C42,1)="v"),F42,IF((LEFT(C42,1)="z"),0,F42*1/6))) -> 0
D43: =IF(E$9="y",F43-G43,0) -> 0 | E43: =IF(E$9="n",F43-G43,0) -> 0 | G43: =IF(($E$11="n"),0,IF((LEFT(C43,1)="v"),F43,IF((LEFT(C43,1)="z"),0,F43*1/6))) -> 0
D44: =IF(E$9="y",F44-G44,0) -> 0 | E44: =IF(E$9="n",F44-G44,0) -> 0 | G44: =IF(($E$11="n"),0,IF((LEFT(C44,1)="v"),F44,IF((LEFT(C44,1)="z"),0,F44*1/6))) -> 0
D45: =IF(E$9="y",F45-G45,0) -> 0 | E45: =IF(E$9="n",F45-G45,0) -> 0 | G45: =IF(($E$11="n"),0,IF((LEFT(C45,1)="v"),F45,IF((LEFT(C45,1)="z"),0,F45*1/6))) -> 0
D46: =IF(E$9="y",F46-G46,0) -> 0 | E46: =IF(E$9="n",F46-G46,0) -> 0 | G46: =IF(($E$11="n"),0,IF((LEFT(C46,1)="v"),F46,IF((LEFT(C46,1)="z"),0,F46*1/6))) -> 0
D47: =IF(E$9="y",F47-G47,0) -> 0 | E47: =IF(E$9="n",F47-G47,0) -> 0 | G47: =IF(($E$11="n"),0,IF((LEFT(C47,1)="v"),F47,IF((LEFT(C47,1)="z"),0,F47*1/6))) -> 0
D48: =IF(E$9="y",F48-G48,0) -> 0 | E48: =IF(E$9="n",F48-G48,0) -> 0 | G48: =IF(($E$11="n"),0,IF((LEFT(C48,1)="v"),F48,IF((LEFT(C48,1)="z"),0,F48*1/6))) -> 0
D49: =IF(E$9="y",F49-G49,0) -> 0 | E49: =IF(E$9="n",F49-G49,0) -> 0 | G49: =IF(($E$11="n"),0,IF((LEFT(C49,1)="v"),F49,IF((LEFT(C49,1)="z"),0,F49*1/6))) -> 0
D50: =IF(E$9="y",F50-G50,0) -> 0 | E50: =IF(E$9="n",F50-G50,0) -> 0 | G50: =IF(($E$11="n"),0,IF((LEFT(C50,1)="v"),F50,IF((LEFT(C50,1)="z"),0,F50*1/6))) -> 0
D51: =IF(E$9="y",F51-G51,0) -> 0 | E51: =IF(E$9="n",F51-G51,0) -> 0 | G51: =IF(($E$11="n"),0,IF((LEFT(C51,1)="v"),F51,IF((LEFT(C51,1)="z"),0,F51*1/6))) -> 0
D52: =IF(E$9="y",F52-G52,0) -> 0 | E52: =IF(E$9="n",F52-G52,0) -> 0 | G52: =IF(($E$11="n"),0,IF((LEFT(C52,1)="v"),F52,IF((LEFT(C52,1)="z"),0,F52*1/6))) -> 0
A53: Total | D53: =SUM(D17:D52) -> 0 | E53: =SUM(E17:E52) -> 0 | F53: =SUM(F17:F52) -> 0 | G53: =SUM(G17:G52) -> 0 | I53: Total | L53: =SUM(L17:L52) -> 3300 | M53: =SUM(M17:M52) -> 0 | N53: =SUM(N17:N52) -> 0 | O53: =SUM(O17:O52) -> 0 | P53: =SUM(P17:P52) -> 2.5
A54: C/fwd | D54: =SUM(D16:D52) -> 0 | E54: =SUM(E16:E52) -> 19250 | F54: =SUM(F16:F52) -> 23100 | G54: =SUM(G16:G52) -> 3850 | I54: C/fwd | L54: =SUM(L16:L52) -> 46200 | M54: =SUM(M16:M52) -> 66.53 | N54: =SUM(N16:N52) -> 0 | O54: =SUM(O16:O52) -> 50488.86 | P54: =SUM(P16:P52) -> -61.08
A56: IR35 Details (ignore if outside IR35): | D56: Flat Rate Scheme Details (ignore if outside FRS):
A58: Deemed Salary | C58: =IF(E9="y",G59*0.95-(SUM(H197:K197)),0) -> 0 | E58: Per List Above | F58: FRS | G58: VAT account figures
A59: Deemed Salary | C59: =IF(E9="both",G59*0.95-(SUM(H197:K197)),0) -> 0 | D59: IR35 | E59: =+D53 -> 0 | F59: =+G59-E59 -> 0 | G59: =IF(E59+E60<>0,E59/(E59+E60)*(G61-G62),0) -> 0
D60: Non IR35 | E60: =+E53 -> 0 | F60: =+G60-E60 -> 0 | G60: =IF(E59+E60<>0,E60/(E59+E60)*(G61-G62),0) -> 0
D61: Gross | E61: =+F53 -> 0 | F61: =+G61-E61 -> 0 | G61: =+E61 -> 0
A62: Total PAYE & NI Due on deemed salary | C62: =IF(E243<=0,0,IF(C4<42095,E265,E243)) -> 0 | D62: VAT | E62: =+G53 -> 0 | F62: =+G62-E62 -> 0 | G62: =IF(E12>0,(G61)*E12,E62) -> 0
A63: 41730 = Numerical Value of 01 April 2014
A65: Tax provision to be made
A66: (payable by 19th April 2016) | C66: =C62 -> 0
A69: Net salary available to draw | C69: =C58+C59-C66 -> 0
A70: (after all taxes, NI and allowable expenses)
A74: Expenditure
H76: Motor | I76: Travelling, | J76: Professional, Public | P76: Printing, | S76: Computer | T76: Books, | V76: Bank Charges | X76: Transfers to | Z76: Corporation | AA76: Directors
C77: Reference / | D77: Company | E77: Cash/Personal | F77: Company | H77: Expenses Or | I77: Accommodation | J77: and Employers | K77: Company | M77: PAYE & NIC | O77: Cost of | P77: Postage & | Q77: Internet & | R77: Assets | S77: Related | T77: Journals & | V77: & Interest | X77: Deposit | Y77: VAT paid to | Z77: Tax paid to | AA77: Loan | AB77: Business
A78: Date | B78: Details | C78: Cheque No | D78: Bank | E78: Expenses | F78: Credit Card | G78: VAT | H78: Mileage Claims | I78: & Subsistence | J78: Liability Insurance | K78: Pension | L78: Net salary paid | M78: paid to HMR&C | N78: Dividends | O78: Goods sold | P78: Stationery | Q78: Telephone | R78: Purchased | S78: Costs | T78: Subscriptions | U78: Accountancy | V78: Payable | W78: Use of Home | X78: Account | Y78: HMC&E | Z78: HMR&C | AA78: Account | AB78: Entertainment | AC78: Sundries | AF78: error line?
B79: Balance b/f | D79: ='Dec 17'!D198 -> 65986.99 | E79: ='Dec 17'!E198 -> -901 | F79: ='Dec 17'!F198 -> 0 | G79: ='Dec 17'!G198 -> 0 | H79: ='Dec 17'!H198 -> 450 | I79: ='Dec 17'!I198 -> 328 | J79: ='Dec 17'!J198 -> 70 | K79: ='Dec 17'!K198 -> 0 | ... AC79: ='Dec 17'!AC198 -> 0 | AG79: =IF(AF79=0,0,"ERROR HERE") -> 0 | AH79: =IF(OR(ISERROR(+H79/($D79+$E79-$G79)*$G79+H79),LEFT(F79,1)="x"),0,+H79/($D79+$E79-$G79)*$G79+H79) -> 450 | AI79: =IF(OR(ISERROR(+I79/($D79+$E79-$G79)*$G79+I79),LEFT(G79,1)="x"),0,+I79/($D79+$E79-$G79)*$G79+I79) -> 328 | AJ79: =IF(OR(ISERROR(+J79/($D79+$E79-$G79)*$G79+J79),LEFT(H79,1)="x"),0,+J79/($D79+$E79-$G79)*$G79+J79) -> 70 | AK79: =IF(OR(ISERROR(+K79/($D79+$E79-$G79)*$G79+K79),LEFT(I79,1)="x"),0,+K79/($D79+$E79-$G79)*$G79+K79) -> 0 | AL79: =IF(OR(ISERROR(+L79/($D79+$E79-$G79)*$G79+L79),LEFT(J79,1)="x"),0,+L79/($D79+$E79-$G79)*$G79+L79) -> 5472 | AM79: =IF(OR(ISERROR(+M79/($D79+$E79-$G79)*$G79+M79),LEFT(K79,1)="x"),0,+M79/($D79+$E79-$G79)*$G79+M79) -> 0 | AN79: =IF(OR(ISERROR(+N79/($D79+$E79-$G79)*$G79+N79),LEFT(L79,1)="x"),0,+N79/($D79+$E79-$G79)*$G79+N79) -> 0 | AO79: =IF(OR(ISERROR(+O79/($D79+$E79-$G79)*$G79+O79),LEFT(M79,1)="x"),0,+O79/($D79+$E79-$G79)*$G79+O79) -> 0 | ... BB79: =IF(OR(ISERROR(+AB79/($D79+$E79-$G79)*$G79+AB79),LEFT(Z79,1)="x"),0,+AB79/($D79+$E79-$G79)*$G79+AB79) -> 314 | BC79: =IF(OR(ISERROR(+#REF!/($D79+$E79-$G79)*$G79+#REF!),LEFT(AA79,1)="x"),0,+#REF!/($D79+$E79-$G79)*$G79+#REF!) -> 0 | BD79: =IF(OR(ISERROR(+AC79/($D79+$E79-$G79)*$G79+AC79),LEFT(Z79,1)="x"),0,+AC79/($D79+$E79-$G79)*$G79+AC79) -> 0
B80: Salary Director S Haldar | D80: 924 | L80: 924 | AD80: =SUM(G80:AC80) -> 924 | AE80: =SUM(D80:F80) -> 924 | AF80: =AD80-AE80 -> 0 | AG80: =IF(AF80=0,0,"ERROR HERE") -> 0 | AH80: =IF(OR(ISERROR(+H80/($D80+$E80-$G80)*$G80+H80),LEFT(F80,1)="x"),0,+H80/($D80+$E80-$G80)*$G80+H80) -> 0 | AI80: =IF(OR(ISERROR(+I80/($D80+$E80-$G80)*$G80+I80),LEFT(G80,1)="x"),0,+I80/($D80+$E80-$G80)*$G80+I80) -> 0 | AJ80: =IF(OR(ISERROR(+J80/($D80+$E80-$G80)*$G80+J80),LEFT(H80,1)="x"),0,+J80/($D80+$E80-$G80)*$G80+J80) -> 0 | AK80: =IF(OR(ISERROR(+K80/($D80+$E80-$G80)*$G80+K80),LEFT(I80,1)="x"),0,+K80/($D80+$E80-$G80)*$G80+K80) -> 0 | AL80: =IF(OR(ISERROR(+L80/($D80+$E80-$G80)*$G80+L80),LEFT(J80,1)="x"),0,+L80/($D80+$E80-$G80)*$G80+L80) -> 924 | AM80: =IF(OR(ISERROR(+M80/($D80+$E80-$G80)*$G80+M80),LEFT(K80,1)="x"),0,+M80/($D80+$E80-$G80)*$G80+M80) -> 0 | AN80: =IF(OR(ISERROR(+N80/($D80+$E80-$G80)*$G80+N80),LEFT(L80,1)="x"),0,+N80/($D80+$E80-$G80)*$G80+N80) -> 0 | AO80: =IF(OR(ISERROR(+O80/($D80+$E80-$G80)*$G80+O80),LEFT(M80,1)="x"),0,+O80/($D80+$E80-$G80)*$G80+O80) -> 0 | ... BB80: =IF(OR(ISERROR(+AB80/($D80+$E80-$G80)*$G80+AB80),LEFT(Z80,1)="x"),0,+AB80/($D80+$E80-$G80)*$G80+AB80) -> 0 | BC80: =IF(OR(ISERROR(+#REF!/($D80+$E80-$G80)*$G80+#REF!),LEFT(AA80,1)="x"),0,+#REF!/($D80+$E80-$G80)*$G80+#REF!) -> 0 | BD80: =IF(OR(ISERROR(+AC80/($D80+$E80-$G80)*$G80+AC80),LEFT(Z80,1)="x"),0,+AC80/($D80+$E80-$G80)*$G80+AC80) -> 0
B81: Salary Director S Deb | D81: 900 | L81: 900 | AD81: =SUM(G81:AC81) -> 900 | AE81: =SUM(D81:F81) -> 900 | AF81: =AD81-AE81 -> 0 | AG81: =IF(AF81=0,0,"ERROR HERE") -> 0 | AH81: =IF(OR(ISERROR(+H81/($D81+$E81-$G81)*$G81+H81),LEFT(F81,1)="x"),0,+H81/($D81+$E81-$G81)*$G81+H81) -> 0 | AI81: =IF(OR(ISERROR(+I81/($D81+$E81-$G81)*$G81+I81),LEFT(G81,1)="x"),0,+I81/($D81+$E81-$G81)*$G81+I81) -> 0 | AJ81: =IF(OR(ISERROR(+J81/($D81+$E81-$G81)*$G81+J81),LEFT(H81,1)="x"),0,+J81/($D81+$E81-$G81)*$G81+J81) -> 0 | AK81: =IF(OR(ISERROR(+K81/($D81+$E81-$G81)*$G81+K81),LEFT(I81,1)="x"),0,+K81/($D81+$E81-$G81)*$G81+K81) -> 0 | AL81: =IF(OR(ISERROR(+L81/($D81+$E81-$G81)*$G81+L81),LEFT(J81,1)="x"),0,+L81/($D81+$E81-$G81)*$G81+L81) -> 900 | AM81: =IF(OR(ISERROR(+M81/($D81+$E81-$G81)*$G81+M81),LEFT(K81,1)="x"),0,+M81/($D81+$E81-$G81)*$G81+M81) -> 0 | AN81: =IF(OR(ISERROR(+N81/($D81+$E81-$G81)*$G81+N81),LEFT(L81,1)="x"),0,+N81/($D81+$E81-$G81)*$G81+N81) -> 0 | AO81: =IF(OR(ISERROR(+O81/($D81+$E81-$G81)*$G81+O81),LEFT(M81,1)="x"),0,+O81/($D81+$E81-$G81)*$G81+O81) -> 0 | ... BB81: =IF(OR(ISERROR(+AB81/($D81+$E81-$G81)*$G81+AB81),LEFT(Z81,1)="x"),0,+AB81/($D81+$E81-$G81)*$G81+AB81) -> 0 | BC81: =IF(OR(ISERROR(+#REF!/($D81+$E81-$G81)*$G81+#REF!),LEFT(AA81,1)="x"),0,+#REF!/($D81+$E81-$G81)*$G81+#REF!) -> 0 | BD81: =IF(OR(ISERROR(+AC81/($D81+$E81-$G81)*$G81+AC81),LEFT(Z81,1)="x"),0,+AC81/($D81+$E81-$G81)*$G81+AC81) -> 0
B82: Accountancy fees | D82: 138 | U82: 138 | AD82: =SUM(G82:AC82) -> 138 | AE82: =SUM(D82:F82) -> 138 | AF82: =AD82-AE82 -> 0 | AG82: =IF(AF82=0,0,"ERROR HERE - CHECK NUMBER IS CORRECTLY EXTENDED") -> 0 | AH82: =IF(OR(ISERROR(+H82/($D82+$E82-$G82)*$G82+H82),LEFT(F82,1)="x"),0,+H82/($D82+$E82-$G82)*$G82+H82) -> 0 | AI82: =IF(OR(ISERROR(+I82/($D82+$E82-$G82)*$G82+I82),LEFT(G82,1)="x"),0,+I82/($D82+$E82-$G82)*$G82+I82) -> 0 | AJ82: =IF(OR(ISERROR(+J82/($D82+$E82-$G82)*$G82+J82),LEFT(H82,1)="x"),0,+J82/($D82+$E82-$G82)*$G82+J82) -> 0 | AK82: =IF(OR(ISERROR(+K82/($D82+$E82-$G82)*$G82+K82),LEFT(I82,1)="x"),0,+K82/($D82+$E82-$G82)*$G82+K82) -> 0 | AL82: =IF(OR(ISERROR(+L82/($D82+$E82-$G82)*$G82+L82),LEFT(J82,1)="x"),0,+L82/($D82+$E82-$G82)*$G82+L82) -> 0 | AM82: =IF(OR(ISERROR(+M82/($D82+$E82-$G82)*$G82+M82),LEFT(K82,1)="x"),0,+M82/($D82+$E82-$G82)*$G82+M82) -> 0 | AN82: =IF(OR(ISERROR(+N82/($D82+$E82-$G82)*$G82+N82),LEFT(L82,1)="x"),0,+N82/($D82+$E82-$G82)*$G82+N82) -> 0 | AO82: =IF(OR(ISERROR(+O82/($D82+$E82-$G82)*$G82+O82),LEFT(M82,1)="x"),0,+O82/($D82+$E82-$G82)*$G82+O82) -> 0 | ... BB82: =IF(OR(ISERROR(+AB82/($D82+$E82-$G82)*$G82+AB82),LEFT(Z82,1)="x"),0,+AB82/($D82+$E82-$G82)*$G82+AB82) -> 0 | BC82: =IF(OR(ISERROR(+#REF!/($D82+$E82-$G82)*$G82+#REF!),LEFT(AA82,1)="x"),0,+#REF!/($D82+$E82-$G82)*$G82+#REF!) -> 0 | BD82: =IF(OR(ISERROR(+#REF!/($D82+$E82-$G82)*$G82+#REF!),LEFT(AB82,1)="x"),0,+#REF!/($D82+$E82-$G82)*$G82+#REF!) -> 0 | BE82: =IF(OR(ISERROR(+AC82/($D82+$E82-$G82)*$G82+AC82),LEFT(#REF!,1)="x"),0,+AC82/($D82+$E82-$G82)*$G82+AC82) -> #REF!
B83: Bus & Tube fare | E83: 164 | I83: 164 | AD83: =SUM(G83:AC83) -> 164 | AE83: =SUM(D83:F83) -> 164 | AF83: =AD83-AE83 -> 0 | AG83: =IF(AF83=0,0,"ERROR HERE") -> 0 | AH83: =IF(OR(ISERROR(+H83/($D83+$E83-$G83)*$G83+H83),LEFT(F83,1)="x"),0,+H83/($D83+$E83-$G83)*$G83+H83) -> 0 | AI83: =IF(OR(ISERROR(+I83/($D83+$E83-$G83)*$G83+I83),LEFT(G83,1)="x"),0,+I83/($D83+$E83-$G83)*$G83+I83) -> 164 | AJ83: =IF(OR(ISERROR(+J83/($D83+$E83-$G83)*$G83+J83),LEFT(H83,1)="x"),0,+J83/($D83+$E83-$G83)*$G83+J83) -> 0 | AK83: =IF(OR(ISERROR(+K83/($D83+$E83-$G83)*$G83+K83),LEFT(I83,1)="x"),0,+K83/($D83+$E83-$G83)*$G83+K83) -> 0 | AL83: =IF(OR(ISERROR(+L83/($D83+$E83-$G83)*$G83+L83),LEFT(J83,1)="x"),0,+L83/($D83+$E83-$G83)*$G83+L83) -> 0 | AM83: =IF(OR(ISERROR(+M83/($D83+$E83-$G83)*$G83+M83),LEFT(K83,1)="x"),0,+M83/($D83+$E83-$G83)*$G83+M83) -> 0 | AN83: =IF(OR(ISERROR(+N83/($D83+$E83-$G83)*$G83+N83),LEFT(L83,1)="x"),0,+N83/($D83+$E83-$G83)*$G83+N83) -> 0 | AO83: =IF(OR(ISERROR(+O83/($D83+$E83-$G83)*$G83+O83),LEFT(M83,1)="x"),0,+O83/($D83+$E83-$G83)*$G83+O83) -> 0 | ... BB83: =IF(OR(ISERROR(+AB83/($D83+$E83-$G83)*$G83+AB83),LEFT(Z83,1)="x"),0,+AB83/($D83+$E83-$G83)*$G83+AB83) -> 0 | BC83: =IF(OR(ISERROR(+#REF!/($D83+$E83-$G83)*$G83+#REF!),LEFT(AA83,1)="x"),0,+#REF!/($D83+$E83-$G83)*$G83+#REF!) -> 0 | BD83: =IF(OR(ISERROR(+#REF!/($D83+$E83-$G83)*$G83+#REF!),LEFT(AB83,1)="x"),0,+#REF!/($D83+$E83-$G83)*$G83+#REF!) -> 0 | BE83: =IF(OR(ISERROR(+AC83/($D83+$E83-$G83)*$G83+AC83),LEFT(#REF!,1)="x"),0,+AC83/($D83+$E83-$G83)*$G83+AC83) -> #REF!
B84: Postage | E84: 20 | P84: 20 | AD84: =SUM(G84:AC84) -> 20 | AE84: =SUM(D84:F84) -> 20 | AF84: =AD84-AE84 -> 0 | AG84: =IF(AF84=0,0,"ERROR HERE") -> 0 | AH84: =IF(OR(ISERROR(+H84/($D84+$E84-$G84)*$G84+H84),LEFT(F84,1)="x"),0,+H84/($D84+$E84-$G84)*$G84+H84) -> 0 | AI84: =IF(OR(ISERROR(+I84/($D84+$E84-$G84)*$G84+I84),LEFT(G84,1)="x"),0,+I84/($D84+$E84-$G84)*$G84+I84) -> 0 | AJ84: =IF(OR(ISERROR(+J84/($D84+$E84-$G84)*$G84+J84),LEFT(H84,1)="x"),0,+J84/($D84+$E84-$G84)*$G84+J84) -> 0 | AK84: =IF(OR(ISERROR(+K84/($D84+$E84-$G84)*$G84+K84),LEFT(I84,1)="x"),0,+K84/($D84+$E84-$G84)*$G84+K84) -> 0 | AL84: =IF(OR(ISERROR(+L84/($D84+$E84-$G84)*$G84+L84),LEFT(J84,1)="x"),0,+L84/($D84+$E84-$G84)*$G84+L84) -> 0 | AM84: =IF(OR(ISERROR(+M84/($D84+$E84-$G84)*$G84+M84),LEFT(K84,1)="x"),0,+M84/($D84+$E84-$G84)*$G84+M84) -> 0 | AN84: =IF(OR(ISERROR(+N84/($D84+$E84-$G84)*$G84+N84),LEFT(L84,1)="x"),0,+N84/($D84+$E84-$G84)*$G84+N84) -> 0 | AO84: =IF(OR(ISERROR(+O84/($D84+$E84-$G84)*$G84+O84),LEFT(M84,1)="x"),0,+O84/($D84+$E84-$G84)*$G84+O84) -> 0 | ... BB84: =IF(OR(ISERROR(+AB84/($D84+$E84-$G84)*$G84+AB84),LEFT(Z84,1)="x"),0,+AB84/($D84+$E84-$G84)*$G84+AB84) -> 0 | BC84: =IF(OR(ISERROR(+#REF!/($D84+$E84-$G84)*$G84+#REF!),LEFT(AA84,1)="x"),0,+#REF!/($D84+$E84-$G84)*$G84+#REF!) -> 0 | BD84: =IF(OR(ISERROR(+#REF!/($D84+$E84-$G84)*$G84+#REF!),LEFT(AB84,1)="x"),0,+#REF!/($D84+$E84-$G84)*$G84+#REF!) -> 0 | BE84: =IF(OR(ISERROR(+AC84/($D84+$E84-$G84)*$G84+AC84),LEFT(#REF!,1)="x"),0,+AC84/($D84+$E84-$G84)*$G84+AC84) -> #REF!
B85: use of residence as office | E85: 95 | W85: 95 | AD85: =SUM(G85:AC85) -> 95 | AE85: =SUM(D85:F85) -> 95 | AF85: =AD85-AE85 -> 0 | AG85: =IF(AF85=0,0,"ERROR HERE") -> 0 | AH85: =IF(OR(ISERROR(+H85/($D85+$E85-$G85)*$G85+H85),LEFT(F85,1)="x"),0,+H85/($D85+$E85-$G85)*$G85+H85) -> 0 | AI85: =IF(OR(ISERROR(+I85/($D85+$E85-$G85)*$G85+I85),LEFT(G85,1)="x"),0,+I85/($D85+$E85-$G85)*$G85+I85) -> 0 | AJ85: =IF(OR(ISERROR(+J85/($D85+$E85-$G85)*$G85+J85),LEFT(H85,1)="x"),0,+J85/($D85+$E85-$G85)*$G85+J85) -> 0 | AK85: =IF(OR(ISERROR(+K85/($D85+$E85-$G85)*$G85+K85),LEFT(I85,1)="x"),0,+K85/($D85+$E85-$G85)*$G85+K85) -> 0 | AL85: =IF(OR(ISERROR(+L85/($D85+$E85-$G85)*$G85+L85),LEFT(J85,1)="x"),0,+L85/($D85+$E85-$G85)*$G85+L85) -> 0 | AM85: =IF(OR(ISERROR(+M85/($D85+$E85-$G85)*$G85+M85),LEFT(K85,1)="x"),0,+M85/($D85+$E85-$G85)*$G85+M85) -> 0 | AN85: =IF(OR(ISERROR(+N85/($D85+$E85-$G85)*$G85+N85),LEFT(L85,1)="x"),0,+N85/($D85+$E85-$G85)*$G85+N85) -> 0 | AO85: =IF(OR(ISERROR(+O85/($D85+$E85-$G85)*$G85+O85),LEFT(M85,1)="x"),0,+O85/($D85+$E85-$G85)*$G85+O85) -> 0 | ... BB85: =IF(OR(ISERROR(+AB85/($D85+$E85-$G85)*$G85+AB85),LEFT(Z85,1)="x"),0,+AB85/($D85+$E85-$G85)*$G85+AB85) -> 0 | BC85: =IF(OR(ISERROR(+#REF!/($D85+$E85-$G85)*$G85+#REF!),LEFT(AA85,1)="x"),0,+#REF!/($D85+$E85-$G85)*$G85+#REF!) -> 0 | BD85: =IF(OR(ISERROR(+#REF!/($D85+$E85-$G85)*$G85+#REF!),LEFT(AB85,1)="x"),0,+#REF!/($D85+$E85-$G85)*$G85+#REF!) -> 0 | BE85: =IF(OR(ISERROR(+AC85/($D85+$E85-$G85)*$G85+AC85),LEFT(#REF!,1)="x"),0,+AC85/($D85+$E85-$G85)*$G85+AC85) -> #REF!
B86: Subscriptions | E86: 85 | T86: 85 | AD86: =SUM(G86:AC86) -> 85 | AE86: =SUM(D86:F86) -> 85 | AF86: =AD86-AE86 -> 0 | AG86: =IF(AF86=0,0,"ERROR HERE") -> 0 | AH86: =IF(OR(ISERROR(+H86/($D86+$E86-$G86)*$G86+H86),LEFT(F86,1)="x"),0,+H86/($D86+$E86-$G86)*$G86+H86) -> 0 | AI86: =IF(OR(ISERROR(+I86/($D86+$E86-$G86)*$G86+I86),LEFT(G86,1)="x"),0,+I86/($D86+$E86-$G86)*$G86+I86) -> 0 | AJ86: =IF(OR(ISERROR(+J86/($D86+$E86-$G86)*$G86+J86),LEFT(H86,1)="x"),0,+J86/($D86+$E86-$G86)*$G86+J86) -> 0 | AK86: =IF(OR(ISERROR(+K86/($D86+$E86-$G86)*$G86+K86),LEFT(I86,1)="x"),0,+K86/($D86+$E86-$G86)*$G86+K86) -> 0 | AL86: =IF(OR(ISERROR(+L86/($D86+$E86-$G86)*$G86+L86),LEFT(J86,1)="x"),0,+L86/($D86+$E86-$G86)*$G86+L86) -> 0 | AM86: =IF(OR(ISERROR(+M86/($D86+$E86-$G86)*$G86+M86),LEFT(K86,1)="x"),0,+M86/($D86+$E86-$G86)*$G86+M86) -> 0 | AN86: =IF(OR(ISERROR(+N86/($D86+$E86-$G86)*$G86+N86),LEFT(L86,1)="x"),0,+N86/($D86+$E86-$G86)*$G86+N86) -> 0 | AO86: =IF(OR(ISERROR(+O86/($D86+$E86-$G86)*$G86+O86),LEFT(M86,1)="x"),0,+O86/($D86+$E86-$G86)*$G86+O86) -> 0 | ... BB86: =IF(OR(ISERROR(+AB86/($D86+$E86-$G86)*$G86+AB86),LEFT(Z86,1)="x"),0,+AB86/($D86+$E86-$G86)*$G86+AB86) -> 0 | BC86: =IF(OR(ISERROR(+#REF!/($D86+$E86-$G86)*$G86+#REF!),LEFT(AA86,1)="x"),0,+#REF!/($D86+$E86-$G86)*$G86+#REF!) -> 0 | BD86: =IF(OR(ISERROR(+#REF!/($D86+$E86-$G86)*$G86+#REF!),LEFT(AB86,1)="x"),0,+#REF!/($D86+$E86-$G86)*$G86+#REF!) -> 0 | BE86: =IF(OR(ISERROR(+AC86/($D86+$E86-$G86)*$G86+AC86),LEFT(#REF!,1)="x"),0,+AC86/($D86+$E86-$G86)*$G86+AC86) -> #REF!
B87: Motor expenses (Parking, Maintainance) | E87: 225 | H87: 225 | AD87: =SUM(G87:AC87) -> 225 | AE87: =SUM(D87:F87) -> 225 | AF87: =AD87-AE87 -> 0 | AG87: =IF(AF87=0,0,"ERROR HERE") -> 0 | AH87: =IF(OR(ISERROR(+H87/($D87+$E87-$G87)*$G87+H87),LEFT(F87,1)="x"),0,+H87/($D87+$E87-$G87)*$G87+H87) -> 225 | AI87: =IF(OR(ISERROR(+I87/($D87+$E87-$G87)*$G87+I87),LEFT(G87,1)="x"),0,+I87/($D87+$E87-$G87)*$G87+I87) -> 0 | AJ87: =IF(OR(ISERROR(+J87/($D87+$E87-$G87)*$G87+J87),LEFT(H87,1)="x"),0,+J87/($D87+$E87-$G87)*$G87+J87) -> 0 | AK87: =IF(OR(ISERROR(+K87/($D87+$E87-$G87)*$G87+K87),LEFT(I87,1)="x"),0,+K87/($D87+$E87-$G87)*$G87+K87) -> 0 | AL87: =IF(OR(ISERROR(+L87/($D87+$E87-$G87)*$G87+L87),LEFT(J87,1)="x"),0,+L87/($D87+$E87-$G87)*$G87+L87) -> 0 | AM87: =IF(OR(ISERROR(+M87/($D87+$E87-$G87)*$G87+M87),LEFT(K87,1)="x"),0,+M87/($D87+$E87-$G87)*$G87+M87) -> 0 | AN87: =IF(OR(ISERROR(+N87/($D87+$E87-$G87)*$G87+N87),LEFT(L87,1)="x"),0,+N87/($D87+$E87-$G87)*$G87+N87) -> 0 | AO87: =IF(OR(ISERROR(+O87/($D87+$E87-$G87)*$G87+O87),LEFT(M87,1)="x"),0,+O87/($D87+$E87-$G87)*$G87+O87) -> 0 | ... BB87: =IF(OR(ISERROR(+AB87/($D87+$E87-$G87)*$G87+AB87),LEFT(Z87,1)="x"),0,+AB87/($D87+$E87-$G87)*$G87+AB87) -> 0 | BC87: =IF(OR(ISERROR(+#REF!/($D87+$E87-$G87)*$G87+#REF!),LEFT(AA87,1)="x"),0,+#REF!/($D87+$E87-$G87)*$G87+#REF!) -> 0 | BD87: =IF(OR(ISERROR(+#REF!/($D87+$E87-$G87)*$G87+#REF!),LEFT(AB87,1)="x"),0,+#REF!/($D87+$E87-$G87)*$G87+#REF!) -> 0 | BE87: =IF(OR(ISERROR(+AC87/($D87+$E87-$G87)*$G87+AC87),LEFT(#REF!,1)="x"),0,+AC87/($D87+$E87-$G87)*$G87+AC87) -> #REF!
B88: Business lunch | E88: 157 | AB88: 157 | AD88: =SUM(G88:AC88) -> 157 | AE88: =SUM(D88:F88) -> 157 | AF88: =AD88-AE88 -> 0
B89: Computer related costs | E89: 55 | S89: 55 | AD89: =SUM(G89:AC89) -> 55 | AE89: =SUM(D89:F89) -> 55 | AF89: =AD89-AE89 -> 0
B90: Telephone Costs | E90: 65 | R90: 65 | AD90: =SUM(G90:AC90) -> 65 | AE90: =SUM(D90:F90) -> 65 | AF90: =AD90-AE90 -> 0
B91: Insurance | E91: 35 | J91: 35 | N91: . | AD91: =SUM(G91:AC91) -> 35 | AE91: =SUM(D91:F91) -> 35 | AF91: =AD91-AE91 -> 0
B92: Bank Charges | D92: 5.5 | V92: 5.5 | AD92: =SUM(G92:AC92) -> 5.5 | AE92: =SUM(D92:F92) -> 5.5 | AF92: =AD92-AE92 -> 0
B93: Expenses reclaimed | D93: 901 | E93: -901 | AD93: =SUM(G93:AC93) -> 0 | AE93: =SUM(D93:F93) -> 0 | AF93: =AD93-AE93 -> 0
AD94: =SUM(G94:AC94) -> 0 | AE94: =SUM(D94:F94) -> 0 | AF94: =AD94-AE94 -> 0
AD95: =SUM(G95:AC95) -> 0 | AE95: =SUM(D95:F95) -> 0 | AF95: =AD95-AE95 -> 0
AD96: =SUM(G96:AC96) -> 0 | AE96: =SUM(D96:F96) -> 0 | AF96: =AD96-AE96 -> 0
AD97: =SUM(G97:AC97) -> 0 | AE97: =SUM(D97:F97) -> 0 | AF97: =AD97-AE97 -> 0
AD98: =SUM(G98:AC98) -> 0 | AE98: =SUM(D98:F98) -> 0 | AF98: =AD98-AE98 -> 0
AD99: =SUM(G99:AC99) -> 0 | AE99: =SUM(D99:F99) -> 0 | AF99: =AD99-AE99 -> 0
AD100: =SUM(G100:AC100) -> 0 | AE100: =SUM(D100:F100) -> 0 | AF100: =AD100-AE100 -> 0
AD101: =SUM(G101:AC101) -> 0 | AE101: =SUM(D101:F101) -> 0 | AF101: =AD101-AE101 -> 0
AD102: =SUM(G102:AC102) -> 0 | AE102: =SUM(D102:F102) -> 0 | AF102: =AD102-AE102 -> 0
AD103: =SUM(G103:AC103) -> 0 | AE103: =SUM(D103:F103) -> 0 | AF103: =AD103-AE103 -> 0
AD104: =SUM(G104:AC104) -> 0 | AE104: =SUM(D104:F104) -> 0 | AF104: =AD104-AE104 -> 0
AD105: =SUM(G105:AC105) -> 0 | AE105: =SUM(D105:F105) -> 0 | AF105: =AD105-AE105 -> 0
... AD153: =SUM(G153:AC153) -> 0 | AE153: =SUM(D153:F153) -> 0 | AF153: =AD153-AE153 -> 0
AD154: =SUM(G154:AC154) -> 0 | AE154: =SUM(D154:F154) -> 0 | AF154: =AD154-AE154 -> 0 | AG154: =IF(AF154=0,0,"ERROR HERE") -> 0 | AH154: =IF(OR(ISERROR(+H154/($D154+$E154-$G154)*$G154+H154),LEFT(F154,1)="x"),0,+H154/($D154+$E154-$G154)*$G154+H154) -> 0 | AI154: =IF(OR(ISERROR(+I154/($D154+$E154-$G154)*$G154+I154),LEFT(G154,1)="x"),0,+I154/($D154+$E154-$G154)*$G154+I154) -> 0 | AJ154: =IF(OR(ISERROR(+J154/($D154+$E154-$G154)*$G154+J154),LEFT(H154,1)="x"),0,+J154/($D154+$E154-$G154)*$G154+J154) -> 0 | AK154: =IF(OR(ISERROR(+K154/($D154+$E154-$G154)*$G154+K154),LEFT(I154,1)="x"),0,+K154/($D154+$E154-$G154)*$G154+K154) -> 0 | AL154: =IF(OR(ISERROR(+L154/($D154+$E154-$G154)*$G154+L154),LEFT(J154,1)="x"),0,+L154/($D154+$E154-$G154)*$G154+L154) -> 0 | AM154: =IF(OR(ISERROR(+M154/($D154+$E154-$G154)*$G154+M154),LEFT(K154,1)="x"),0,+M154/($D154+$E154-$G154)*$G154+M154) -> 0 | AN154: =IF(OR(ISERROR(+N154/($D154+$E154-$G154)*$G154+N154),LEFT(L154,1)="x"),0,+N154/($D154+$E154-$G154)*$G154+N154) -> 0 | AO154: =IF(OR(ISERROR(+O154/($D154+$E154-$G154)*$G154+O154),LEFT(M154,1)="x"),0,+O154/($D154+$E154-$G154)*$G154+O154) -> 0 | ... BB154: =IF(OR(ISERROR(+AB154/($D154+$E154-$G154)*$G154+AB154),LEFT(Z154,1)="x"),0,+AB154/($D154+$E154-$G154)*$G154+AB154) -> 0 | BC154: =IF(OR(ISERROR(+#REF!/($D154+$E154-$G154)*$G154+#REF!),LEFT(AA154,1)="x"),0,+#REF!/($D154+$E154-$G154)*$G154+#REF!) -> 0 | BD154: =IF(OR(ISERROR(+#REF!/($D154+$E154-$G154)*$G154+#REF!),LEFT(AB154,1)="x"),0,+#REF!/($D154+$E154-$G154)*$G154+#REF!) -> 0 | BE154: =IF(OR(ISERROR(+AC154/($D154+$E154-$G154)*$G154+AC154),LEFT(#REF!,1)="x"),0,+AC154/($D154+$E154-$G154)*$G154+AC154) -> #REF!
AD155: =SUM(G155:AC155) -> 0 | AE155: =SUM(D155:F155) -> 0 | AF155: =AD155-AE155 -> 0 | AG155: =IF(AF155=0,0,"ERROR HERE") -> 0 | AH155: =IF(OR(ISERROR(+H155/($D155+$E155-$G155)*$G155+H155),LEFT(F155,1)="x"),0,+H155/($D155+$E155-$G155)*$G155+H155) -> 0 | AI155: =IF(OR(ISERROR(+I155/($D155+$E155-$G155)*$G155+I155),LEFT(G155,1)="x"),0,+I155/($D155+$E155-$G155)*$G155+I155) -> 0 | AJ155: =IF(OR(ISERROR(+J155/($D155+$E155-$G155)*$G155+J155),LEFT(H155,1)="x"),0,+J155/($D155+$E155-$G155)*$G155+J155) -> 0 | AK155: =IF(OR(ISERROR(+K155/($D155+$E155-$G155)*$G155+K155),LEFT(I155,1)="x"),0,+K155/($D155+$E155-$G155)*$G155+K155) -> 0 | AL155: =IF(OR(ISERROR(+L155/($D155+$E155-$G155)*$G155+L155),LEFT(J155,1)="x"),0,+L155/($D155+$E155-$G155)*$G155+L155) -> 0 | AM155: =IF(OR(ISERROR(+M155/($D155+$E155-$G155)*$G155+M155),LEFT(K155,1)="x"),0,+M155/($D155+$E155-$G155)*$G155+M155) -> 0 | AN155: =IF(OR(ISERROR(+N155/($D155+$E155-$G155)*$G155+N155),LEFT(L155,1)="x"),0,+N155/($D155+$E155-$G155)*$G155+N155) -> 0 | AO155: =IF(OR(ISERROR(+O155/($D155+$E155-$G155)*$G155+O155),LEFT(M155,1)="x"),0,+O155/($D155+$E155-$G155)*$G155+O155) -> 0 | ... BB155: =IF(OR(ISERROR(+AB155/($D155+$E155-$G155)*$G155+AB155),LEFT(Z155,1)="x"),0,+AB155/($D155+$E155-$G155)*$G155+AB155) -> 0 | BC155: =IF(OR(ISERROR(+#REF!/($D155+$E155-$G155)*$G155+#REF!),LEFT(AA155,1)="x"),0,+#REF!/($D155+$E155-$G155)*$G155+#REF!) -> 0 | BD155: =IF(OR(ISERROR(+#REF!/($D155+$E155-$G155)*$G155+#REF!),LEFT(AB155,1)="x"),0,+#REF!/($D155+$E155-$G155)*$G155+#REF!) -> 0 | BE155: =IF(OR(ISERROR(+AC155/($D155+$E155-$G155)*$G155+AC155),LEFT(#REF!,1)="x"),0,+AC155/($D155+$E155-$G155)*$G155+AC155) -> #REF!
AD156: =SUM(G156:AC156) -> 0 | AE156: =SUM(D156:F156) -> 0 | AF156: =AD156-AE156 -> 0 | AG156: =IF(AF156=0,0,"ERROR HERE") -> 0 | AH156: =IF(OR(ISERROR(+H156/($D156+$E156-$G156)*$G156+H156),LEFT(F156,1)="x"),0,+H156/($D156+$E156-$G156)*$G156+H156) -> 0 | AI156: =IF(OR(ISERROR(+I156/($D156+$E156-$G156)*$G156+I156),LEFT(G156,1)="x"),0,+I156/($D156+$E156-$G156)*$G156+I156) -> 0 | AJ156: =IF(OR(ISERROR(+J156/($D156+$E156-$G156)*$G156+J156),LEFT(H156,1)="x"),0,+J156/($D156+$E156-$G156)*$G156+J156) -> 0 | AK156: =IF(OR(ISERROR(+K156/($D156+$E156-$G156)*$G156+K156),LEFT(I156,1)="x"),0,+K156/($D156+$E156-$G156)*$G156+K156) -> 0 | AL156: =IF(OR(ISERROR(+L156/($D156+$E156-$G156)*$G156+L156),LEFT(J156,1)="x"),0,+L156/($D156+$E156-$G156)*$G156+L156) -> 0 | AM156: =IF(OR(ISERROR(+M156/($D156+$E156-$G156)*$G156+M156),LEFT(K156,1)="x"),0,+M156/($D156+$E156-$G156)*$G156+M156) -> 0 | AN156: =IF(OR(ISERROR(+N156/($D156+$E156-$G156)*$G156+N156),LEFT(L156,1)="x"),0,+N156/($D156+$E156-$G156)*$G156+N156) -> 0 | AO156: =IF(OR(ISERROR(+O156/($D156+$E156-$G156)*$G156+O156),LEFT(M156,1)="x"),0,+O156/($D156+$E156-$G156)*$G156+O156) -> 0 | ... BB156: =IF(OR(ISERROR(+AB156/($D156+$E156-$G156)*$G156+AB156),LEFT(Z156,1)="x"),0,+AB156/($D156+$E156-$G156)*$G156+AB156) -> 0 | BC156: =IF(OR(ISERROR(+#REF!/($D156+$E156-$G156)*$G156+#REF!),LEFT(AA156,1)="x"),0,+#REF!/($D156+$E156-$G156)*$G156+#REF!) -> 0 | BD156: =IF(OR(ISERROR(+#REF!/($D156+$E156-$G156)*$G156+#REF!),LEFT(AB156,1)="x"),0,+#REF!/($D156+$E156-$G156)*$G156+#REF!) -> 0 | BE156: =IF(OR(ISERROR(+AC156/($D156+$E156-$G156)*$G156+AC156),LEFT(#REF!,1)="x"),0,+AC156/($D156+$E156-$G156)*$G156+AC156) -> #REF!
AD157: =SUM(G157:AC157) -> 0 | AE157: =SUM(D157:F157) -> 0 | AF157: =AD157-AE157 -> 0 | AG157: =IF(AF157=0,0,"ERROR HERE") -> 0 | AH157: =IF(OR(ISERROR(+H157/($D157+$E157-$G157)*$G157+H157),LEFT(F157,1)="x"),0,+H157/($D157+$E157-$G157)*$G157+H157) -> 0 | AI157: =IF(OR(ISERROR(+I157/($D157+$E157-$G157)*$G157+I157),LEFT(G157,1)="x"),0,+I157/($D157+$E157-$G157)*$G157+I157) -> 0 | AJ157: =IF(OR(ISERROR(+J157/($D157+$E157-$G157)*$G157+J157),LEFT(H157,1)="x"),0,+J157/($D157+$E157-$G157)*$G157+J157) -> 0 | AK157: =IF(OR(ISERROR(+K157/($D157+$E157-$G157)*$G157+K157),LEFT(I157,1)="x"),0,+K157/($D157+$E157-$G157)*$G157+K157) -> 0 | AL157: =IF(OR(ISERROR(+L157/($D157+$E157-$G157)*$G157+L157),LEFT(J157,1)="x"),0,+L157/($D157+$E157-$G157)*$G157+L157) -> 0 | AM157: =IF(OR(ISERROR(+M157/($D157+$E157-$G157)*$G157+M157),LEFT(K157,1)="x"),0,+M157/($D157+$E157-$G157)*$G157+M157) -> 0 | AN157: =IF(OR(ISERROR(+N157/($D157+$E157-$G157)*$G157+N157),LEFT(L157,1)="x"),0,+N157/($D157+$E157-$G157)*$G157+N157) -> 0 | AO157: =IF(OR(ISERROR(+O157/($D157+$E157-$G157)*$G157+O157),LEFT(M157,1)="x"),0,+O157/($D157+$E157-$G157)*$G157+O157) -> 0 | ... BB157: =IF(OR(ISERROR(+AB157/($D157+$E157-$G157)*$G157+AB157),LEFT(Z157,1)="x"),0,+AB157/($D157+$E157-$G157)*$G157+AB157) -> 0 | BC157: =IF(OR(ISERROR(+#REF!/($D157+$E157-$G157)*$G157+#REF!),LEFT(AA157,1)="x"),0,+#REF!/($D157+$E157-$G157)*$G157+#REF!) -> 0 | BD157: =IF(OR(ISERROR(+#REF!/($D157+$E157-$G157)*$G157+#REF!),LEFT(AB157,1)="x"),0,+#REF!/($D157+$E157-$G157)*$G157+#REF!) -> 0 | BE157: =IF(OR(ISERROR(+AC157/($D157+$E157-$G157)*$G157+AC157),LEFT(#REF!,1)="x"),0,+AC157/($D157+$E157-$G157)*$G157+AC157) -> #REF!
AD158: =SUM(G158:AC158) -> 0 | AE158: =SUM(D158:F158) -> 0 | AF158: =AD158-AE158 -> 0 | AG158: =IF(AF158=0,0,"ERROR HERE") -> 0 | AH158: =IF(OR(ISERROR(+H158/($D158+$E158-$G158)*$G158+H158),LEFT(F158,1)="x"),0,+H158/($D158+$E158-$G158)*$G158+H158) -> 0 | AI158: =IF(OR(ISERROR(+I158/($D158+$E158-$G158)*$G158+I158),LEFT(G158,1)="x"),0,+I158/($D158+$E158-$G158)*$G158+I158) -> 0 | AJ158: =IF(OR(ISERROR(+J158/($D158+$E158-$G158)*$G158+J158),LEFT(H158,1)="x"),0,+J158/($D158+$E158-$G158)*$G158+J158) -> 0 | AK158: =IF(OR(ISERROR(+K158/($D158+$E158-$G158)*$G158+K158),LEFT(I158,1)="x"),0,+K158/($D158+$E158-$G158)*$G158+K158) -> 0 | AL158: =IF(OR(ISERROR(+L158/($D158+$E158-$G158)*$G158+L158),LEFT(J158,1)="x"),0,+L158/($D158+$E158-$G158)*$G158+L158) -> 0 | AM158: =IF(OR(ISERROR(+M158/($D158+$E158-$G158)*$G158+M158),LEFT(K158,1)="x"),0,+M158/($D158+$E158-$G158)*$G158+M158) -> 0 | AN158: =IF(OR(ISERROR(+N158/($D158+$E158-$G158)*$G158+N158),LEFT(L158,1)="x"),0,+N158/($D158+$E158-$G158)*$G158+N158) -> 0 | AO158: =IF(OR(ISERROR(+O158/($D158+$E158-$G158)*$G158+O158),LEFT(M158,1)="x"),0,+O158/($D158+$E158-$G158)*$G158+O158) -> 0 | ... BB158: =IF(OR(ISERROR(+AB158/($D158+$E158-$G158)*$G158+AB158),LEFT(Z158,1)="x"),0,+AB158/($D158+$E158-$G158)*$G158+AB158) -> 0 | BC158: =IF(OR(ISERROR(+#REF!/($D158+$E158-$G158)*$G158+#REF!),LEFT(AA158,1)="x"),0,+#REF!/($D158+$E158-$G158)*$G158+#REF!) -> 0 | BD158: =IF(OR(ISERROR(+#REF!/($D158+$E158-$G158)*$G158+#REF!),LEFT(AB158,1)="x"),0,+#REF!/($D158+$E158-$G158)*$G158+#REF!) -> 0 | BE158: =IF(OR(ISERROR(+AC158/($D158+$E158-$G158)*$G158+AC158),LEFT(#REF!,1)="x"),0,+AC158/($D158+$E158-$G158)*$G158+AC158) -> #REF!
AD159: =SUM(G159:AC159) -> 0 | AE159: =SUM(D159:F159) -> 0 | AF159: =AD159-AE159 -> 0
AD160: =SUM(G160:AC160) -> 0 | AE160: =SUM(D160:F160) -> 0 | AF160: =AD160-AE160 -> 0
AD161: =SUM(G161:AC161) -> 0 | AE161: =SUM(D161:F161) -> 0 | AF161: =AD161-AE161 -> 0
AD162: =SUM(G162:AC162) -> 0 | AE162: =SUM(D162:F162) -> 0 | AF162: =AD162-AE162 -> 0
AD163: =SUM(G163:AC163) -> 0 | AE163: =SUM(D163:F163) -> 0 | AF163: =AD163-AE163 -> 0
AD164: =SUM(G164:AC164) -> 0 | AE164: =SUM(D164:F164) -> 0 | AF164: =AD164-AE164 -> 0
AD165: =SUM(G165:AC165) -> 0 | AE165: =SUM(D165:F165) -> 0 | AF165: =AD165-AE165 -> 0
AD166: =SUM(G166:AC166) -> 0 | AE166: =SUM(D166:F166) -> 0 | AF166: =AD166-AE166 -> 0
AD167: =SUM(G167:AC167) -> 0 | AE167: =SUM(D167:F167) -> 0 | AF167: =AD167-AE167 -> 0
AD168: =SUM(G168:AC168) -> 0 | AE168: =SUM(D168:F168) -> 0 | AF168: =AD168-AE168 -> 0
AD169: =SUM(G169:AC169) -> 0 | AE169: =SUM(D169:F169) -> 0 | AF169: =AD169-AE169 -> 0
AD170: =SUM(G170:AC170) -> 0 | AE170: =SUM(D170:F170) -> 0 | AF170: =AD170-AE170 -> 0
...

Sheet Feb 18
A2: ='Nov 17'!A2 -> Design-spectrum Limited
A4: Month | C4: ='Jan 18'!C4+31 -> 43133
A7: Sales Invoices | I7: Bankings - Receipts
A9: Does this months income fall within IR35? (Y/N/both) | E9: ='Jan 18'!E9 -> n | F9: =IF(E9="Both","enter sales invoices manually at row 30 onwards",0) -> 0
A11: Is the Company VAT registered (Y/N) | E11: ='Jan 18'!E11 -> y
A12: VAT Flat rate scheme percentage | E12: ='Jan 18'!E12 -> 0.165
A13: (leave blank or zero if not using flat rate scheme) | M13: Interest | O13: Transfers from | P13: Interest
L14: Sales Invoice | M14: Received on | O14: Deposit | P14: Received on
A15: Date | B15: Details | C15: Sales Invoice No | D15: IR35 | E15: Non IR35 | F15: Gross | G15: VAT | I15: Date | J15: Details | K15: Sales Invoice no | L15: Amount £ | M15: Current Account | N15: Other bankings | O15: Account | P15: Deposit Account
C16: Balance b/f | D16: ='Jan 18'!D54 -> 0 | E16: ='Jan 18'!E54 -> 19250 | F16: ='Jan 18'!F54 -> 23100 | G16: ='Jan 18'!G54 -> 3850 | J16: Balance b/f | L16: ='Jan 18'!L54 -> 46200 | M16: ='Jan 18'!M54 -> 66.53 | N16: ='Jan 18'!N54 -> 0 | O16: ='Jan 18'!O54 -> 50488.86 | P16: ='Jan 18'!P54 -> -61.08
B17: Invoice 2Jan-2Feb2018 | D17: =IF(E$9="y",F17-G17,0) -> 0 | E17: =IF(E$9="n",F17-G17,0) -> 13200 | F17: 15840 | G17: =IF(($E$11="n"),0,IF((LEFT(C17,1)="v"),F17,IF((LEFT(C17,1)="z"),0,F17*1/6))) -> 2640 | J17: R S C S LTD | L17: 15840
D18: =IF(E$9="y",F18-G18,0) -> 0 | E18: =IF(E$9="n",F18-G18,0) -> 0 | G18: =IF(($E$11="n"),0,IF((LEFT(C18,1)="v"),F18,IF((LEFT(C18,1)="z"),0,F18*1/6))) -> 0 | P18: 2.5
D19: =IF(E$9="y",F19-G19,0) -> 0 | E19: =IF(E$9="n",F19-G19,0) -> 0 | G19: =IF(($E$11="n"),0,IF((LEFT(C19,1)="v"),F19,IF((LEFT(C19,1)="z"),0,F19*1/6))) -> 0
D20: =IF(E$9="y",F20-G20,0) -> 0 | E20: =IF(E$9="n",F20-G20,0) -> 0 | G20: =IF(($E$11="n"),0,IF((LEFT(C20,1)="v"),F20,IF((LEFT(C20,1)="z"),0,F20*1/6))) -> 0
D21: =IF(E$9="y",F21-G21,0) -> 0 | E21: =IF(E$9="n",F21-G21,0) -> 0 | G21: =IF(($E$11="n"),0,IF((LEFT(C21,1)="v"),F21,IF((LEFT(C21,1)="z"),0,F21*1/6))) -> 0
D22: =IF(E$9="y",F22-G22,0) -> 0 | E22: =IF(E$9="n",F22-G22,0) -> 0 | G22: =IF(($E$11="n"),0,IF((LEFT(C22,1)="v"),F22,IF((LEFT(C22,1)="z"),0,F22*1/6))) -> 0
D23: =IF(E$9="y",F23-G23,0) -> 0 | E23: =IF(E$9="n",F23-G23,0) -> 0 | G23: =IF(($E$11="n"),0,IF((LEFT(C23,1)="v"),F23,IF((LEFT(C23,1)="z"),0,F23*1/6))) -> 0
D24: =IF(E$9="y",F24-G24,0) -> 0 | E24: =IF(E$9="n",F24-G24,0) -> 0 | G24: =IF(($E$11="n"),0,IF((LEFT(C24,1)="v"),F24,IF((LEFT(C24,1)="z"),0,F24*1/6))) -> 0
D25: =IF(E$9="y",F25-G25,0) -> 0 | E25: =IF(E$9="n",F25-G25,0) -> 0 | G25: =IF(($E$11="n"),0,IF((LEFT(C25,1)="v"),F25,IF((LEFT(C25,1)="z"),0,F25*1/6))) -> 0
D26: =IF(E$9="y",F26-G26,0) -> 0 | E26: =IF(E$9="n",F26-G26,0) -> 0 | G26: =IF(($E$11="n"),0,IF((LEFT(C26,1)="v"),F26,IF((LEFT(C26,1)="z"),0,F26*1/6))) -> 0
D27: =IF(E$9="y",F27-G27,0) -> 0 | E27: =IF(E$9="n",F27-G27,0) -> 0 | G27: =IF(($E$11="n"),0,IF((LEFT(C27,1)="v"),F27,IF((LEFT(C27,1)="z"),0,F27*1/6))) -> 0
D28: =IF(E$9="y",F28-G28,0) -> 0 | E28: =IF(E$9="n",F28-G28,0) -> 0 | G28: =IF(($E$11="n"),0,IF((LEFT(C28,1)="v"),F28,IF((LEFT(C28,1)="z"),0,F28*1/6))) -> 0
D29: =IF(E$9="y",F29-G29,0) -> 0 | E29: =IF(E$9="n",F29-G29,0) -> 0 | G29: =IF(($E$11="n"),0,IF((LEFT(C29,1)="v"),F29,IF((LEFT(C29,1)="z"),0,F29*1/6))) -> 0
D30: =IF(E$9="y",F30-G30,0) -> 0 | E30: =IF(E$9="n",F30-G30,0) -> 0 | G30: =IF(($E$11="n"),0,IF((LEFT(C30,1)="v"),F30,IF((LEFT(C30,1)="z"),0,F30*1/6))) -> 0
... D40: =IF(E$9="y",F40-G40,0) -> 0 | E40: =IF(E$9="n",F40-G40,0) -> 0 | G40: =IF(($E$11="n"),0,IF((LEFT(C40,1)="v"),F40,IF((LEFT(C40,1)="z"),0,F40*1/6))) -> 0
B41: =IF(E9="Both","Enter manual values here",0) -> 0 | D41: =IF(E$9="y",F41-G41,0) -> 0 | E41: =IF(E$9="n",F41-G41,0) -> 0 | G41: =IF(($E$11="n"),0,IF((LEFT(C41,1)="v"),F41,IF((LEFT(C41,1)="z"),0,F41*1/6))) -> 0
D42: =IF(E$9="y",F42-G42,0) -> 0 | E42: =IF(E$9="n",F42-G42,0) -> 0 | G42: =IF(($E$11="n"),0,IF((LEFT(C42,1)="v"),F42,IF((LEFT(C42,1)="z"),0,F42*1/6))) -> 0
D43: =IF(E$9="y",F43-G43,0) -> 0 | E43: =IF(E$9="n",F43-G43,0) -> 0 | G43: =IF(($E$11="n"),0,IF((LEFT(C43,1)="v"),F43,IF((LEFT(C43,1)="z"),0,F43*1/6))) -> 0
D44: =IF(E$9="y",F44-G44,0) -> 0 | E44: =IF(E$9="n",F44-G44,0) -> 0 | G44: =IF(($E$11="n"),0,IF((LEFT(C44,1)="v"),F44,IF((LEFT(C44,1)="z"),0,F44*1/6))) -> 0
D45: =IF(E$9="y",F45-G45,0) -> 0 | E45: =IF(E$9="n",F45-G45,0) -> 0 | G45: =IF(($E$11="n"),0,IF((LEFT(C45,1)="v"),F45,IF((LEFT(C45,1)="z"),0,F45*1/6))) -> 0
D46: =IF(E$9="y",F46-G46,0) -> 0 | E46: =IF(E$9="n",F46-G46,0) -> 0 | G46: =IF(($E$11="n"),0,IF((LEFT(C46,1)="v"),F46,IF((LEFT(C46,1)="z"),0,F46*1/6))) -> 0
D47: =IF(E$9="y",F47-G47,0) -> 0 | E47: =IF(E$9="n",F47-G47,0) -> 0 | G47: =IF(($E$11="n"),0,IF((LEFT(C47,1)="v"),F47,IF((LEFT(C47,1)="z"),0,F47*1/6))) -> 0
D48: =IF(E$9="y",F48-G48,0) -> 0 | E48: =IF(E$9="n",F48-G48,0) -> 0 | G48: =IF(($E$11="n"),0,IF((LEFT(C48,1)="v"),F48,IF((LEFT(C48,1)="z"),0,F48*1/6))) -> 0
D49: =IF(E$9="y",F49-G49,0) -> 0 | E49: =IF(E$9="n",F49-G49,0) -> 0 | G49: =IF(($E$11="n"),0,IF((LEFT(C49,1)="v"),F49,IF((LEFT(C49,1)="z"),0,F49*1/6))) -> 0
D50: =IF(E$9="y",F50-G50,0) -> 0 | E50: =IF(E$9="n",F50-G50,0) -> 0 | G50: =IF(($E$11="n"),0,IF((LEFT(C50,1)="v"),F50,IF((LEFT(C50,1)="z"),0,F50*1/6))) -> 0
D51: =IF(E$9="y",F51-G51,0) -> 0 | E51: =IF(E$9="n",F51-G51,0) -> 0 | G51: =IF(($E$11="n"),0,IF((LEFT(C51,1)="v"),F51,IF((LEFT(C51,1)="z"),0,F51*1/6))) -> 0
D52: =IF(E$9="y",F52-G52,0) -> 0 | E52: =IF(E$9="n",F52-G52,0) -> 0 | G52: =IF(($E$11="n"),0,IF((LEFT(C52,1)="v"),F52,IF((LEFT(C52,1)="z"),0,F52*1/6))) -> 0
A53: Total | D53: =SUM(D17:D52) -> 0 | E53: =SUM(E17:E52) -> 13200 | F53: =SUM(F17:F52) -> 15840 | G53: =SUM(G17:G52) -> 2640 | I53: Total | L53: =SUM(L17:L52) -> 15840 | M53: =SUM(M17:M52) -> 0 | N53: =SUM(N17:N52) -> 0 | O53: =SUM(O17:O52) -> 0 | P53: =SUM(P17:P52) -> 2.5
A54: C/fwd | D54: =SUM(D16:D52) -> 0 | E54: =SUM(E16:E52) -> 32450 | F54: =SUM(F16:F52) -> 38940 | G54: =SUM(G16:G52) -> 6490 | I54: C/fwd | L54: =SUM(L16:L52) -> 62040 | M54: =SUM(M16:M52) -> 66.53 | N54: =SUM(N16:N52) -> 0 | O54: =SUM(O16:O52) -> 50488.86 | P54: =SUM(P16:P52) -> -58.58
A56: IR35 Details (ignore if outside IR35): | D56: Flat Rate Scheme Details (ignore if outside FRS):
A58: Deemed Salary | C58: =IF(E9="y",G59*0.95-(SUM(H197:K197)),0) -> 0 | E58: Per List Above | F58: FRS | G58: VAT account figures
A59: Deemed Salary | C59: =IF(E9="both",G59*0.95-(SUM(H197:K197)),0) -> 0 | D59: IR35 | E59: =+D53 -> 0 | F59: =+G59-E59 -> 0 | G59: =IF(E59+E60<>0,E59/(E59+E60)*(G61-G62),0) -> 0
D60: Non IR35 | E60: =+E53 -> 13200 | F60: =+G60-E60 -> 26.4 | G60: =IF(E59+E60<>0,E60/(E59+E60)*(G61-G62),0) -> 13226.4
D61: Gross | E61: =+F53 -> 15840 | F61: =+G61-E61 -> 0 | G61: =+E61 -> 15840
A62: Total PAYE & NI Due on deemed salary | C62: =IF(E243<=0,0,IF(C4<42095,E265,E243)) -> 0 | D62: VAT | E62: =+G53 -> 2640 | F62: =+G62-E62 -> -26.4 | G62: =IF(E12>0,(G61)*E12,E62) -> 2613.6
A63: 41730 = Numerical Value of 01 April 2014
A65: Tax provision to be made
A66: (payable by 19th April 2016) | C66: =C62 -> 0
A69: Net salary available to draw | C69: =C58+C59-C66 -> 0
A70: (after all taxes, NI and allowable expenses)
A74: Expenditure
H76: Motor | I76: Travelling, | J76: Professional, Public | P76: Printing, | S76: Computer | T76: Books, | V76: Bank Charges | X76: Transfers to | Z76: Corporation | AA76: Directors
C77: Reference / | D77: Company | E77: Cash/Personal | F77: Company | H77: Expenses Or | I77: Accommodation | J77: and Employers | K77: Company | M77: PAYE & NIC | O77: Cost of | P77: Postage & | Q77: Internet & | R77: Assets | S77: Related | T77: Journals & | V77: & Interest | X77: Deposit | Y77: VAT paid to | Z77: Tax paid to | AA77: Loan | AB77: Business
A78: Date | B78: Details | C78: Cheque No | D78: Bank | E78: Expenses | F78: Credit Card | G78: VAT | H78: Mileage Claims | I78: & Subsistence | J78: Liability Insurance | K78: Pension | L78: Net salary paid | M78: paid to HMR&C | N78: Dividends | O78: Goods sold | P78: Stationery | Q78: Telephone | R78: Purchased | S78: Costs | T78: Subscriptions | U78: Accountancy | V78: Payable | W78: Use of Home | X78: Account | Y78: HMC&E | Z78: HMR&C | AA78: Account | AB78: Entertainment | AC78: Sundries | AF78: error line?
B79: Balance b/f | D79: ='Jan 18'!D198 -> 68855.49 | E79: ='Jan 18'!E198 -> -901 | F79: ='Jan 18'!F198 -> 0 | G79: ='Jan 18'!G198 -> 0 | H79: ='Jan 18'!H198 -> 675 | I79: ='Jan 18'!I198 -> 492 | J79: ='Jan 18'!J198 -> 105 | K79: ='Jan 18'!K198 -> 0 | ... AC79: ='Jan 18'!AC198 -> 0 | AG79: =IF(AF79=0,0,"ERROR HERE") -> 0 | AH79: =IF(OR(ISERROR(+H79/($D79+$E79-$G79)*$G79+H79),LEFT(F79,1)="x"),0,+H79/($D79+$E79-$G79)*$G79+H79) -> 675 | AI79: =IF(OR(ISERROR(+I79/($D79+$E79-$G79)*$G79+I79),LEFT(G79,1)="x"),0,+I79/($D79+$E79-$G79)*$G79+I79) -> 492 | AJ79: =IF(OR(ISERROR(+J79/($D79+$E79-$G79)*$G79+J79),LEFT(H79,1)="x"),0,+J79/($D79+$E79-$G79)*$G79+J79) -> 105 | AK79: =IF(OR(ISERROR(+K79/($D79+$E79-$G79)*$G79+K79),LEFT(I79,1)="x"),0,+K79/($D79+$E79-$G79)*$G79+K79) -> 0 | AL79: =IF(OR(ISERROR(+L79/($D79+$E79-$G79)*$G79+L79),LEFT(J79,1)="x"),0,+L79/($D79+$E79-$G79)*$G79+L79) -> 7296 | AM79: =IF(OR(ISERROR(+M79/($D79+$E79-$G79)*$G79+M79),LEFT(K79,1)="x"),0,+M79/($D79+$E79-$G79)*$G79+M79) -> 0 | AN79: =IF(OR(ISERROR(+N79/($D79+$E79-$G79)*$G79+N79),LEFT(L79,1)="x"),0,+N79/($D79+$E79-$G79)*$G79+N79) -> 0 | AO79: =IF(OR(ISERROR(+O79/($D79+$E79-$G79)*$G79+O79),LEFT(M79,1)="x"),0,+O79/($D79+$E79-$G79)*$G79+O79) -> 0 | ... BB79: =IF(OR(ISERROR(+AB79/($D79+$E79-$G79)*$G79+AB79),LEFT(Z79,1)="x"),0,+AB79/($D79+$E79-$G79)*$G79+AB79) -> 471 | BC79: =IF(OR(ISERROR(+#REF!/($D79+$E79-$G79)*$G79+#REF!),LEFT(AA79,1)="x"),0,+#REF!/($D79+$E79-$G79)*$G79+#REF!) -> 0 | BD79: =IF(OR(ISERROR(+AC79/($D79+$E79-$G79)*$G79+AC79),LEFT(Z79,1)="x"),0,+AC79/($D79+$E79-$G79)*$G79+AC79) -> 0
B80: Salary Director S Haldar | D80: 924 | L80: 924 | AD80: =SUM(G80:AC80) -> 924 | AE80: =SUM(D80:F80) -> 924 | AF80: =AD80-AE80 -> 0 | AG80: =IF(AF80=0,0,"ERROR HERE") -> 0 | AH80: =IF(OR(ISERROR(+H80/($D80+$E80-$G80)*$G80+H80),LEFT(F80,1)="x"),0,+H80/($D80+$E80-$G80)*$G80+H80) -> 0 | AI80: =IF(OR(ISERROR(+I80/($D80+$E80-$G80)*$G80+I80),LEFT(G80,1)="x"),0,+I80/($D80+$E80-$G80)*$G80+I80) -> 0 | AJ80: =IF(OR(ISERROR(+J80/($D80+$E80-$G80)*$G80+J80),LEFT(H80,1)="x"),0,+J80/($D80+$E80-$G80)*$G80+J80) -> 0 | AK80: =IF(OR(ISERROR(+K80/($D80+$E80-$G80)*$G80+K80),LEFT(I80,1)="x"),0,+K80/($D80+$E80-$G80)*$G80+K80) -> 0 | AL80: =IF(OR(ISERROR(+L80/($D80+$E80-$G80)*$G80+L80),LEFT(J80,1)="x"),0,+L80/($D80+$E80-$G80)*$G80+L80) -> 924 | AM80: =IF(OR(ISERROR(+M80/($D80+$E80-$G80)*$G80+M80),LEFT(K80,1)="x"),0,+M80/($D80+$E80-$G80)*$G80+M80) -> 0 | AN80: =IF(OR(ISERROR(+N80/($D80+$E80-$G80)*$G80+N80),LEFT(L80,1)="x"),0,+N80/($D80+$E80-$G80)*$G80+N80) -> 0 | AO80: =IF(OR(ISERROR(+O80/($D80+$E80-$G80)*$G80+O80),LEFT(M80,1)="x"),0,+O80/($D80+$E80-$G80)*$G80+O80) -> 0 | ... BB80: =IF(OR(ISERROR(+AB80/($D80+$E80-$G80)*$G80+AB80),LEFT(Z80,1)="x"),0,+AB80/($D80+$E80-$G80)*$G80+AB80) -> 0 | BC80: =IF(OR(ISERROR(+#REF!/($D80+$E80-$G80)*$G80+#REF!),LEFT(AA80,1)="x"),0,+#REF!/($D80+$E80-$G80)*$G80+#REF!) -> 0 | BD80: =IF(OR(ISERROR(+AC80/($D80+$E80-$G80)*$G80+AC80),LEFT(Z80,1)="x"),0,+AC80/($D80+$E80-$G80)*$G80+AC80) -> 0
B81: Salary Director S Deb | D81: 900 | L81: 900 | AD81: =SUM(G81:AC81) -> 900 | AE81: =SUM(D81:F81) -> 900 | AF81: =AD81-AE81 -> 0 | AG81: =IF(AF81=0,0,"ERROR HERE") -> 0 | AH81: =IF(OR(ISERROR(+H81/($D81+$E81-$G81)*$G81+H81),LEFT(F81,1)="x"),0,+H81/($D81+$E81-$G81)*$G81+H81) -> 0 | AI81: =IF(OR(ISERROR(+I81/($D81+$E81-$G81)*$G81+I81),LEFT(G81,1)="x"),0,+I81/($D81+$E81-$G81)*$G81+I81) -> 0 | AJ81: =IF(OR(ISERROR(+J81/($D81+$E81-$G81)*$G81+J81),LEFT(H81,1)="x"),0,+J81/($D81+$E81-$G81)*$G81+J81) -> 0 | AK81: =IF(OR(ISERROR(+K81/($D81+$E81-$G81)*$G81+K81),LEFT(I81,1)="x"),0,+K81/($D81+$E81-$G81)*$G81+K81) -> 0 | AL81: =IF(OR(ISERROR(+L81/($D81+$E81-$G81)*$G81+L81),LEFT(J81,1)="x"),0,+L81/($D81+$E81-$G81)*$G81+L81) -> 900 | AM81: =IF(OR(ISERROR(+M81/($D81+$E81-$G81)*$G81+M81),LEFT(K81,1)="x"),0,+M81/($D81+$E81-$G81)*$G81+M81) -> 0 | AN81: =IF(OR(ISERROR(+N81/($D81+$E81-$G81)*$G81+N81),LEFT(L81,1)="x"),0,+N81/($D81+$E81-$G81)*$G81+N81) -> 0 | AO81: =IF(OR(ISERROR(+O81/($D81+$E81-$G81)*$G81+O81),LEFT(M81,1)="x"),0,+O81/($D81+$E81-$G81)*$G81+O81) -> 0 | ... BB81: =IF(OR(ISERROR(+AB81/($D81+$E81-$G81)*$G81+AB81),LEFT(Z81,1)="x"),0,+AB81/($D81+$E81-$G81)*$G81+AB81) -> 0 | BC81: =IF(OR(ISERROR(+#REF!/($D81+$E81-$G81)*$G81+#REF!),LEFT(AA81,1)="x"),0,+#REF!/($D81+$E81-$G81)*$G81+#REF!) -> 0 | BD81: =IF(OR(ISERROR(+AC81/($D81+$E81-$G81)*$G81+AC81),LEFT(Z81,1)="x"),0,+AC81/($D81+$E81-$G81)*$G81+AC81) -> 0
B82: Accountancy fees | D82: 138 | U82: 138 | AD82: =SUM(G82:AC82) -> 138 | AE82: =SUM(D82:F82) -> 138 | AF82: =AD82-AE82 -> 0 | AG82: =IF(AF82=0,0,"ERROR HERE - CHECK NUMBER IS CORRECTLY EXTENDED") -> 0 | AH82: =IF(OR(ISERROR(+H82/($D82+$E82-$G82)*$G82+H82),LEFT(F82,1)="x"),0,+H82/($D82+$E82-$G82)*$G82+H82) -> 0 | AI82: =IF(OR(ISERROR(+I82/($D82+$E82-$G82)*$G82+I82),LEFT(G82,1)="x"),0,+I82/($D82+$E82-$G82)*$G82+I82) -> 0 | AJ82: =IF(OR(ISERROR(+J82/($D82+$E82-$G82)*$G82+J82),LEFT(H82,1)="x"),0,+J82/($D82+$E82-$G82)*$G82+J82) -> 0 | AK82: =IF(OR(ISERROR(+K82/($D82+$E82-$G82)*$G82+K82),LEFT(I82,1)="x"),0,+K82/($D82+$E82-$G82)*$G82+K82) -> 0 | AL82: =IF(OR(ISERROR(+L82/($D82+$E82-$G82)*$G82+L82),LEFT(J82,1)="x"),0,+L82/($D82+$E82-$G82)*$G82+L82) -> 0 | AM82: =IF(OR(ISERROR(+M82/($D82+$E82-$G82)*$G82+M82),LEFT(K82,1)="x"),0,+M82/($D82+$E82-$G82)*$G82+M82) -> 0 | AN82: =IF(OR(ISERROR(+N82/($D82+$E82-$G82)*$G82+N82),LEFT(L82,1)="x"),0,+N82/($D82+$E82-$G82)*$G82+N82) -> 0 | AO82: =IF(OR(ISERROR(+O82/($D82+$E82-$G82)*$G82+O82),LEFT(M82,1)="x"),0,+O82/($D82+$E82-$G82)*$G82+O82) -> 0 | ... BB82: =IF(OR(ISERROR(+AB82/($D82+$E82-$G82)*$G82+AB82),LEFT(Z82,1)="x"),0,+AB82/($D82+$E82-$G82)*$G82+AB82) -> 0 | BC82: =IF(OR(ISERROR(+#REF!/($D82+$E82-$G82)*$G82+#REF!),LEFT(AA82,1)="x"),0,+#REF!/($D82+$E82-$G82)*$G82+#REF!) -> 0 | BD82: =IF(OR(ISERROR(+#REF!/($D82+$E82-$G82)*$G82+#REF!),LEFT(AB82,1)="x"),0,+#REF!/($D82+$E82-$G82)*$G82+#REF!) -> 0 | BE82: =IF(OR(ISERROR(+AC82/($D82+$E82-$G82)*$G82+AC82),LEFT(#REF!,1)="x"),0,+AC82/($D82+$E82-$G82)*$G82+AC82) -> #REF!
B83: Bus & Tube fare | E83: 164 | I83: 164 | AD83: =SUM(G83:AC83) -> 164 | AE83: =SUM(D83:F83) -> 164 | AF83: =AD83-AE83 -> 0 | AG83: =IF(AF83=0,0,"ERROR HERE") -> 0 | AH83: =IF(OR(ISERROR(+H83/($D83+$E83-$G83)*$G83+H83),LEFT(F83,1)="x"),0,+H83/($D83+$E83-$G83)*$G83+H83) -> 0 | AI83: =IF(OR(ISERROR(+I83/($D83+$E83-$G83)*$G83+I83),LEFT(G83,1)="x"),0,+I83/($D83+$E83-$G83)*$G83+I83) -> 164 | AJ83: =IF(OR(ISERROR(+J83/($D83+$E83-$G83)*$G83+J83),LEFT(H83,1)="x"),0,+J83/($D83+$E83-$G83)*$G83+J83) -> 0 | AK83: =IF(OR(ISERROR(+K83/($D83+$E83-$G83)*$G83+K83),LEFT(I83,1)="x"),0,+K83/($D83+$E83-$G83)*$G83+K83) -> 0 | AL83: =IF(OR(ISERROR(+L83/($D83+$E83-$G83)*$G83+L83),LEFT(J83,1)="x"),0,+L83/($D83+$E83-$G83)*$G83+L83) -> 0 | AM83: =IF(OR(ISERROR(+M83/($D83+$E83-$G83)*$G83+M83),LEFT(K83,1)="x"),0,+M83/($D83+$E83-$G83)*$G83+M83) -> 0 | AN83: =IF(OR(ISERROR(+N83/($D83+$E83-$G83)*$G83+N83),LEFT(L83,1)="x"),0,+N83/($D83+$E83-$G83)*$G83+N83) -> 0 | AO83: =IF(OR(ISERROR(+O83/($D83+$E83-$G83)*$G83+O83),LEFT(M83,1)="x"),0,+O83/($D83+$E83-$G83)*$G83+O83) -> 0 | ... BB83: =IF(OR(ISERROR(+AB83/($D83+$E83-$G83)*$G83+AB83),LEFT(Z83,1)="x"),0,+AB83/($D83+$E83-$G83)*$G83+AB83) -> 0 | BC83: =IF(OR(ISERROR(+#REF!/($D83+$E83-$G83)*$G83+#REF!),LEFT(AA83,1)="x"),0,+#REF!/($D83+$E83-$G83)*$G83+#REF!) -> 0 | BD83: =IF(OR(ISERROR(+#REF!/($D83+$E83-$G83)*$G83+#REF!),LEFT(AB83,1)="x"),0,+#REF!/($D83+$E83-$G83)*$G83+#REF!) -> 0 | BE83: =IF(OR(ISERROR(+AC83/($D83+$E83-$G83)*$G83+AC83),LEFT(#REF!,1)="x"),0,+AC83/($D83+$E83-$G83)*$G83+AC83) -> #REF!
B84: Postage | E84: 20 | P84: 20 | AD84: =SUM(G84:AC84) -> 20 | AE84: =SUM(D84:F84) -> 20 | AF84: =AD84-AE84 -> 0 | AG84: =IF(AF84=0,0,"ERROR HERE") -> 0 | AH84: =IF(OR(ISERROR(+H84/($D84+$E84-$G84)*$G84+H84),LEFT(F84,1)="x"),0,+H84/($D84+$E84-$G84)*$G84+H84) -> 0 | AI84: =IF(OR(ISERROR(+I84/($D84+$E84-$G84)*$G84+I84),LEFT(G84,1)="x"),0,+I84/($D84+$E84-$G84)*$G84+I84) -> 0 | AJ84: =IF(OR(ISERROR(+J84/($D84+$E84-$G84)*$G84+J84),LEFT(H84,1)="x"),0,+J84/($D84+$E84-$G84)*$G84+J84) -> 0 | AK84: =IF(OR(ISERROR(+K84/($D84+$E84-$G84)*$G84+K84),LEFT(I84,1)="x"),0,+K84/($D84+$E84-$G84)*$G84+K84) -> 0 | AL84: =IF(OR(ISERROR(+L84/($D84+$E84-$G84)*$G84+L84),LEFT(J84,1)="x"),0,+L84/($D84+$E84-$G84)*$G84+L84) -> 0 | AM84: =IF(OR(ISERROR(+M84/($D84+$E84-$G84)*$G84+M84),LEFT(K84,1)="x"),0,+M84/($D84+$E84-$G84)*$G84+M84) -> 0 | AN84: =IF(OR(ISERROR(+N84/($D84+$E84-$G84)*$G84+N84),LEFT(L84,1)="x"),0,+N84/($D84+$E84-$G84)*$G84+N84) -> 0 | AO84: =IF(OR(ISERROR(+O84/($D84+$E84-$G84)*$G84+O84),LEFT(M84,1)="x"),0,+O84/($D84+$E84-$G84)*$G84+O84) -> 0 | ... BB84: =IF(OR(ISERROR(+AB84/($D84+$E84-$G84)*$G84+AB84),LEFT(Z84,1)="x"),0,+AB84/($D84+$E84-$G84)*$G84+AB84) -> 0 | BC84: =IF(OR(ISERROR(+#REF!/($D84+$E84-$G84)*$G84+#REF!),LEFT(AA84,1)="x"),0,+#REF!/($D84+$E84-$G84)*$G84+#REF!) -> 0 | BD84: =IF(OR(ISERROR(+#REF!/($D84+$E84-$G84)*$G84+#REF!),LEFT(AB84,1)="x"),0,+#REF!/($D84+$E84-$G84)*$G84+#REF!) -> 0 | BE84: =IF(OR(ISERROR(+AC84/($D84+$E84-$G84)*$G84+AC84),LEFT(#REF!,1)="x"),0,+AC84/($D84+$E84-$G84)*$G84+AC84) -> #REF!
B85: use of residence as office | E85: 95 | W85: 95 | AD85: =SUM(G85:AC85) -> 95 | AE85: =SUM(D85:F85) -> 95 | AF85: =AD85-AE85 -> 0 | AG85: =IF(AF85=0,0,"ERROR HERE") -> 0 | AH85: =IF(OR(ISERROR(+H85/($D85+$E85-$G85)*$G85+H85),LEFT(F85,1)="x"),0,+H85/($D85+$E85-$G85)*$G85+H85) -> 0 | AI85: =IF(OR(ISERROR(+I85/($D85+$E85-$G85)*$G85+I85),LEFT(G85,1)="x"),0,+I85/($D85+$E85-$G85)*$G85+I85) -> 0 | AJ85: =IF(OR(ISERROR(+J85/($D85+$E85-$G85)*$G85+J85),LEFT(H85,1)="x"),0,+J85/($D85+$E85-$G85)*$G85+J85) -> 0 | AK85: =IF(OR(ISERROR(+K85/($D85+$E85-$G85)*$G85+K85),LEFT(I85,1)="x"),0,+K85/($D85+$E85-$G85)*$G85+K85) -> 0 | AL85: =IF(OR(ISERROR(+L85/($D85+$E85-$G85)*$G85+L85),LEFT(J85,1)="x"),0,+L85/($D85+$E85-$G85)*$G85+L85) -> 0 | AM85: =IF(OR(ISERROR(+M85/($D85+$E85-$G85)*$G85+M85),LEFT(K85,1)="x"),0,+M85/($D85+$E85-$G85)*$G85+M85) -> 0 | AN85: =IF(OR(ISERROR(+N85/($D85+$E85-$G85)*$G85+N85),LEFT(L85,1)="x"),0,+N85/($D85+$E85-$G85)*$G85+N85) -> 0 | AO85: =IF(OR(ISERROR(+O85/($D85+$E85-$G85)*$G85+O85),LEFT(M85,1)="x"),0,+O85/($D85+$E85-$G85)*$G85+O85) -> 0 | ... BB85: =IF(OR(ISERROR(+AB85/($D85+$E85-$G85)*$G85+AB85),LEFT(Z85,1)="x"),0,+AB85/($D85+$E85-$G85)*$G85+AB85) -> 0 | BC85: =IF(OR(ISERROR(+#REF!/($D85+$E85-$G85)*$G85+#REF!),LEFT(AA85,1)="x"),0,+#REF!/($D85+$E85-$G85)*$G85+#REF!) -> 0 | BD85: =IF(OR(ISERROR(+#REF!/($D85+$E85-$G85)*$G85+#REF!),LEFT(AB85,1)="x"),0,+#REF!/($D85+$E85-$G85)*$G85+#REF!) -> 0 | BE85: =IF(OR(ISERROR(+AC85/($D85+$E85-$G85)*$G85+AC85),LEFT(#REF!,1)="x"),0,+AC85/($D85+$E85-$G85)*$G85+AC85) -> #REF!
B86: Subscriptions | E86: 85 | T86: 85 | AD86: =SUM(G86:AC86) -> 85 | AE86: =SUM(D86:F86) -> 85 | AF86: =AD86-AE86 -> 0 | AG86: =IF(AF86=0,0,"ERROR HERE") -> 0 | AH86: =IF(OR(ISERROR(+H86/($D86+$E86-$G86)*$G86+H86),LEFT(F86,1)="x"),0,+H86/($D86+$E86-$G86)*$G86+H86) -> 0 | AI86: =IF(OR(ISERROR(+I86/($D86+$E86-$G86)*$G86+I86),LEFT(G86,1)="x"),0,+I86/($D86+$E86-$G86)*$G86+I86) -> 0 | AJ86: =IF(OR(ISERROR(+J86/($D86+$E86-$G86)*$G86+J86),LEFT(H86,1)="x"),0,+J86/($D86+$E86-$G86)*$G86+J86) -> 0 | AK86: =IF(OR(ISERROR(+K86/($D86+$E86-$G86)*$G86+K86),LEFT(I86,1)="x"),0,+K86/($D86+$E86-$G86)*$G86+K86) -> 0 | AL86: =IF(OR(ISERROR(+L86/($D86+$E86-$G86)*$G86+L86),LEFT(J86,1)="x"),0,+L86/($D86+$E86-$G86)*$G86+L86) -> 0 | AM86: =IF(OR(ISERROR(+M86/($D86+$E86-$G86)*$G86+M86),LEFT(K86,1)="x"),0,+M86/($D86+$E86-$G86)*$G86+M86) -> 0 | AN86: =IF(OR(ISERROR(+N86/($D86+$E86-$G86)*$G86+N86),LEFT(L86,1)="x"),0,+N86/($D86+$E86-$G86)*$G86+N86) -> 0 | AO86: =IF(OR(ISERROR(+O86/($D86+$E86-$G86)*$G86+O86),LEFT(M86,1)="x"),0,+O86/($D86+$E86-$G86)*$G86+O86) -> 0 | ... BB86: =IF(OR(ISERROR(+AB86/($D86+$E86-$G86)*$G86+AB86),LEFT(Z86,1)="x"),0,+AB86/($D86+$E86-$G86)*$G86+AB86) -> 0 | BC86: =IF(OR(ISERROR(+#REF!/($D86+$E86-$G86)*$G86+#REF!),LEFT(AA86,1)="x"),0,+#REF!/($D86+$E86-$G86)*$G86+#REF!) -> 0 | BD86: =IF(OR(ISERROR(+#REF!/($D86+$E86-$G86)*$G86+#REF!),LEFT(AB86,1)="x"),0,+#REF!/($D86+$E86-$G86)*$G86+#REF!) -> 0 | BE86: =IF(OR(ISERROR(+AC86/($D86+$E86-$G86)*$G86+AC86),LEFT(#REF!,1)="x"),0,+AC86/($D86+$E86-$G86)*$G86+AC86) -> #REF!
B87: Motor expenses (Parking, Maintainance) | E87: 225 | H87: 225 | AD87: =SUM(G87:AC87) -> 225 | AE87: =SUM(D87:F87) -> 225 | AF87: =AD87-AE87 -> 0 | AG87: =IF(AF87=0,0,"ERROR HERE") -> 0 | AH87: =IF(OR(ISERROR(+H87/($D87+$E87-$G87)*$G87+H87),LEFT(F87,1)="x"),0,+H87/($D87+$E87-$G87)*$G87+H87) -> 225 | AI87: =IF(OR(ISERROR(+I87/($D87+$E87-$G87)*$G87+I87),LEFT(G87,1)="x"),0,+I87/($D87+$E87-$G87)*$G87+I87) -> 0 | AJ87: =IF(OR(ISERROR(+J87/($D87+$E87-$G87)*$G87+J87),LEFT(H87,1)="x"),0,+J87/($D87+$E87-$G87)*$G87+J87) -> 0 | AK87: =IF(OR(ISERROR(+K87/($D87+$E87-$G87)*$G87+K87),LEFT(I87,1)="x"),0,+K87/($D87+$E87-$G87)*$G87+K87) -> 0 | AL87: =IF(OR(ISERROR(+L87/($D87+$E87-$G87)*$G87+L87),LEFT(J87,1)="x"),0,+L87/($D87+$E87-$G87)*$G87+L87) -> 0 | AM87: =IF(OR(ISERROR(+M87/($D87+$E87-$G87)*$G87+M87),LEFT(K87,1)="x"),0,+M87/($D87+$E87-$G87)*$G87+M87) -> 0 | AN87: =IF(OR(ISERROR(+N87/($D87+$E87-$G87)*$G87+N87),LEFT(L87,1)="x"),0,+N87/($D87+$E87-$G87)*$G87+N87) -> 0 | AO87: =IF(OR(ISERROR(+O87/($D87+$E87-$G87)*$G87+O87),LEFT(M87,1)="x"),0,+O87/($D87+$E87-$G87)*$G87+O87) -> 0 | ... BB87: =IF(OR(ISERROR(+AB87/($D87+$E87-$G87)*$G87+AB87),LEFT(Z87,1)="x"),0,+AB87/($D87+$E87-$G87)*$G87+AB87) -> 0 | BC87: =IF(OR(ISERROR(+#REF!/($D87+$E87-$G87)*$G87+#REF!),LEFT(AA87,1)="x"),0,+#REF!/($D87+$E87-$G87)*$G87+#REF!) -> 0 | BD87: =IF(OR(ISERROR(+#REF!/($D87+$E87-$G87)*$G87+#REF!),LEFT(AB87,1)="x"),0,+#REF!/($D87+$E87-$G87)*$G87+#REF!) -> 0 | BE87: =IF(OR(ISERROR(+AC87/($D87+$E87-$G87)*$G87+AC87),LEFT(#REF!,1)="x"),0,+AC87/($D87+$E87-$G87)*$G87+AC87) -> #REF!
B88: Business lunch | E88: 157 | AB88: 157 | AD88: =SUM(G88:AC88) -> 157 | AE88: =SUM(D88:F88) -> 157 | AF88: =AD88-AE88 -> 0
B89: Computer related costs | E89: 55 | S89: 55 | AD89: =SUM(G89:AC89) -> 55 | AE89: =SUM(D89:F89) -> 55 | AF89: =AD89-AE89 -> 0
B90: Telephone Costs | E90: 65 | R90: 65 | AD90: =SUM(G90:AC90) -> 65 | AE90: =SUM(D90:F90) -> 65 | AF90: =AD90-AE90 -> 0
B91: Insurance | E91: 35 | J91: 35 | N91: . | AD91: =SUM(G91:AC91) -> 35 | AE91: =SUM(D91:F91) -> 35 | AF91: =AD91-AE91 -> 0
B92: Bank Charges(+ £4 CHARGE UNPAID ITEM IN) | D92: 9.5 | V92: 9.5 | AD92: =SUM(G92:AC92) -> 9.5 | AE92: =SUM(D92:F92) -> 9.5 | AF92: =AD92-AE92 -> 0
D93: 0 | E93: 0 | AD93: =SUM(G93:AC93) -> 0 | AE93: =SUM(D93:F93) -> 0 | AF93: =AD93-AE93 -> 0
AD94: =SUM(G94:AC94) -> 0 | AE94: =SUM(D94:F94) -> 0 | AF94: =AD94-AE94 -> 0
AD95: =SUM(G95:AC95) -> 0 | AE95: =SUM(D95:F95) -> 0 | AF95: =AD95-AE95 -> 0
AD96: =SUM(G96:AC96) -> 0 | AE96: =SUM(D96:F96) -> 0 | AF96: =AD96-AE96 -> 0
AD97: =SUM(G97:AC97) -> 0 | AE97: =SUM(D97:F97) -> 0 | AF97: =AD97-AE97 -> 0
AD98: =SUM(G98:AC98) -> 0 | AE98: =SUM(D98:F98) -> 0 | AF98: =AD98-AE98 -> 0
AD99: =SUM(G99:AC99) -> 0 | AE99: =SUM(D99:F99) -> 0 | AF99: =AD99-AE99 -> 0
AD100: =SUM(G100:AC100) -> 0 | AE100: =SUM(D100:F100) -> 0 | AF100: =AD100-AE100 -> 0
AD101: =SUM(G101:AC101) -> 0 | AE101: =SUM(D101:F101) -> 0 | AF101: =AD101-AE101 -> 0
AD102: =SUM(G102:AC102) -> 0 | AE102: =SUM(D102:F102) -> 0 | AF102: =AD102-AE102 -> 0
AD103: =SUM(G103:AC103) -> 0 | AE103: =SUM(D103:F103) -> 0 | AF103: =AD103-AE103 -> 0
AD104: =SUM(G104:AC104) -> 0 | AE104: =SUM(D104:F104) -> 0 | AF104: =AD104-AE104 -> 0
AD105: =SUM(G105:AC105) -> 0 | AE105: =SUM(D105:F105) -> 0 | AF105: =AD105-AE105 -> 0
... AD165: =SUM(G165:AC165) -> 0 | AE165: =SUM(D165:F165) -> 0 | AF165: =AD165-AE165 -> 0
AD166: =SUM(G166:AC166) -> 0 | AE166: =SUM(D166:F166) -> 0 | AF166: =AD166-AE166 -> 0 | AG166: =IF(AF166=0,0,"ERROR HERE") -> 0 | AH166: =IF(OR(ISERROR(+H166/($D166+$E166-$G166)*$G166+H166),LEFT(F166,1)="x"),0,+H166/($D166+$E166-$G166)*$G166+H166) -> 0 | AI166: =IF(OR(ISERROR(+I166/($D166+$E166-$G166)*$G166+I166),LEFT(G166,1)="x"),0,+I166/($D166+$E166-$G166)*$G166+I166) -> 0 | AJ166: =IF(OR(ISERROR(+J166/($D166+$E166-$G166)*$G166+J166),LEFT(H166,1)="x"),0,+J166/($D166+$E166-$G166)*$G166+J166) -> 0 | AK166: =IF(OR(ISERROR(+K166/($D166+$E166-$G166)*$G166+K166),LEFT(I166,1)="x"),0,+K166/($D166+$E166-$G166)*$G166+K166) -> 0 | AL166: =IF(OR(ISERROR(+L166/($D166+$E166-$G166)*$G166+L166),LEFT(J166,1)="x"),0,+L166/($D166+$E166-$G166)*$G166+L166) -> 0 | AM166: =IF(OR(ISERROR(+M166/($D166+$E166-$G166)*$G166+M166),LEFT(K166,1)="x"),0,+M166/($D166+$E166-$G166)*$G166+M166) -> 0 | AN166: =IF(OR(ISERROR(+N166/($D166+$E166-$G166)*$G166+N166),LEFT(L166,1)="x"),0,+N166/($D166+$E166-$G166)*$G166+N166) -> 0 | AO166: =IF(OR(ISERROR(+O166/($D166+$E166-$G166)*$G166+O166),LEFT(M166,1)="x"),0,+O166/($D166+$E166-$G166)*$G166+O166) -> 0 | ... BB166: =IF(OR(ISERROR(+AB166/($D166+$E166-$G166)*$G166+AB166),LEFT(Z166,1)="x"),0,+AB166/($D166+$E166-$G166)*$G166+AB166) -> 0 | BC166: =IF(OR(ISERROR(+#REF!/($D166+$E166-$G166)*$G166+#REF!),LEFT(AA166,1)="x"),0,+#REF!/($D166+$E166-$G166)*$G166+#REF!) -> 0 | BD166: =IF(OR(ISERROR(+#REF!/($D166+$E166-$G166)*$G166+#REF!),LEFT(AB166,1)="x"),0,+#REF!/($D166+$E166-$G166)*$G166+#REF!) -> 0 | BE166: =IF(OR(ISERROR(+AC166/($D166+$E166-$G166)*$G166+AC166),LEFT(#REF!,1)="x"),0,+AC166/($D166+$E166-$G166)*$G166+AC166) -> #REF!
AD167: =SUM(G167:AC167) -> 0 | AE167: =SUM(D167:F167) -> 0 | AF167: =AD167-AE167 -> 0
AD168: =SUM(G168:AC168) -> 0 | AE168: =SUM(D168:F168) -> 0 | AF168: =AD168-AE168 -> 0 | AG168: =IF(AF168=0,0,"ERROR HERE") -> 0 | AH168: =IF(OR(ISERROR(+H168/($D168+$E168-$G168)*$G168+H168),LEFT(F168,1)="x"),0,+H168/($D168+$E168-$G168)*$G168+H168) -> 0 | AI168: =IF(OR(ISERROR(+I168/($D168+$E168-$G168)*$G168+I168),LEFT(G168,1)="x"),0,+I168/($D168+$E168-$G168)*$G168+I168) -> 0 | AJ168: =IF(OR(ISERROR(+J168/($D168+$E168-$G168)*$G168+J168),LEFT(H168,1)="x"),0,+J168/($D168+$E168-$G168)*$G168+J168) -> 0 | AK168: =IF(OR(ISERROR(+K168/($D168+$E168-$G168)*$G168+K168),LEFT(I168,1)="x"),0,+K168/($D168+$E168-$G168)*$G168+K168) -> 0 | AL168: =IF(OR(ISERROR(+L168/($D168+$E168-$G168)*$G168+L168),LEFT(J168,1)="x"),0,+L168/($D168+$E168-$G168)*$G168+L168) -> 0 | AM168: =IF(OR(ISERROR(+M168/($D168+$E168-$G168)*$G168+M168),LEFT(K168,1)="x"),0,+M168/($D168+$E168-$G168)*$G168+M168) -> 0 | AN168: =IF(OR(ISERROR(+N168/($D168+$E168-$G168)*$G168+N168),LEFT(L168,1)="x"),0,+N168/($D168+$E168-$G168)*$G168+N168) -> 0 | AO168: =IF(OR(ISERROR(+O168/($D168+$E168-$G168)*$G168+O168),LEFT(M168,1)="x"),0,+O168/($D168+$E168-$G168)*$G168+O168) -> 0 | ... BB168: =IF(OR(ISERROR(+AB168/($D168+$E168-$G168)*$G168+AB168),LEFT(Z168,1)="x"),0,+AB168/($D168+$E168-$G168)*$G168+AB168) -> 0 | BC168: =IF(OR(ISERROR(+#REF!/($D168+$E168-$G168)*$G168+#REF!),LEFT(AA168,1)="x"),0,+#REF!/($D168+$E168-$G168)*$G168+#REF!) -> 0 | BD168: =IF(OR(ISERROR(+#REF!/($D168+$E168-$G168)*$G168+#REF!),LEFT(AB168,1)="x"),0,+#REF!/($D168+$E168-$G168)*$G168+#REF!) -> 0 | BE168: =IF(OR(ISERROR(+AC168/($D168+$E168-$G168)*$G168+AC168),LEFT(#REF!,1)="x"),0,+AC168/($D168+$E168-$G168)*$G168+AC168) -> #REF!
AD169: =SUM(G169:AC169) -> 0 | AE169: =SUM(D169:F169) -> 0 | AF169: =AD169-AE169 -> 0 | AG169: =IF(AF169=0,0,"ERROR HERE") -> 0 | AH169: =IF(OR(ISERROR(+H169/($D169+$E169-$G169)*$G169+H169),LEFT(F169,1)="x"),0,+H169/($D169+$E169-$G169)*$G169+H169) -> 0 | AI169: =IF(OR(ISERROR(+I169/($D169+$E169-$G169)*$G169+I169),LEFT(G169,1)="x"),0,+I169/($D169+$E169-$G169)*$G169+I169) -> 0 | AJ169: =IF(OR(ISERROR(+J169/($D169+$E169-$G169)*$G169+J169),LEFT(H169,1)="x"),0,+J169/($D169+$E169-$G169)*$G169+J169) -> 0 | AK169: =IF(OR(ISERROR(+K169/($D169+$E169-$G169)*$G169+K169),LEFT(I169,1)="x"),0,+K169/($D169+$E169-$G169)*$G169+K169) -> 0 | AL169: =IF(OR(ISERROR(+L169/($D169+$E169-$G169)*$G169+L169),LEFT(J169,1)="x"),0,+L169/($D169+$E169-$G169)*$G169+L169) -> 0 | AM169: =IF(OR(ISERROR(+M169/($D169+$E169-$G169)*$G169+M169),LEFT(K169,1)="x"),0,+M169/($D169+$E169-$G169)*$G169+M169) -> 0 | AN169: =IF(OR(ISERROR(+N169/($D169+$E169-$G169)*$G169+N169),LEFT(L169,1)="x"),0,+N169/($D169+$E169-$G169)*$G169+N169) -> 0 | AO169: =IF(OR(ISERROR(+O169/($D169+$E169-$G169)*$G169+O169),LEFT(M169,1)="x"),0,+O169/($D169+$E169-$G169)*$G169+O169) -> 0 | ... BB169: =IF(OR(ISERROR(+AB169/($D169+$E169-$G169)*$G169+AB169),LEFT(Z169,1)="x"),0,+AB169/($D169+$E169-$G169)*$G169+AB169) -> 0 | BC169: =IF(OR(ISERROR(+#REF!/($D169+$E169-$G169)*$G169+#REF!),LEFT(AA169,1)="x"),0,+#REF!/($D169+$E169-$G169)*$G169+#REF!) -> 0 | BD169: =IF(OR(ISERROR(+#REF!/($D169+$E169-$G169)*$G169+#REF!),LEFT(AB169,1)="x"),0,+#REF!/($D169+$E169-$G169)*$G169+#REF!) -> 0 | BE169: =IF(OR(ISERROR(+AC169/($D169+$E169-$G169)*$G169+AC169),LEFT(#REF!,1)="x"),0,+AC169/($D169+$E169-$G169)*$G169+AC169) -> #REF!
AD170: =SUM(G170:AC170) -> 0 | AE170: =SUM(D170:F170) -> 0 | AF170: =AD170-AE170 -> 0 | AG170: =IF(AF170=0,0,"ERROR HERE") -> 0 | AH170: =IF(OR(ISERROR(+H170/($D170+$E170-$G170)*$G170+H170),LEFT(F170,1)="x"),0,+H170/($D170+$E170-$G170)*$G170+H170) -> 0 | AI170: =IF(OR(ISERROR(+I170/($D170+$E170-$G170)*$G170+I170),LEFT(G170,1)="x"),0,+I170/($D170+$E170-$G170)*$G170+I170) -> 0 | AJ170: =IF(OR(ISERROR(+J170/($D170+$E170-$G170)*$G170+J170),LEFT(H170,1)="x"),0,+J170/($D170+$E170-$G170)*$G170+J170) -> 0 | AK170: =IF(OR(ISERROR(+K170/($D170+$E170-$G170)*$G170+K170),LEFT(I170,1)="x"),0,+K170/($D170+$E170-$G170)*$G170+K170) -> 0 | AL170: =IF(OR(ISERROR(+L170/($D170+$E170-$G170)*$G170+L170),LEFT(J170,1)="x"),0,+L170/($D170+$E170-$G170)*$G170+L170) -> 0 | AM170: =IF(OR(ISERROR(+M170/($D170+$E170-$G170)*$G170+M170),LEFT(K170,1)="x"),0,+M170/($D170+$E170-$G170)*$G170+M170) -> 0 | AN170: =IF(OR(ISERROR(+N170/($D170+$E170-$G170)*$G170+N170),LEFT(L170,1)="x"),0,+N170/($D170+$E170-$G170)*$G170+N170) -> 0 | AO170: =IF(OR(ISERROR(+O170/($D170+$E170-$G170)*$G170+O170),LEFT(M170,1)="x"),0,+O170/($D170+$E170-$G170)*$G170+O170) -> 0 | ... BB170: =IF(OR(ISERROR(+AB170/($D170+$E170-$G170)*$G170+AB170),LEFT(Z170,1)="x"),0,+AB170/($D170+$E170-$G170)*$G170+AB170) -> 0 | BC170: =IF(OR(ISERROR(+#REF!/($D170+$E170-$G170)*$G170+#REF!),LEFT(AA170,1)="x"),0,+#REF!/($D170+$E170-$G170)*$G170+#REF!) -> 0 | BD170: =IF(OR(ISERROR(+#REF!/($D170+$E170-$G170)*$G170+#REF!),LEFT(AB170,1)="x"),0,+#REF!/($D170+$E170-$G170)*$G170+#REF!) -> 0 | BE170: =IF(OR(ISERROR(+AC170/($D170+$E170-$G170)*$G170+AC170),LEFT(#REF!,1)="x"),0,+AC170/($D170+$E170-$G170)*$G170+AC170) -> #REF!
AD171: =SUM(G171:AC171) -> 0 | AE171: =SUM(D171:F171) -> 0 | AF171: =AD171-AE171 -> 0 | AG171: =IF(AF171=0,0,"ERROR HERE") -> 0 | AH171: =IF(OR(ISERROR(+H171/($D171+$E171-$G171)*$G171+H171),LEFT(F171,1)="x"),0,+H171/($D171+$E171-$G171)*$G171+H171) -> 0 | AI171: =IF(OR(ISERROR(+I171/($D171+$E171-$G171)*$G171+I171),LEFT(G171,1)="x"),0,+I171/($D171+$E171-$G171)*$G171+I171) -> 0 | AJ171: =IF(OR(ISERROR(+J171/($D171+$E171-$G171)*$G171+J171),LEFT(H171,1)="x"),0,+J171/($D171+$E171-$G171)*$G171+J171) -> 0 | AK171: =IF(OR(ISERROR(+K171/($D171+$E171-$G171)*$G171+K171),LEFT(I171,1)="x"),0,+K171/($D171+$E171-$G171)*$G171+K171) -> 0 | AL171: =IF(OR(ISERROR(+L171/($D171+$E171-$G171)*$G171+L171),LEFT(J171,1)="x"),0,+L171/($D171+$E171-$G171)*$G171+L171) -> 0 | AM171: =IF(OR(ISERROR(+M171/($D171+$E171-$G171)*$G171+M171),LEFT(K171,1)="x"),0,+M171/($D171+$E171-$G171)*$G171+M171) -> 0 | AN171: =IF(OR(ISERROR(+N171/($D171+$E171-$G171)*$G171+N171),LEFT(L171,1)="x"),0,+N171/($D171+$E171-$G171)*$G171+N171) -> 0 | AO171: =IF(OR(ISERROR(+O171/($D171+$E171-$G171)*$G171+O171),LEFT(M171,1)="x"),0,+O171/($D171+$E171-$G171)*$G171+O171) -> 0 | ... BB171: =IF(OR(ISERROR(+AB171/($D171+$E171-$G171)*$G171+AB171),LEFT(Z171,1)="x"),0,+AB171/($D171+$E171-$G171)*$G171+AB171) -> 0 | BC171: =IF(OR(ISERROR(+#REF!/($D171+$E171-$G171)*$G171+#REF!),LEFT(AA171,1)="x"),0,+#REF!/($D171+$E171-$G171)*$G171+#REF!) -> 0 | BD171: =IF(OR(ISERROR(+#REF!/($D171+$E171-$G171)*$G171+#REF!),LEFT(AB171,1)="x"),0,+#REF!/($D171+$E171-$G171)*$G171+#REF!) -> 0 | BE171: =IF(OR(ISERROR(+AC171/($D171+$E171-$G171)*$G171+AC171),LEFT(#REF!,1)="x"),0,+AC171/($D171+$E171-$G171)*$G171+AC171) -> #REF!
AD172: =SUM(G172:AC172) -> 0 | AE172: =SUM(D172:F172) -> 0 | AF172: =AD172-AE172 -> 0 | AG172: =IF(AF172=0,0,"ERROR HERE") -> 0 | AH172: =IF(OR(ISERROR(+H172/($D172+$E172-$G172)*$G172+H172),LEFT(F172,1)="x"),0,+H172/($D172+$E172-$G172)*$G172+H172) -> 0 | AI172: =IF(OR(ISERROR(+I172/($D172+$E172-$G172)*$G172+I172),LEFT(G172,1)="x"),0,+I172/($D172+$E172-$G172)*$G172+I172) -> 0 | AJ172: =IF(OR(ISERROR(+J172/($D172+$E172-$G172)*$G172+J172),LEFT(H172,1)="x"),0,+J172/($D172+$E172-$G172)*$G172+J172) -> 0 | AK172: =IF(OR(ISERROR(+K172/($D172+$E172-$G172)*$G172+K172),LEFT(I172,1)="x"),0,+K172/($D172+$E172-$G172)*$G172+K172) -> 0 | AL172: =IF(OR(ISERROR(+L172/($D172+$E172-$G172)*$G172+L172),LEFT(J172,1)="x"),0,+L172/($D172+$E172-$G172)*$G172+L172) -> 0 | AM172: =IF(OR(ISERROR(+M172/($D172+$E172-$G172)*$G172+M172),LEFT(K172,1)="x"),0,+M172/($D172+$E172-$G172)*$G172+M172) -> 0 | AN172: =IF(OR(ISERROR(+N172/($D172+$E172-$G172)*$G172+N172),LEFT(L172,1)="x"),0,+N172/($D172+$E172-$G172)*$G172+N172) -> 0 | AO172: =IF(OR(ISERROR(+O172/($D172+$E172-$G172)*$G172+O172),LEFT(M172,1)="x"),0,+O172/($D172+$E172-$G172)*$G172+O172) -> 0 | ... BB172: =IF(OR(ISERROR(+AB172/($D172+$E172-$G172)*$G172+AB172),LEFT(Z172,1)="x"),0,+AB172/($D172+$E172-$G172)*$G172+AB172) -> 0 | BC172: =IF(OR(ISERROR(+#REF!/($D172+$E172-$G172)*$G172+#REF!),LEFT(AA172,1)="x"),0,+#REF!/($D172+$E172-$G172)*$G172+#REF!) -> 0 | BD172: =IF(OR(ISERROR(+#REF!/($D172+$E172-$G172)*$G172+#REF!),LEFT(AB172,1)="x"),0,+#REF!/($D172+$E172-$G172)*$G172+#REF!) -> 0 | BE172: =IF(OR(ISERROR(+AC172/($D172+$E172-$G172)*$G172+AC172),LEFT(#REF!,1)="x"),0,+AC172/($D172+$E172-$G172)*$G172+AC172) -> #REF!
AD173: =SUM(G173:AC173) -> 0 | AE173: =SUM(D173:F173) -> 0 | AF173: =AD173-AE173 -> 0 | AG173: =IF(AF173=0,0,"ERROR HERE") -> 0 | AH173: =IF(OR(ISERROR(+H173/($D173+$E173-$G173)*$G173+H173),LEFT(F173,1)="x"),0,+H173/($D173+$E173-$G173)*$G173+H173) -> 0 | AI173: =IF(OR(ISERROR(+I173/($D173+$E173-$G173)*$G173+I173),LEFT(G173,1)="x"),0,+I173/($D173+$E173-$G173)*$G173+I173) -> 0 | AJ173: =IF(OR(ISERROR(+J173/($D173+$E173-$G173)*$G173+J173),LEFT(H173,1)="x"),0,+J173/($D173+$E173-$G173)*$G173+J173) -> 0 | AK173: =IF(OR(ISERROR(+K173/($D173+$E173-$G173)*$G173+K173),LEFT(I173,1)="x"),0,+K173/($D173+$E173-$G173)*$G173+K173) -> 0 | AL173: =IF(OR(ISERROR(+L173/($D173+$E173-$G173)*$G173+L173),LEFT(J173,1)="x"),0,+L173/($D173+$E173-$G173)*$G173+L173) -> 0 | AM173: =IF(OR(ISERROR(+M173/($D173+$E173-$G173)*$G173+M173),LEFT(K173,1)="x"),0,+M173/($D173+$E173-$G173)*$G173+M173) -> 0 | AN173: =IF(OR(ISERROR(+N173/($D173+$E173-$G173)*$G173+N173),LEFT(L173,1)="x"),0,+N173/($D173+$E173-$G173)*$G173+N173) -> 0 | AO173: =IF(OR(ISERROR(+O173/($D173+$E173-$G173)*$G173+O173),LEFT(M173,1)="x"),0,+O173/($D173+$E173-$G173)*$G173+O173) -> 0 | ... BB173: =IF(OR(ISERROR(+AB173/($D173+$E173-$G173)*$G173+AB173),LEFT(Z173,1)="x"),0,+AB173/($D173+$E173-$G173)*$G173+AB173) -> 0 | BC173: =IF(OR(ISERROR(+#REF!/($D173+$E173-$G173)*$G173+#REF!),LEFT(AA173,1)="x"),0,+#REF!/($D173+$E173-$G173)*$G173+#REF!) -> 0 | BD173: =IF(OR(ISERROR(+#REF!/($D173+$E173-$G173)*$G173+#REF!),LEFT(AB173,1)="x"),0,+#REF!/($D173+$E173-$G173)*$G173+#REF!) -> 0 | BE173: =IF(OR(ISERROR(+AC173/($D173+$E173-$G173)*$G173+AC173),LEFT(#REF!,1)="x"),0,+AC173/($D173+$E173-$G173)*$G173+AC173) -> #REF!
AD174: =SUM(G174:AC174) -> 0 | AE174: =SUM(D174:F174) -> 0 | AF174: =AD174-AE174 -> 0
AD175: =SUM(G175:AC175) -> 0 | AE175: =SUM(D175:F175) -> 0 | AF175: =AD175-AE175 -> 0
AD176: =SUM(G176:AC176) -> 0 | AE176: =SUM(D176:F176) -> 0 | AF176: =AD176-AE176 -> 0
AD177: =SUM(G177:AC177) -> 0 | AE177: =SUM(D177:F177) -> 0 | AF177: =AD177-AE177 -> 0
AD178: =SUM(G178:AC178) -> 0 | AE178: =SUM(D178:F178) -> 0 | AF178: =AD178-AE178 -> 0
AD179: =SUM(G179:AC179) -> 0 | AE179: =SUM(D179:F179) -> 0 | AF179: =AD179-AE179 -> 0
AD180: =SUM(G180:AC180) -> 0 | AE180: =SUM(D180:F180) -> 0 | AF180: =AD180-AE180 -> 0
AD181: =SUM(G181:AC181) -> 0 | AE181: =SUM(D181:F181) -> 0 | AF181: =AD181-AE181 -> 0 | AG181: =IF(AF181=0,0,"ERROR HERE") -> 0 | AH181: =IF(OR(ISERROR(+H181/($D181+$E181-$G181)*$G181+H181),LEFT(F181,1)="x"),0,+H181/($D181+$E181-$G181)*$G181+H181) -> 0 | AI181: =IF(OR(ISERROR(+I181/($D181+$E181-$G181)*$G181+I181),LEFT(G181,1)="x"),0,+I181/($D181+$E181-$G181)*$G181+I181) -> 0 | AJ181: =IF(OR(ISERROR(+J181/($D181+$E181-$G181)*$G181+J181),LEFT(H181,1)="x"),0,+J181/($D181+$E181-$G181)*$G181+J181) -> 0 | AK181: =IF(OR(ISERROR(+K181/($D181+$E181-$G181)*$G181+K181),LEFT(I181,1)="x"),0,+K181/($D181+$E181-$G181)*$G181+K181) -> 0 | AL181: =IF(OR(ISERROR(+L181/($D181+$E181-$G181)*$G181+L181),LEFT(J181,1)="x"),0,+L181/($D181+$E181-$G181)*$G181+L181) -> 0 | AM181: =IF(OR(ISERROR(+M181/($D181+$E181-$G181)*$G181+M181),LEFT(K181,1)="x"),0,+M181/($D181+$E181-$G181)*$G181+M181) -> 0 | AN181: =IF(OR(ISERROR(+N181/($D181+$E181-$G181)*$G181+N181),LEFT(L181,1)="x"),0,+N181/($D181+$E181-$G181)*$G181+N181) -> 0 | AO181: =IF(OR(ISERROR(+O181/($D181+$E181-$G181)*$G181+O181),LEFT(M181,1)="x"),0,+O181/($D181+$E181-$G181)*$G181+O181) -> 0 | ... BB181: =IF(OR(ISERROR(+AB181/($D181+$E181-$G181)*$G181+AB181),LEFT(Z181,1)="x"),0,+AB181/($D181+$E181-$G181)*$G181+AB181) -> 0 | BC181: =IF(OR(ISERROR(+#REF!/($D181+$E181-$G181)*$G181+#REF!),LEFT(AA181,1)="x"),0,+#REF!/($D181+$E181-$G181)*$G181+#REF!) -> 0 | BD181: =IF(OR(ISERROR(+#REF!/($D181+$E181-$G181)*$G181+#REF!),LEFT(AB181,1)="x"),0,+#REF!/($D181+$E181-$G181)*$G181+#REF!) -> 0 | BE181: =IF(OR(ISERROR(+AC181/($D181+$E181-$G181)*$G181+AC181),LEFT(#REF!,1)="x"),0,+AC181/($D181+$E181-$G181)*$G181+AC181) -> #REF!
AD182: =SUM(G182:AC182) -> 0 | AE182: =SUM(D182:F182) -> 0 | AF182: =AD182-AE182 -> 0 | AG182: =IF(AF182=0,0,"ERROR HERE") -> 0 | AH182: =IF(OR(ISERROR(+H182/($D182+$E182-$G182)*$G182+H182),LEFT(F182,1)="x"),0,+H182/($D182+$E182-$G182)*$G182+H182) -> 0 | AI182: =IF(OR(ISERROR(+I182/($D182+$E182-$G182)*$G182+I182),LEFT(G182,1)="x"),0,+I182/($D182+$E182-$G182)*$G182+I182) -> 0 | AJ182: =IF(OR(ISERROR(+J182/($D182+$E182-$G182)*$G182+J182),LEFT(H182,1)="x"),0,+J182/($D182+$E182-$G182)*$G182+J182) -> 0 | AK182: =IF(OR(ISERROR(+K182/($D182+$E182-$G182)*$G182+K182),LEFT(I182,1)="x"),0,+K182/($D182+$E182-$G182)*$G182+K182) -> 0 | AL182: =IF(OR(ISERROR(+L182/($D182+$E182-$G182)*$G182+L182),LEFT(J182,1)="x"),0,+L182/($D182+$E182-$G182)*$G182+L182) -> 0 | AM182: =IF(OR(ISERROR(+M182/($D182+$E182-$G182)*$G182+M182),LEFT(K182,1)="x"),0,+M182/($D182+$E182-$G182)*$G182+M182) -> 0 | AN182: =IF(OR(ISERROR(+N182/($D182+$E182-$G182)*$G182+N182),LEFT(L182,1)="x"),0,+N182/($D182+$E182-$G182)*$G182+N182) -> 0 | AO182: =IF(OR(ISERROR(+O182/($D182+$E182-$G182)*$G182+O182),LEFT(M182,1)="x"),0,+O182/($D182+$E182-$G182)*$G182+O182) -> 0 | ... BB182: =IF(OR(ISERROR(+AB182/($D182+$E182-$G182)*$G182+AB182),LEFT(Z182,1)="x"),0,+AB182/($D182+$E182-$G182)*$G182+AB182) -> 0 | BC182: =IF(OR(ISERROR(+#REF!/($D182+$E182-$G182)*$G182+#REF!),LEFT(AA182,1)="x"),0,+#REF!/($D182+$E182-$G182)*$G182+#REF!) -> 0 | BD182: =IF(OR(ISERROR(+#REF!/($D182+$E182-$G182)*$G182+#REF!),LEFT(AB182,1)="x"),0,+#REF!/($D182+$E182-$G182)*$G182+#REF!) -> 0 | BE182: =IF(OR(ISERROR(+AC182/($D182+$E182-$G182)*$G182+AC182),LEFT(#REF!,1)="x"),0,+AC182/($D182+$E182-$G182)*$G182+AC182) -> #REF!
AD183: =SUM(G183:AC183) -> 0 | AE183: =SUM(D183:F183) -> 0 | AF183: =AD183-AE183 -> 0 | AG183: =IF(AF183=0,0,"ERROR HERE") -> 0 | AH183: =IF(OR(ISERROR(+H183/($D183+$E183-$G183)*$G183+H183),LEFT(F183,1)="x"),0,+H183/($D183+$E183-$G183)*$G183+H183) -> 0 | AI183: =IF(OR(ISERROR(+I183/($D183+$E183-$G183)*$G183+I183),LEFT(G183,1)="x"),0,+I183/($D183+$E183-$G183)*$G183+I183) -> 0 | AJ183: =IF(OR(ISERROR(+J183/($D183+$E183-$G183)*$G183+J183),LEFT(H183,1)="x"),0,+J183/($D183+$E183-$G183)*$G183+J183) -> 0 | AK183: =IF(OR(ISERROR(+K183/($D183+$E183-$G183)*$G183+K183),LEFT(I183,1)="x"),0,+K183/($D183+$E183-$G183)*$G183+K183) -> 0 | AL183: =IF(OR(ISERROR(+L183/($D183+$E183-$G183)*$G183+L183),LEFT(J183,1)="x"),0,+L183/($D183+$E183-$G183)*$G183+L183) -> 0 | AM183: =IF(OR(ISERROR(+M183/($D183+$E183-$G183)*$G183+M183),LEFT(K183,1)="x"),0,+M183/($D183+$E183-$G183)*$G183+M183) -> 0 | AN183: =IF(OR(ISERROR(+N183/($D183+$E183-$G183)*$G183+N183),LEFT(L183,1)="x"),0,+N183/($D183+$E183-$G183)*$G183+N183) -> 0 | AO183: =IF(OR(ISERROR(+O183/($D183+$E183-$G183)*$G183+O183),LEFT(M183,1)="x"),0,+O183/($D183+$E183-$G183)*$G183+O183) -> 0 | ... BB183: =IF(OR(ISERROR(+AB183/($D183+$E183-$G183)*$G183+AB183),LEFT(Z183,1)="x"),0,+AB183/($D183+$E183-$G183)*$G183+AB183) -> 0 | BC183: =IF(OR(ISERROR(+#REF!/($D183+$E183-$G183)*$G183+#REF!),LEFT(AA183,1)="x"),0,+#REF!/($D183+$E183-$G183)*$G183+#REF!) -> 0 | BD183: =IF(OR(ISERROR(+#REF!/($D183+$E183-$G183)*$G183+#REF!),LEFT(AB183,1)="x"),0,+#REF!/($D183+$E183-$G183)*$G183+#REF!) -> 0 | BE183: =IF(OR(ISERROR(+AC183/($D183+$E183-$G183)*$G183+AC183),LEFT(#REF!,1)="x"),0,+AC183/($D183+$E183-$G183)*$G183+AC183) -> #REF!
...

Sheet Mar 18
A1: 0
A2: ='Nov 17'!A2 -> Design-spectrum Limited
A4: Month | C4: ='Feb 18'!C4+31 -> 43164
A7: Sales Invoices | I7: Bankings - Receipts
A9: Does this months income fall within IR35? (Y/N/both) | E9: ='Feb 18'!E9 -> n | F9: =IF(E9="Both","enter sales invoices manually at row 30 onwards",0) -> 0
A11: Is the Company VAT registered (Y/N) | E11: ='Feb 18'!E11 -> y
A12: VAT Flat rate scheme percentage | E12: ='Feb 18'!E12 -> 0.165
A13: (leave blank or zero if not using flat rate scheme) | M13: Interest | O13: Transfers from | P13: Interest
L14: Sales Invoice | M14: Received on | O14: Deposit | P14: Received on
A15: Date | B15: Details | C15: Sales Invoice No | D15: IR35 | E15: Non IR35 | F15: Gross | G15: VAT | I15: Date | J15: Details | K15: Sales Invoice no | L15: Amount £ | M15: Current Account | N15: Other bankings | O15: Account | P15: Deposit Account
C16: Balance b/f | D16: ='Feb 18'!D54 -> 0 | E16: ='Feb 18'!E54 -> 32450 | F16: ='Feb 18'!F54 -> 38940 | G16: ='Feb 18'!G54 -> 6490 | J16: Balance b/f | L16: ='Feb 18'!L54 -> 62040 | M16: ='Feb 18'!M54 -> 66.53 | N16: ='Feb 18'!N54 -> 0 | O16: ='Feb 18'!O54 -> 50488.86 | P16: ='Feb 18'!P54 -> -58.58
B17: Invoice 2Feb-2Mar2018 | D17: =IF(E$9="y",F17-G17,0) -> 0 | E17: =IF(E$9="n",F17-G17,0) -> 11000 | F17: 13200 | G17: =IF(($E$11="n"),0,IF((LEFT(C17,1)="v"),F17,IF((LEFT(C17,1)="z"),0,F17*1/6))) -> 2200 | I17: 43182 | J17: R S C S LTD | L17: 13200
D18: =IF(E$9="y",F18-G18,0) -> 0 | E18: =IF(E$9="n",F18-G18,0) -> 0 | G18: =IF(($E$11="n"),0,IF((LEFT(C18,1)="v"),F18,IF((LEFT(C18,1)="z"),0,F18*1/6))) -> 0 | P18: 2.26
D19: =IF(E$9="y",F19-G19,0) -> 0 | E19: =IF(E$9="n",F19-G19,0) -> 0 | G19: =IF(($E$11="n"),0,IF((LEFT(C19,1)="v"),F19,IF((LEFT(C19,1)="z"),0,F19*1/6))) -> 0
D20: =IF(E$9="y",F20-G20,0) -> 0 | E20: =IF(E$9="n",F20-G20,0) -> 0 | G20: =IF(($E$11="n"),0,IF((LEFT(C20,1)="v"),F20,IF((LEFT(C20,1)="z"),0,F20*1/6))) -> 0
D21: =IF(E$9="y",F21-G21,0) -> 0 | E21: =IF(E$9="n",F21-G21,0) -> 0 | G21: =IF(($E$11="n"),0,IF((LEFT(C21,1)="v"),F21,IF((LEFT(C21,1)="z"),0,F21*1/6))) -> 0
D22: =IF(E$9="y",F22-G22,0) -> 0 | E22: =IF(E$9="n",F22-G22,0) -> 0 | G22: =IF(($E$11="n"),0,IF((LEFT(C22,1)="v"),F22,IF((LEFT(C22,1)="z"),0,F22*1/6))) -> 0
D23: =IF(E$9="y",F23-G23,0) -> 0 | E23: =IF(E$9="n",F23-G23,0) -> 0 | G23: =IF(($E$11="n"),0,IF((LEFT(C23,1)="v"),F23,IF((LEFT(C23,1)="z"),0,F23*1/6))) -> 0
D24: =IF(E$9="y",F24-G24,0) -> 0 | E24: =IF(E$9="n",F24-G24,0) -> 0 | G24: =IF(($E$11="n"),0,IF((LEFT(C24,1)="v"),F24,IF((LEFT(C24,1)="z"),0,F24*1/6))) -> 0
D25: =IF(E$9="y",F25-G25,0) -> 0 | E25: =IF(E$9="n",F25-G25,0) -> 0 | G25: =IF(($E$11="n"),0,IF((LEFT(C25,1)="v"),F25,IF((LEFT(C25,1)="z"),0,F25*1/6))) -> 0
D26: =IF(E$9="y",F26-G26,0) -> 0 | E26: =IF(E$9="n",F26-G26,0) -> 0 | G26: =IF(($E$11="n"),0,IF((LEFT(C26,1)="v"),F26,IF((LEFT(C26,1)="z"),0,F26*1/6))) -> 0
D27: =IF(E$9="y",F27-G27,0) -> 0 | E27: =IF(E$9="n",F27-G27,0) -> 0 | G27: =IF(($E$11="n"),0,IF((LEFT(C27,1)="v"),F27,IF((LEFT(C27,1)="z"),0,F27*1/6))) -> 0
D28: =IF(E$9="y",F28-G28,0) -> 0 | E28: =IF(E$9="n",F28-G28,0) -> 0 | G28: =IF(($E$11="n"),0,IF((LEFT(C28,1)="v"),F28,IF((LEFT(C28,1)="z"),0,F28*1/6))) -> 0
D29: =IF(E$9="y",F29-G29,0) -> 0 | E29: =IF(E$9="n",F29-G29,0) -> 0 | G29: =IF(($E$11="n"),0,IF((LEFT(C29,1)="v"),F29,IF((LEFT(C29,1)="z"),0,F29*1/6))) -> 0
D30: =IF(E$9="y",F30-G30,0) -> 0 | E30: =IF(E$9="n",F30-G30,0) -> 0 | G30: =IF(($E$11="n"),0,IF((LEFT(C30,1)="v"),F30,IF((LEFT(C30,1)="z"),0,F30*1/6))) -> 0
... D40: =IF(E$9="y",F40-G40,0) -> 0 | E40: =IF(E$9="n",F40-G40,0) -> 0 | G40: =IF(($E$11="n"),0,IF((LEFT(C40,1)="v"),F40,IF((LEFT(C40,1)="z"),0,F40*1/6))) -> 0
B41: =IF(E9="Both","Enter manual values here",0) -> 0 | D41: =IF(E$9="y",F41-G41,0) -> 0 | E41: =IF(E$9="n",F41-G41,0) -> 0 | G41: =IF(($E$11="n"),0,IF((LEFT(C41,1)="v"),F41,IF((LEFT(C41,1)="z"),0,F41*1/6))) -> 0
D42: =IF(E$9="y",F42-G42,0) -> 0 | E42: =IF(E$9="n",F42-G42,0) -> 0 | G42: =IF(($E$11="n"),0,IF((LEFT(C42,1)="v"),F42,IF((LEFT(C42,1)="z"),0,F42*1/6))) -> 0
D43: =IF(E$9="y",F43-G43,0) -> 0 | E43: =IF(E$9="n",F43-G43,0) -> 0 | G43: =IF(($E$11="n"),0,IF((LEFT(C43,1)="v"),F43,IF((LEFT(C43,1)="z"),0,F43*1/6))) -> 0
D44: =IF(E$9="y",F44-G44,0) -> 0 | E44: =IF(E$9="n",F44-G44,0) -> 0 | G44: =IF(($E$11="n"),0,IF((LEFT(C44,1)="v"),F44,IF((LEFT(C44,1)="z"),0,F44*1/6))) -> 0
D45: =IF(E$9="y",F45-G45,0) -> 0 | E45: =IF(E$9="n",F45-G45,0) -> 0 | G45: =IF(($E$11="n"),0,IF((LEFT(C45,1)="v"),F45,IF((LEFT(C45,1)="z"),0,F45*1/6))) -> 0
D46: =IF(E$9="y",F46-G46,0) -> 0 | E46: =IF(E$9="n",F46-G46,0) -> 0 | G46: =IF(($E$11="n"),0,IF((LEFT(C46,1)="v"),F46,IF((LEFT(C46,1)="z"),0,F46*1/6))) -> 0
D47: =IF(E$9="y",F47-G47,0) -> 0 | E47: =IF(E$9="n",F47-G47,0) -> 0 | G47: =IF(($E$11="n"),0,IF((LEFT(C47,1)="v"),F47,IF((LEFT(C47,1)="z"),0,F47*1/6))) -> 0
D48: =IF(E$9="y",F48-G48,0) -> 0 | E48: =IF(E$9="n",F48-G48,0) -> 0 | G48: =IF(($E$11="n"),0,IF((LEFT(C48,1)="v"),F48,IF((LEFT(C48,1)="z"),0,F48*1/6))) -> 0
D49: =IF(E$9="y",F49-G49,0) -> 0 | E49: =IF(E$9="n",F49-G49,0) -> 0 | G49: =IF(($E$11="n"),0,IF((LEFT(C49,1)="v"),F49,IF((LEFT(C49,1)="z"),0,F49*1/6))) -> 0
D50: =IF(E$9="y",F50-G50,0) -> 0 | E50: =IF(E$9="n",F50-G50,0) -> 0 | G50: =IF(($E$11="n"),0,IF((LEFT(C50,1)="v"),F50,IF((LEFT(C50,1)="z"),0,F50*1/6))) -> 0
D51: =IF(E$9="y",F51-G51,0) -> 0 | E51: =IF(E$9="n",F51-G51,0) -> 0 | G51: =IF(($E$11="n"),0,IF((LEFT(C51,1)="v"),F51,IF((LEFT(C51,1)="z"),0,F51*1/6))) -> 0
D52: =IF(E$9="y",F52-G52,0) -> 0 | E52: =IF(E$9="n",F52-G52,0) -> 0 | G52: =IF(($E$11="n"),0,IF((LEFT(C52,1)="v"),F52,IF((LEFT(C52,1)="z"),0,F52*1/6))) -> 0
A53: Total | D53: =SUM(D17:D52) -> 0 | E53: =SUM(E17:E52) -> 11000 | F53: =SUM(F17:F52) -> 13200 | G53: =SUM(G17:G52) -> 2200 | I53: Total | L53: =SUM(L17:L52) -> 13200 | M53: =SUM(M17:M52) -> 0 | N53: =SUM(N17:N52) -> 0 | O53: =SUM(O17:O52) -> 0 | P53: =SUM(P17:P52) -> 2.26
A54: C/fwd | D54: =SUM(D16:D52) -> 0 | E54: =SUM(E16:E52) -> 43450 | F54: =SUM(F16:F52) -> 52140 | G54: =SUM(G16:G52) -> 8690 | I54: C/fwd | L54: =SUM(L16:L52) -> 75240 | M54: =SUM(M16:M52) -> 66.53 | N54: =SUM(N16:N52) -> 0 | O54: =SUM(O16:O52) -> 50488.86 | P54: =SUM(P16:P52) -> -56.32
A56: IR35 Details (ignore if outside IR35): | D56: Flat Rate Scheme Details (ignore if outside FRS):
A58: Deemed Salary | C58: =IF(E9="y",G59*0.95-(SUM(H197:K197)),0) -> 0 | E58: Per List Above | F58: FRS | G58: VAT account figures
A59: Deemed Salary | C59: =IF(E9="both",G59*0.95-(SUM(H197:K197)),0) -> 0 | D59: IR35 | E59: =+D53 -> 0 | F59: =+G59-E59 -> 0 | G59: =IF(E59+E60<>0,E59/(E59+E60)*(G61-G62),0) -> 0
D60: Non IR35 | E60: =+E53 -> 11000 | F60: =+G60-E60 -> 22 | G60: =IF(E59+E60<>0,E60/(E59+E60)*(G61-G62),0) -> 11022
D61: Gross | E61: =+F53 -> 13200 | F61: =+G61-E61 -> 0 | G61: =+E61 -> 13200
A62: Total PAYE & NI Due on deemed salary | C62: =IF(E243<=0,0,IF(C4<42095,E265,E243)) -> 0 | D62: VAT | E62: =+G53 -> 2200 | F62: =+G62-E62 -> -22 | G62: =IF(E12>0,(G61)*E12,E62) -> 2178
A63: 41730 = Numerical Value of 01 April 2014
A65: Tax provision to be made
A66: (payable by 19th April 2016) | C66: =C62 -> 0
A69: Net salary available to draw | C69: =C58+C59-C66 -> 0
A70: (after all taxes, NI and allowable expenses)
A74: Expenditure
H76: Motor | I76: Travelling, | J76: Professional, Public | P76: Printing, | S76: Computer | T76: Books, | V76: Bank Charges | X76: Transfers to | Z76: Corporation | AA76: Directors
C77: Reference / | D77: Company | E77: Cash/Personal | F77: Company | H77: Expenses Or | I77: Accommodation | J77: and Employers | K77: Company | M77: PAYE & NIC | O77: Cost of | P77: Postage & | Q77: Internet & | R77: Assets | S77: Related | T77: Journals & | V77: & Interest | X77: Deposit | Y77: VAT paid to | Z77: Tax paid to | AA77: Loan | AB77: Business
A78: Date | B78: Details | C78: Cheque No | D78: Bank | E78: Expenses | F78: Credit Card | G78: VAT | H78: Mileage Claims | I78: & Subsistence | J78: Liability Insurance | K78: Pension | L78: Net salary paid | M78: paid to HMR&C | N78: Dividends | O78: Goods sold | P78: Stationery | Q78: Telephone | R78: Purchased | S78: Costs | T78: Subscriptions | U78: Accountancy | V78: Payable | W78: Use of Home | X78: Account | Y78: HMC&E | Z78: HMR&C | AA78: Account | AB78: Entertainment | AC78: Sundries | AF78: error line?
B79: Balance b/f | D79: ='Feb 18'!D198 -> 70826.99 | E79: ='Feb 18'!E198 -> 0 | F79: ='Feb 18'!F198 -> 0 | G79: ='Feb 18'!G198 -> 0 | H79: ='Feb 18'!H198 -> 900 | I79: ='Feb 18'!I198 -> 656 | J79: ='Feb 18'!J198 -> 140 | K79: ='Feb 18'!K198 -> 0 | ... AC79: ='Feb 18'!AC198 -> 0 | AG79: =IF(AF79=0,0,"ERROR HERE") -> 0 | AH79: =IF(OR(ISERROR(+H79/($D79+$E79-$G79)*$G79+H79),LEFT(F79,1)="x"),0,+H79/($D79+$E79-$G79)*$G79+H79) -> 900 | AI79: =IF(OR(ISERROR(+I79/($D79+$E79-$G79)*$G79+I79),LEFT(G79,1)="x"),0,+I79/($D79+$E79-$G79)*$G79+I79) -> 656 | AJ79: =IF(OR(ISERROR(+J79/($D79+$E79-$G79)*$G79+J79),LEFT(H79,1)="x"),0,+J79/($D79+$E79-$G79)*$G79+J79) -> 140 | AK79: =IF(OR(ISERROR(+K79/($D79+$E79-$G79)*$G79+K79),LEFT(I79,1)="x"),0,+K79/($D79+$E79-$G79)*$G79+K79) -> 0 | AL79: =IF(OR(ISERROR(+L79/($D79+$E79-$G79)*$G79+L79),LEFT(J79,1)="x"),0,+L79/($D79+$E79-$G79)*$G79+L79) -> 9120 | AM79: =IF(OR(ISERROR(+M79/($D79+$E79-$G79)*$G79+M79),LEFT(K79,1)="x"),0,+M79/($D79+$E79-$G79)*$G79+M79) -> 0 | AN79: =IF(OR(ISERROR(+N79/($D79+$E79-$G79)*$G79+N79),LEFT(L79,1)="x"),0,+N79/($D79+$E79-$G79)*$G79+N79) -> 0 | AO79: =IF(OR(ISERROR(+O79/($D79+$E79-$G79)*$G79+O79),LEFT(M79,1)="x"),0,+O79/($D79+$E79-$G79)*$G79+O79) -> 0 | ... BB79: =IF(OR(ISERROR(+AB79/($D79+$E79-$G79)*$G79+AB79),LEFT(Z79,1)="x"),0,+AB79/($D79+$E79-$G79)*$G79+AB79) -> 628 | BC79: =IF(OR(ISERROR(+#REF!/($D79+$E79-$G79)*$G79+#REF!),LEFT(AA79,1)="x"),0,+#REF!/($D79+$E79-$G79)*$G79+#REF!) -> 0 | BD79: =IF(OR(ISERROR(+AC79/($D79+$E79-$G79)*$G79+AC79),LEFT(Z79,1)="x"),0,+AC79/($D79+$E79-$G79)*$G79+AC79) -> 0
B80: Salary Director S Haldar | D80: 924 | L80: 924 | AD80: =SUM(G80:AC80) -> 924 | AE80: =SUM(D80:F80) -> 924 | AF80: =AD80-AE80 -> 0 | AH80: =IF(OR(ISERROR(+H80/($D80+$E80-$G80)*$G80+H80),LEFT(F80,1)="x"),0,+H80/($D80+$E80-$G80)*$G80+H80) -> 0 | AI80: =IF(OR(ISERROR(+I80/($D80+$E80-$G80)*$G80+I80),LEFT(G80,1)="x"),0,+I80/($D80+$E80-$G80)*$G80+I80) -> 0 | AJ80: =IF(OR(ISERROR(+J80/($D80+$E80-$G80)*$G80+J80),LEFT(H80,1)="x"),0,+J80/($D80+$E80-$G80)*$G80+J80) -> 0 | AK80: =IF(OR(ISERROR(+K80/($D80+$E80-$G80)*$G80+K80),LEFT(I80,1)="x"),0,+K80/($D80+$E80-$G80)*$G80+K80) -> 0 | AL80: =IF(OR(ISERROR(+L80/($D80+$E80-$G80)*$G80+L80),LEFT(J80,1)="x"),0,+L80/($D80+$E80-$G80)*$G80+L80) -> 924 | AM80: =IF(OR(ISERROR(+M80/($D80+$E80-$G80)*$G80+M80),LEFT(K80,1)="x"),0,+M80/($D80+$E80-$G80)*$G80+M80) -> 0 | AN80: =IF(OR(ISERROR(+N80/($D80+$E80-$G80)*$G80+N80),LEFT(L80,1)="x"),0,+N80/($D80+$E80-$G80)*$G80+N80) -> 0 | AO80: =IF(OR(ISERROR(+O80/($D80+$E80-$G80)*$G80+O80),LEFT(M80,1)="x"),0,+O80/($D80+$E80-$G80)*$G80+O80) -> 0 | ... BB80: =IF(OR(ISERROR(+AB80/($D80+$E80-$G80)*$G80+AB80),LEFT(Z80,1)="x"),0,+AB80/($D80+$E80-$G80)*$G80+AB80) -> 0 | BC80: =IF(OR(ISERROR(+#REF!/($D80+$E80-$G80)*$G80+#REF!),LEFT(AA80,1)="x"),0,+#REF!/($D80+$E80-$G80)*$G80+#REF!) -> 0 | BD80: =IF(OR(ISERROR(+AC80/($D80+$E80-$G80)*$G80+AC80),LEFT(Z80,1)="x"),0,+AC80/($D80+$E80-$G80)*$G80+AC80) -> 0
